Workbook

Sheet Instructions
A1: Amazon Ads Data Clean up & Diagnosis
A2: Brand: Auralis Naturals
A3: Scenario | B3: This data is from skincare seller - a one-month Sponsored Products 'Search Term Report' (about 3,000 rows, 26 columns). The export is messy. You need to identify where money is being wasted, what is working, and what to change first.
A4: No Amazon knowledge needed | B4: Everything you need is defined in the Glossary below.
A6: Effort | B6: About 2 hours. You will be asked to walk us through it and explain working. You may use online resources for reference and help. Do not upload the sheet to AI and ask it to solve. AI work will be easily identifiable and will result in cancellation of your candidature.
A7: Tool | B7: Microsoft Excel. Classic functions are enough (VLOOKUP/INDEX-MATCH, SUMIFS, COUNTIFS, IF, IFERROR, TRIM, LOWER, pivot tables). You may use any of them.
A9: THE TASKS (suggested time in brackets)
A10: A. Clean the data (35 min) | B10: Copy Search_Term_Report to a new sheet called 'Clean_Data' and fix the data there. Record every problem you find in 'Cleaning_Log': what the issue is, where it is, roughly how many rows, and what you did. Do not silently delete anything. If you are unsure whether to keep or remove something, decide, and write down why.
A11: B. Add calculated columns (20 min) | B11: In Clean_Data, add formula columns (not pasted values): Week No., Selling Price, Break-even ACOS (look up from Product_Master), your own CTR, CPC, ACOS, ROAS and CVR (do not trust the pre-filled ones), Profit after ads, and Row Status. Row Status: 'Profitable' if Sales > 0 and ACOS < Break-even ACOS; 'Losing' if Sales > 0 and ACOS ≥ Break-even ACOS; 'No Sales' if Sales = 0 and Spend > 0; 'No Spend' if Spend = 0; 'Cost missing' if the SKU cannot be found in Product_Master.
A12: C. Analyse (35 min) | B12: On a sheet called 'Analysis' (pivot tables are fine), show: C1. Campaign summary: Spend, Sales, Orders, ACOS, ROAS and Profit after ads per campaign. C2. The same measures by Match Type and by Placement. C3. Top 10 search terms by Spend that have ZERO orders (treat the same term typed in different cases as one term). C4. Top 10 search terms by Profit after ads. C5. Week 1 to Week 4 trend of Spend, Sales, Orders, ACOS and CVR, with one chart. C6. (Stretch) Search terms that appear in more than one campaign, with their combined Spend and Sales.
A13: D. Action_List (20 min) | B13: Apply the four rules in Seller_Notes and list every recommended action on a sheet called 'Action_List' using the headers provided in that sheet.
A14: E. Summary for the seller (10 min) | B14: On a sheet called 'Summary', write a note of no more than 150 words to a non-technical seller: answer their question about the end of the month, say what is going wrong, what you would do first, and anything you were unsure about.
A15: Optional | B15: A one-page dashboard sheet. It will not earn a pass on its own; do it only if you finish early.
A17: HOW YOU WILL BE JUDGED
A18: What we look for | B18: Care with the data (did you find and handle the problems?), correct formulas and method, correct analysis, sensible recommendations that follow the rules, a clear summary, and following instructions (sheet names, file name, deadline). Neatness matters. Being honest about what you were unsure of scores higher than guessing.
B19: This job assumes you do not know anything about Amazon Ads. So do not worry about getting everything 100% right, it’s the approach that matters.
A20: GLOSSARY
A21: Search term | B21: What the shopper actually typed into Amazon search box before seeing/clicking the ad.
A22: Impressions | B22: Number of times the ad was shown. Typically Amazon does not charge on Impressions.
A23: Clicks | B23: Number of times shoppers clicked the ad. Amazon charges every time someone clicks on your ad.
A24: CTR (click-through rate) | B24: Clicks ÷ Impressions - Higher CTR implies that consumers found your ad to be relevant.
A25: CPC (cost per click) | B25: Spend ÷ Clicks.
A26: Spend | B26: What the seller paid Amazon for the clicks (₹).
A27: Sales (7-day) | B27: Sales (₹) that Amazon credits to the ad within 7 days of the click.
A28: Orders / Units | B28: Number of orders / number of items sold. One order can contain several units.
A29: CVR (conversion rate) | B29: Orders ÷ Clicks.
A30: ACOS | B30: Spend ÷ Sales. Lower is better. Example: Spend ₹300, Sales ₹1,000 gives ACOS 30%.
A31: ROAS | B31: Sales ÷ Spend (the inverse of ACOS).
A32: Break-even ACOS | B32: (Selling Price - Product Cost - Amazon Fees) ÷ Selling Price. If a product's ACOS is above this, every ad sale loses money.
... A36: Negate / negative keyword | B36: Tell Amazon to stop showing the ad for a search term.
A38: FILE MAP
A39: Search_Term_Report | B39: Main data. One row per date, campaign, ad group and search term (Sep 2026).
A40: Product_Master | B40: Selling price, cost and fees per SKU, plus stock status.
A41: Campaign_List | B41: All campaigns, budgets and status.
A42: Seller_Notes | B42: The seller's message, rules for Task D, competitor names.
A43: Cleaning_Log, Action_List | B43: Templates are included. Replace the example row (shaded) with your own entries.
A45: ASIN | B45: Amazon identification of a product - Aadhar number of a product on Amazon
A46: SKU | B46: Stock Keeping Unit - An ASIN may be mapped to multiple ASIN, one SKU can be mapped to only one ASIN.
A47: Ad Group | B47: An Ad Group containst ASINs (products) that are being advertised, and targets (keywords etc) on which the ad is to be shown, along with bid (price we are ready to pay for a click for that particular target).
A48: Campaign | B48: Cluster of Ad Groups

Sheet Search_Term_Report
A1: Date | B1: Campaign Name | C1: Portfolio | D1: Campaign Status | E1: Ad Group | F1: Ad Format | G1: Targeting | H1: Match Type | I1: Customer Search Term | J1: Product SKU | K1: Placement | L1: Impressions | M1: Clicks | N1: CTR | O1: CPC (₹) | P1: Spend (₹) | Q1: 7 Day Total Sales (₹) | R1: 7 Day Total Orders | S1: 7 Day Total Units | T1: ACOS | U1: ROAS | V1: CVR | W1: Bid (₹) | X1: Currency | Y1: Region | Z1: Notes
A2: 46266 | B2: SP | Auto | Face Care | C2: Face Care | D2: Enabled | E2: AG | Vitamin C Serum | F2: Sponsored Products | G2: close-match | H2: Auto | I2: best face serum vitamin c | J2: SKN-001 | K2: Top of Search | L2: 125 | M2: 4 | N2: 0.032 | O2: 15.54 | P2: 62.16 | Q2: 0 | R2: 0 | S2: 0 | U2: 0 | V2: 0 | W2: 17.5 | X2: INR | Y2: India
A3: 46266 | B3: SP | Auto | Face Care | C3: Face Care | D3: Enabled | E3: AG | Niacinamide Serum | F3: Sponsored Products | G3: loose-match | H3: Auto | I3: niacinamide serum with vitamin e | J3: SKN-002 | K3: Top of Search | L3: 300 | M3: 4 | N3: 0.013333333 | O3: 16.5 | P3: 66 | Q3: 0 | R3: 0 | S3: 0 | U3: 0 | V3: 0 | W3: 16.5 | X3: INR | Y3: India
A4: 01-Sep-2026 | B4: SP | Auto | Face Care | C4: Face Care | D4: Enabled | E4: AG | Niacinamide Serum | F4: Sponsored Products | G4: close-match | H4: Auto | I4: organic niacinamide 10% serum | J4: SKN-002 | K4: Product Pages | L4: 201 | M4: 5 | N4: 0.024875622 | O4: 6.14 | P4: 30.7 | Q4: 0 | R4: 0 | S4: 0 | U4: 0 | V4: 0 | W4: 10.5 | X4: INR | Y4: India
A5: 46266 | B5: SP | Auto | Face Care | C5: Face Care | D5: Enabled | E5: AG | Niacinamide Serum | F5: Sponsored Products | G5: loose-match | H5: Auto | I5: niacinamide 10% serum | J5: SKN-002 | K5: Rest of Search | L5: 808 | M5: 4 | N5: 0.004950495 | O5: 6.82 | P5: 27.28 | Q5: 0 | R5: 0 | S5: 0 | U5: 0 | V5: 0 | W5: 10 | X5: INR | Y5: India
A6: 46266 | B6: SP | Auto | Face Care | C6: Face Care | D6: Enabled | E6: AG | Gel Moisturizer | F6: Sponsored Products | G6: loose-match | H6: Auto | I6: organic gel moisturizer | J6: SKN-005 | K6: Product Pages | L6: 216 | M6: 0 | N6: 0 | P6: 0 | Q6: 0 | R6: 0 | S6: 0 | W6: 12 | X6: INR | Y6: India
A7: 01.09.2026 | B7: SP | Auto | Face Care | C7: Face Care | D7: Enabled | E7: AG | Gel Moisturizer | F7: Sponsored Products | G7: close-match | H7: Auto | I7: face moisturizer | J7: SKN-005 | K7: Rest of Search | L7: 1431 | M7: 17 | N7: 0.011879804 | O7: 6 | P7: 102 | Q7: 399 | R7: 1 | S7: 1 | T7: 0.2556 | U7: 3.91 | V7: 0.0588 | W7: 10.5 | X7: INR | Y7: India
A8: 46266 | B8: SP | Auto | Face Care | C8: Face Care | D8: Enabled | E8: AG | Gel Moisturizer | F8: Sponsored Products | G8: close-match | H8: Auto | I8: gel moisturizer | J8: SKN-005 | K8: Top of Search | L8: 1,449 | M8: 22 | N8: 0.015182885 | O8: 11.5 | P8: 253 | Q8: 1197 | R8: 3 | S8: 3 | T8: 0.2114 | U8: 4.73 | V8: 0.1364 | W8: 12 | X8: INR | Y8: India
A9: 46266 | B9: SP | Auto | Face Care | C9: Face Care | D9: Enabled | E9: AG | Sunscreen Spf 50 | F9: Sponsored Products | G9: close-match | H9: Auto | I9: sunscreen spf 50 | J9: SKN-006 | K9: Product Pages | L9: 2603 | M9: 14 | N9: 0.0053784095 | O9: 7.67 | P9: 107.38 | Q9: 0 | R9: 0 | S9: 0 | U9: 0 | V9: 0 | W9: 12 | X9: INR | Y9: India
A10: 46266 | B10: SP | Auto | Face Care | C10: Face Care | D10: Enabled | E10: AG | Rose Water Toner | F10: Sponsored Products | G10: close-match | H10: Auto | I10: rose water toner | J10: SKN-010 | K10: Top of Search | L10: 993 | M10: 3 | N10: 0.003021148 | O10: 7.49 | P10: 22.47 | Q10: 0 | R10: 0 | S10: 0 | U10: 0 | V10: 0 | W10: 8 | X10: INR | Y10: India
A11: 01-Sep-2026 | B11: SP | Auto | Face Care | C11: Face Care | D11: Enabled | E11: AG | Rose Water Toner | F11: Sponsored Products | G11: complements | H11: Auto | I11: face cream for dogs | J11: SKN-010 | K11: Product Pages | L11: 233 | M11: 2 | N11: 0.008583691 | O11: 2.95 | P11: 5.9 | Q11: 0 | R11: 0 | S11: 0 | U11: 0 | V11: 0 | W11: 5.5 | X11: INR | Y11: India
A12: 46266 | B12: SP | Auto | Face Care | C12: Face Care | D12: Enabled | E12: AG | Rose Water Toner | F12: Sponsored Products | G12: close-match | H12: Auto | I12: face toner price | J12: SKN-010 | K12: Top of Search | L12: 247 | M12: 1 | N12: 0.004048583 | O12: 6 | P12: 6 | Q12: 0 | R12: 0 | S12: 0 | U12: 0 | V12: 0 | W12: 6 | X12: INR | Y12: India
A13: 46266 | B13: SP | Auto | Body & Hair | C13: Body & Hair | D13: Enabled | E13: AG | Body Lotion | F13: Sponsored Products | G13: close-match | H13: Auto | I13: body lotion for dry skin | J13: SKN-017 | K13: Rest of Search | L13: 1128 | M13: 5 | N13: 0.0044326241 | O13: 7.2 | P13: 36 | Q13: 0 | R13: 0 | S13: 0 | U13: 0 | V13: 0 | W13: 12 | X13: INR | Y13: India | Z13: seller wants to monitor
A14: 46266 | B14: SP | Auto | Body & Hair | C14: Body & Hair | D14: Enabled | E14: AG | Body Lotion | F14: Sponsored Products | G14: substitutes | H14: Auto | I14: veluna shea body lotion | J14: SKN-017 | K14: Top of Search | L14: 115 | M14: 1 | N14: 0.0086956522 | O14: 14 | P14: 14 | Q14: 0 | R14: 0 | S14: 0 | U14: 0 | V14: 0 | W14: 14 | X14: INR | Y14: India
A15: 46287 | B15: SP | Manual | Masks & Gels | Broad | C15: Face Care | D15: Paused | E15: AG | Clay Face Mask | F15: Sponsored Products | G15: multani mitti face pack | H15: broad | I15: face cream for dogs | J15: SKN-012 | K15: Top of Search | L15: 176 | M15: 2 | N15: 0.0114 | O15: 13.87 | P15: 27.74 | Q15: 0 | R15: 0 | S15: 0 | U15: 0 | V15: 0 | W15: 7.5 | X15: INR | Y15: India
A16: 01-Sep-2026 | B16: SP | Auto | Body & Hair | C16: Body & Hair | D16: Enabled | E16: AG | Body Lotion | F16: Sponsored Products | G16: loose-match | H16: Auto | I16: baby lotion | J16: SKN-017 | K16: Top of Search | L16: 914 | M16: 15 | N16: 0.016411379 | O16: 9 | P16: 135 | Q16: 0 | R16: 0 | S16: 0 | U16: 0 | V16: 0 | W16: 9 | X16: INR | Y16: India
A17: 46266 | B17: SP | Auto | Body & Hair | C17: Body & Hair | D17: Enabled | E17: AG | Body Wash | F17: Sponsored Products | G17: close-match | H17: Auto | I17: body wash under 300 | J17: SKN-018 | K17: Product Pages | L17: 172 | M17: 1 | N17: 0.0058139535 | O17: 4.72 | P17: 4.72 | Q17: 0 | R17: 0 | S17: 0 | U17: 0 | V17: 0 | W17: 8.5 | X17: INR | Y17: India
A18: 46266 | B18: SP | Auto | Body & Hair | C18: Body & Hair | D18: Enabled | E18: AG | Body Wash | F18: Sponsored Products | G18: close-match | H18: Auto | I18: body wash | J18: SKN-018 | K18: Product Pages | L18: 1183 | M18: 7 | N18: 0.0059171598 | O18: 4.38 | P18: 30.66 | Q18: 0 | R18: 0 | S18: 0 | U18: 0 | V18: 0 | W18: 8.5 | X18: INR | Y18: India
A19: 46266 | B19: SP | Auto | Body & Hair | C19: Body & Hair | D19: Enabled | E19: AG | Body Wash | F19: Sponsored Products | G19: close-match | H19: Auto | I19: body wash for women under 300 | J19: SKN-018 | K19: Top of Search | L19: 772 | M19: 12 | N19: 0.015544041 | O19: 7.5 | P19: 90 | Q19: 0 | R19: 0 | S19: 0 | U19: 0 | V19: 0 | W19: 7.5 | X19: INR | Y19: India
A20: 46266 | B20: SP | Auto | Body & Hair | C20: Body & Hair | D20: Enabled | E20: AG | Body Wash | F20: Sponsored Products | G20: loose-match | H20: Auto | I20: body wash for women paraben free | J20: SKN-018 | K20: Rest of Search | L20: 927 | M20: 4 | N20: 0.0043149946 | O20: 6.04 | P20: 24.16 | Q20: 0 | R20: 0 | S20: 0 | U20: 0 | V20: 0 | W20: 8.5 | X20: INR | Y20: India
A21: 46266 | B21: SP | Auto | Body & Hair | C21: Body & Hair | D21: Enabled | E21: AG | Body Wash | F21: Sponsored Products | G21: complements | H21: Auto | I21: baby lotion | J21: SKN-018 | K21: Top of Search | L21: 150 | M21: 0 | N21: 0 | P21: 0 | Q21: 0 | R21: 0 | S21: 0 | W21: 8 | X21: INR | Y21: India
A22: 46266 | B22: SP | Auto | Body & Hair | C22: Body & Hair | D22: Enabled | E22: AG | Onion Hair Oil | F22: Sponsored Products | G22: loose-match | H22: Auto | I22: onion hair oil | J22: SKN-021 | K22: Top of Search | L22: 405 | M22: 4 | N22: 0.0098765432 | O22: 9.5 | P22: ₹38.00 | Q22: 798 | R22: 1 | S22: 2 | T22: 0.0476 | U22: 21 | V22: 0.25 | W22: 9.5 | X22: INR | Y22: India
A23: 46266 | B23: SP | Auto | Body & Hair | C23: Body & Hair | D23: Enabled | E23: AG | Onion Hair Oil | F23: Sponsored Products | G23: close-match | H23: Auto | I23: hair oil for hair growth | J23: SKN-021 | K23: Rest of Search | L23: 1645 | M23: 13 | N23: 0.0079027356 | O23: 6.16 | P23: 80.08 | Q23: 798 | R23: 2 | S23: 2 | T23: 0.1004 | U23: 9.97 | V23: 0.1538 | W23: 7.5 | X23: INR | Y23: India
A24: 46266 | B24: SP | Auto | Body & Hair | C24: Body & Hair | D24: Enabled | E24: AG | Onion Hair Oil | F24: Sponsored Products | G24: close-match | H24: Auto | I24: hair oil for hair growth for oily scalp | J24: SKN-021 | K24: Rest of Search | L24: 415 | M24: 3 | N24: 0.0072289157 | O24: 6.16 | P24: 18.48 | Q24: 399 | R24: 1 | S24: 1 | T24: 0.0463 | U24: 21.59 | V24: 0.3333 | W24: 11 | X24: INR | Y24: India
A25: 46266 | B25: SP | Auto | Body & Hair | C25: Body & Hair | D25: Enabled | E25: AG | Onion Hair Oil | F25: Sponsored Products | G25: loose-match | H25: Auto | I25: hair dryer | J25: SKN-021 | K25: Product Pages | L25: 569 | M25: 4 | N25: 0.007029877 | O25: 6.74 | P25: 26.96 | Q25: 0 | R25: 0 | S25: 0 | U25: 0 | V25: 0 | W25: 12.5 | X25: INR | Y25: India
A26: 46266 | B26: SP | Auto | Body & Hair | C26: Body & Hair | D26: Enabled | E26: AG | Anti Dandruff Shampoo | F26: Sponsored Products | G26: loose-match | H26: Auto | I26: anti dandruff shampoo paraben free | J26: SKN-022 | K26: Rest of Search | L26: 798 | M26: 6 | N26: 0.007518797 | O26: 5.18 | P26: 31.08 | Q26: 429 | R26: 1 | S26: 1 | T26: 0.0724 | U26: 13.8 | V26: 0.1667 | W26: 9 | X26: INR | Y26: India
A27: 01-Sep-2026 | B27: SP | Manual | Face Serums | Exact | C27: Face Care | D27: Enabled | E27: AG | Vitamin C Serum | F27: Sponsored Products | G27: face serum vitamin c pack of 2 | H27: Exact match | I27: face serum vitamin c pack of 2 | J27: SKN-001 | K27: Rest of Search | L27: 585 | M27: 2 | N27: 0.0034188034 | O27: 12.18 | P27: 24.36 | Q27: 599 | R27: 1 | S27: 1 | T27: 0.0407 | U27: 24.59 | V27: 0.5 | W27: 18.5 | X27: INR | Y27: India
A28: 46266 | B28: SP | Manual | Face Serums | Exact | C28: Face Care | D28: Enabled | E28: AG | Vitamin C Serum | F28: Sponsored Products | G28: vit c face serum | H28: Exact | I28: vit c face serum | J28: SKN-001 | K28: Top of Search | L28: 349 | M28: 2 | N28: 0.005730659 | O28: 10.97 | P28: 21.94 | Q28: 0 | R28: 0 | S28: 0 | U28: 0 | V28: 0 | W28: 14 | X28: INR | Y28: India
A29: 46266 | B29: SP | Manual | Face Serums | Exact | C29: Face Care | D29: Enabled | E29: AG | Vitamin C Serum | F29: Sponsored Products | G29: face serum vitamin c | H29: Exact | I29: face serum vitamin c | J29: SKN-001 | K29: Product Pages | L29: 895 | M29: 10 | N29: 0.011173184 | O29: 10.64 | P29: 106.4 | Q29: 0 | R29: 0 | S29: 0 | U29: 0 | V29: 0 | W29: 15.5 | X29: INR | Y29: India
A30: 46266 | B30: SP | Manual | Face Serums | Exact | C30: Face Care | D30: Enabled | E30: AG | Niacinamide Serum | F30: Sponsored Products | G30: niacinamide 10% serum under 300 | H30: Exact | I30: niacinamide 10% serum under 300 | J30: SKN-002 | K30: Product Pages | L30: 560 | M30: 6 | N30: 0.010714286 | O30: 8.03 | P30: 48.18 | Q30: 549 | R30: 1 | S30: 1 | T30: 0.0878 | U30: 11.39 | V30: 0.1667 | W30: 13 | X30: INR | Y30: India
A31: 46266 | B31: SP | Manual | Face Serums | Exact | C31: Face Care | D31: Enabled | E31: AG | Niacinamide Serum | F31: Sponsored Products | G31: niacinamide 10% serum | H31: Exact | I31: niacinamide 10% serum | J31: SKN-002 | K31: Rest of Search | L31: 1024 | M31: 2 | N31: 0.001953125 | O31: 10.52 | P31: 21.04 | Q31: 0 | R31: 0 | S31: 0 | U31: 0 | V31: 0 | W31: 15 | X31: INR | Y31: India
A32: 46266 | B32: SP | Manual | Face Serums | Exact | C32: Face Care | D32: Enabled | E32: AG | Niacinamide Serum | F32: Sponsored Products | G32: niacinamide serum | H32: Exact | I32: niacinamide serum | J32: SKN-002 | K32: Product Pages | L32: 762 | M32: 9 | N32: 0.011811024 | O32: 11.69 | P32: 105.21 | Q32: 0 | R32: 0 | S32: 0 | U32: 0 | V32: 0 | W32: 15 | X32: INR | Y32: India
A33: 46266 | B33: SP | Manual | Face Serums | Exact | C33: Face Care | D33: Enabled | E33: AG | Hyaluronic Acid Serum | F33: Sponsored Products | G33: hyaluronic acid serum for dry skin | H33: exact | I33: hyaluronic acid serum for dry skin | J33: SKN-003 | K33: Top of Search | L33: 100 | M33: 1 | N33: 0.01 | O33: 24 | P33: 24 | Q33: 0 | R33: 0 | S33: 0 | U33: 0 | V33: 0 | W33: 24 | X33: INR | Y33: India
A34: 46266 | B34: SP | Manual | Face Serums | Exact | C34: Face Care | D34: Enabled | E34: AG | Hyaluronic Acid Serum | F34: Sponsored Products | G34: hyaluronic serum | H34: Exact | I34: hyaluronic serum | J34: SKN-003 | K34: Product Pages | L34: 919 | M34: 11 | N34: 0.011969532 | O34: 17.49 | P34: ₹192.39 | Q34: 649 | R34: 1 | S34: 1 | T34: 0.2964 | U34: 3.37 | V34: 0.0909 | W34: 25 | X34: INR | Y34: India
A35: 46266 | B35: SP | Manual | Face Serums | Exact | C35: Face Care | D35: Enabled | E35: AG | Retinol Night Cream | F35: Sponsored Products | G35: night cream for face | H35: Exact | I35: night cream for face | J35: SKN-004 | K35: Product Pages | L35: 486 | M35: 0 | N35: 0 | P35: 0 | Q35: 0 | R35: 0 | S35: 0 | W35: 23.5 | X35: INR | Y35: India
A36: 46266 | B36: SP | Manual | Face Serums | Broad | C36: Face Care | D36: Enabled | E36: AG | Niacinamide Serum | F36: Sponsored Products | G36: niacinamide 10% serum | H36: Broad | I36: pureroots niacinamide 10% serum | J36: SKN-002 | K36: Top of Search | L36: 345 | M36: 1 | N36: 0.0028985507 | O36: 10.5 | P36: 10.5 | Q36: 0 | R36: 0 | S36: 0 | U36: 0 | V36: 0 | W36: 10.5 | X36: INR | Y36: India
A37: 46266 | B37: SP | Manual | Face Serums | Broad | C37: Face Care | D37: Enabled | E37: AG | Niacinamide Serum | F37: Sponsored Products | G37: niacinamide 10% serum | H37: Broad | I37: BEST NIACINAMIDE 10% SERUM | J37: SKN-002 | K37: Rest of Search | L37: 357 | M37: 1 | N37: 0.0028011204 | O37: 7.68 | P37: 7.68 | Q37: 0 | R37: 0 | S37: 0 | U37: 0 | V37: 0 | W37: 12.5 | X37: Rs. | Y37: India
A38: 46266 | B38: SP | Manual | Face Serums | Broad | C38: Face Care | D38: Enabled | E38: AG | Hyaluronic Acid Serum | F38: Sponsored Products | G38: hyaluronic serum | H38: Broad | I38: hyaluronic serum | J38: SKN-003 | K38: Rest of Search | L38: 1412 | M38: 14 | N38: 0.0099150142 | O38: 10.55 | P38: 147.7 | Q38: 0 | R38: 0 | S38: 0 | U38: 0 | V38: 0 | W38: 14 | X38: INR | Y38: India
A39: 46266 | B39: SP | Manual | Face Serums | Broad | C39: Face Care | D39: Enabled | E39: AG | Hyaluronic Acid Serum | F39: Sponsored Products | G39: hyaluronic serum | H39: Broad | I39: face serum hyaluronic for daily use | J39: SKN-003 | K39: Top of Search | L39: 174 | M39: 4 | N39: 0.022988506 | O39: 14.5 | P39: 58 | Q39: 649 | R39: 1 | S39: 1 | T39: 0.0894 | U39: 11.19 | V39: 0.25 | W39: 14.5 | X39: INR | Y39: India
A40: 46266 | B40: SP | Manual | Face Serums | Broad | C40: Face Care | D40: Enabled | E40: AG | Hyaluronic Acid Serum | F40: Sponsored Products | G40: hyaluronic acid serum | H40: Broad | I40: face serum hyaluronic pack of 2 | J40: SKN-003 | K40: Product Pages | L40: 239 | M40: 1 | N40: 0.0041841004 | O40: 6.67 | P40: 6.67 | Q40: 0 | R40: 0 | S40: 0 | U40: 0 | V40: 0 | W40: 12 | X40: INR | Y40: India
A41: 46266 | B41: SP | Manual | Face Serums | Broad | C41: Face Care | D41: Enabled | E41: AG | Hyaluronic Acid Serum | F41: Sponsored Products | G41: hyaluronic acid serum | H41: broad | I41: hyaluronic acid serum | J41: SKN-003 | K41: Rest of Search | L41: 1510 | M41: 11 | N41: 0.0072847682 | O41: 13.09 | P41: 143.99 | Q41: 0 | R41: 0 | S41: 0 | U41: 0 | V41: 0 | W41: 16 | X41: INR | Y41: India
A42: 46266 | B42: SP | Manual | Sunscreen | Phrase | C42: Face Care | D42: Enabled | E42: AG | Sunscreen Spf 50 | F42: Sponsored Products | G42: sunscreen spf 50 | H42: PHRASE | I42: spf 50 sunscreen for face for men | J42: SKN-006 | K42: Product Pages | L42: 96 | M42: 1 | N42: 0.010416667 | O42: 7.77 | P42: 7.77 | Q42: 0 | R42: 0 | S42: 0 | U42: 0 | V42: 0 | W42: 13.5 | X42: INR | Y42: India
A43: 46266 | B43: SP | Manual | Sunscreen | Phrase | C43: Face Care | D43: Enabled | E43: AG | Sunscreen Spf 50 | F43: Sponsored Products | G43: sunscreen | H43: phrase | I43: SUNSCREEN FOR DRY SKIN | J43: SKN-006 | K43: Rest of Search | L43: 1100 | M43: 6 | N43: 0.0054545455 | O43: 10.04 | P43: 60.24 | Q43: 0 | R43: 0 | S43: 0 | U43: 0 | V43: 0 | W43: 13 | X43: INR | Y43: India
A44: 46266 | B44: SP | Manual | Sunscreen | Phrase | C44: Face Care | D44: Enabled | E44: AG | Sunscreen Spf 50 | F44: Sponsored Products | G44: sunscreen | H44: Phrase | I44: sunscreen | J44: skn-006 | K44: Top of Search | L44: 409 | M44: 8 | N44: 0.019559902 | O44: 15 | P44: 120 | Q44: 0 | R44: 0 | S44: 0 | U44: 0 | V44: 0 | W44: 15 | X44: INR | Y44: India
A45: 46266 | B45: SP | Manual | Sunscreen | Phrase | C45: Face Care | D45: Enabled | E45: AG | Sunscreen Spf 50 | F45: Sponsored Products | G45: sunscreen | H45: Phrase | I45: spf 50 sunscreen for face | J45: SKN-006 | K45: Top of Search | L45: 525 | M45: 7 | N45: 0.013333333 | O45: 11.69 | P45: 81.83 | Q45: 0 | R45: 0 | S45: 0 | U45: 0 | V45: 0 | W45: 13 | X45: INR | Y45: India
A46: 46266 | B46: SP | Manual | Skincare Essentials | Broad | C46: Face Care | D46: Enabled | E46: AG | Gel Moisturizer | F46: Sponsored Products | G46: gel moisturizer | H46: Broad | I46: organic gel moisturizer | J46: SKN-005 | K46: Rest of Search | L46: 98 | M46: 1 | N46: 0.010204082 | O46: 6.95 | P46: 6.95 | Q46: 0 | R46: 0 | S46: 0 | U46: 0 | V46: 0 | W46: 11 | X46: INR | Y46: India
A47: 01-Sep-2026 | B47: SP | Manual | Skincare Essentials | Broad | C47: Face Care | D47: Enabled | E47: AG | Gel Moisturizer | F47: Sponsored Products | G47: oil free moisturizer | H47: Broad | I47: face moisturizer for teenagers | J47: SKN-005 | K47: Top of Search | L47: 90 | M47: 1 | N47: 0.011111111 | O47: 8.83 | P47: 8.83 | Q47: 0 | R47: 0 | S47: 0 | U47: 0 | V47: 0 | W47: 9 | X47: INR | Y47: India
A48: 46266 | B48: SP | Manual | Skincare Essentials | Broad | C48: Face Care | D48: Enabled | E48: AG | Gel Moisturizer | F48: Sponsored Products | G48: gel moisturizer | H48: Broad | I48: gel moisturizer | J48: SKN-005 | K48: Product Pages | L48: 686 | M48: 8 | N48: 0.011661808 | O48: 7.41 | P48: 59.28 | Q48: 0 | R48: 0 | S48: 0 | U48: 0 | V48: 0 | W48: 10 | X48: INR | Y48: India
A49: 46266 | B49: SP | Manual | Skincare Essentials | Broad | C49: Face Care | D49: Enabled | E49: AG | Gel Moisturizer | F49: Sponsored Products | G49: gel moisturizer | H49: Broad | I49: skin care course online | J49: SKN-005 | K49: Top of Search | L49: 128 | M49: 0 | N49: 0 | P49: 0 | Q49: 0 | R49: 0 | S49: 0 | W49: 7 | X49: INR | Y49: India
A50: 46266 | B50: SP | Manual | Skincare Essentials | Broad | C50: Face Care | D50: Enabled | E50: AG | Gel Moisturizer | F50: Sponsored Products | G50: gel moisturizer | H50: Broad | I50: face moisturizer | J50: SKN-005 | K50: Top of Search | L50: 375 | M50: 6 | N50: 0.0352 | O50: 10.41 | P50: 62.46 | Q50: 0 | R50: 0 | S50: 0 | U50: 0 | V50: 0 | W50: 11.5 | X50: INR | Y50: India
A51: 46266 | B51: SP | Manual | Skincare Essentials | Broad | C51: Face Care | D51: Enabled | E51: AG | Gel Moisturizer | F51: Sponsored Products | G51: gel moisturizer | H51: Broad | I51: gel moisturizer for tan removal | J51: SKN-005 | K51: Rest of Search | L51: 222 | M51: 1 | N51: 0.0045045045 | O51: 6.6 | P51: 6.6 | Q51: 0 | R51: 0 | S51: 0 | U51: 0 | V51: 0 | W51: 8 | X51: INR | Y51: India
A52: 46266 | B52: SP | Manual | Skincare Essentials | Broad | C52: Face Care | D52: Enabled | E52: AG | Gel Moisturizer | F52: Sponsored Products | G52: oil free moisturizer | H52: Broad | I52: face cream for dogs | J52: SKN-005 | K52: Rest of Search | L52: 826 | M52: 4 | N52: 0.004842615 | O52: 9.52 | P52: 38.08 | Q52: 0 | R52: 0 | S52: 0 | U52: 0 | V52: 0 | W52: 11.5 | X52: Rs. | Y52: India
A53: 01-Sep-2026 | B53: SP | Manual | Skincare Essentials | Broad | C53: Face Care | D53: Enabled | E53: AG | Face Wash | F53: Sponsored Products | G53: foaming face wash | H53: Broad | I53: face wash for dry skin | J53: SKN-008 | K53: Product Pages | L53: 376 | M53: 3 | N53: 0.0798 | O53: 6.71 | P53: 20.13 | Q53: 0 | R53: 0 | S53: 0 | U53: 0 | V53: 0 | W53: 8.5 | X53: INR | Y53: India
A54: 01-Sep-2026 | B54: SP | Manual | Skincare Essentials | Broad | C54: Face Care | D54: Enabled | E54: AG | Face Wash | F54: Sponsored Products | G54: foaming face wash | H54: Broad | I54: foaming face wash for summer | J54: SKN-008 | K54: Rest of Search | L54: 341 | M54: 4 | N54: 0.011730205 | O54: 5.39 | P54: 21.56 | Q54: 0 | R54: 0 | S54: 0 | U54: 0 | V54: 0 | W54: 9 | X54: INR | Y54: India
A55: 46266 | B55: SP | Manual | Skincare Essentials | Broad | C55: Face Care | D55: Enabled | E55: AG | Salicylic Acid Face Wash | F55: Sponsored Products | G55: acne face wash | H55: broad | I55: Acne Face Wash | J55: SKN-009 | K55: Rest of Search | L55: 1087 | M55: 2 | N55: 0.0018399264 | O55: 6.56 | P55: 13.12 | Q55: 0 | R55: 0 | S55: 0 | U55: 0 | V55: 0 | W55: 8 | X55: INR | Y55: India
A56: 46266 | B56: SP | Manual | Skincare Essentials | Broad | C56: Face Care | D56: Enabled | E56: AG | Salicylic Acid Face Wash | F56: Sponsored Products | G56: acne face wash | H56: Broad | I56: salicylic acid face wash for acne | J56: SKN-009 | K56: Top of Search | L56: 66 | M56: 2 | N56: 0.03030303 | O56: 6 | P56: 12 | Q56: 0 | R56: 0 | S56: 0 | U56: 0 | V56: 0 | W56: 6 | X56: INR | Y56: India
A57: 46292 | B57: SP | Brand Defence | Exact | C57: Brand | D57: Enabled | E57: AG | Vitamin C Serum | F57: Sponsored Products | G57: auralis face serum vitamin c | H57: Exact | I57: auralis face serum vitamin c | J57: SKN-001 | K57: Top of Search | L57: 0 | M57: 0 | P57: -130.81 | Q57: 0 | R57: 0 | S57: 0 | W57: 8 | X57: INR | Y57: India | Z57: refund
A58: 46266 | B58: SP | Manual | Skincare Essentials | Broad | C58: Face Care | D58: Enabled | E58: AG | Salicylic Acid Face Wash | F58: Sponsored Products | G58: acne face wash | H58: Broad | I58: salicylic face wash price | J58: SKN-009 | K58: Top of Search | L58: 224 | M58: 1 | N58: 0.0044642857 | O58: 7 | P58: 7 | Q58: 0 | R58: 0 | S58: 0 | U58: 0 | V58: 0 | W58: 7 | X58: INR | Y58: India
A59: 46266 | B59: SP | Manual | Skincare Essentials | Broad | C59: Face Care | D59: Enabled | E59: AG | Salicylic Acid Face Wash | F59: Sponsored Products | G59: acne face wash | H59: Broad | I59: salicylic acid face wash for night use | J59: SKN-009 | K59: Top of Search | L59: 212 | M59: 4 | N59: 0.018867925 | O59: 5.5 | P59: 22 | Q59: 0 | R59: 0 | S59: 0 | U59: 0 | V59: 0 | W59: 5.5 | X59: INR | Y59: India
A60: 46266 | B60: SP | Manual | Skincare Essentials | Broad | C60: Face Care | D60: Enabled | E60: AG | Rose Water Toner | F60: Sponsored Products | G60: rose water toner | H60: Broad | I60: ayurvedic rose water toner | J60: SKN-010 | K60: Rest of Search | L60: 444 | M60: 1 | N60: 0.0022522523 | O60: 3.92 | P60: 3.92 | Q60: 0 | R60: 0 | S60: 0 | U60: 0 | V60: 0 | W60: 5.5 | X60: INR | Y60: India
A61: 46266 | B61: SP | Manual | Skincare Essentials | Broad | C61: Face Care | D61: Enabled | E61: AG | Rose Water Toner | F61: Sponsored Products | G61: face toner | H61: Broad | I61: rose water spray | J61: SKN-010 | K61: Top of Search | L61: 478 | M61: 3 | N61: 0.0062761506 | O61: 5.36 | P61: 16.08 | Q61: 0 | R61: 0 | S61: 0 | U61: 0 | V61: 0 | W61: 6 | X61: INR | Y61: India
A62: 46266 | B62: SP | Manual | Skincare Essentials | Broad | C62: Face Care | D62: Enabled | E62: AG | Sheet Mask | F62: Sponsored Products | G62: sheet mask | H62: Broad | I62: face sheet mask for sensitive skin | J62: SKN-014 | K62: Top of Search | L62: 409 | M62: 9 | N62: 0.02200489 | O62: 8.72 | P62: 78.48 | Q62: 1047 | R62: 2 | S62: 3 | T62: 0.075 | U62: 13.34 | V62: 0.2222 | W62: 10.5 | X62: INR | Y62: India
A63: 46266 | B63: SP | Manual | Skincare Essentials | Broad | C63: Face Care | D63: Enabled | E63: AG | Sheet Mask | F63: Sponsored Products | G63: sheet mask | H63: Broad | I63: free sample face cream | J63: SKN-014 | K63: Product Pages | L63: 409 | M63: 0 | N63: 0 | P63: 0 | Q63: 0 | R63: 0 | S63: 0 | W63: 10 | X63: Rs. | Y63: India
A64: 01-Sep-2026 | B64: SP | Manual | Skincare Essentials | Broad | C64: Face Care | D64: Enabled | E64: AG | Sheet Mask | F64: Sponsored Products | G64: face sheet mask | H64: broad | I64: face sheet mask for night use | J64: SKN-014 | K64: Product Pages | L64: 271 | M64: 3 | N64: 0.011070111 | O64: 5.62 | P64: 16.86 | Q64: 349 | R64: 1 | S64: 1 | T64: 4.8 | U64: 20.7 | V64: 0.3333 | W64: 7.5 | X64: INR | Y64: India
A65: 46266 | B65: SP | Manual | Hair Care | Phrase | C65: Body & Hair | D65: Enabled | E65: AG | Onion Hair Oil | F65: Sponsored Products | G65: hair oil | H65: Phrase | I65: skinlore hair oil for hair growth | J65: SKN-021 | K65: Rest of Search | L65: 766 | M65: 3 | N65: 0.0039164491 | O65: 6.71 | P65: 20.13 | Q65: 0 | R65: 0 | S65: 0 | U65: 0 | V65: 0 | W65: 10.5 | X65: INR | Y65: India
A66: 46266 | B66: SP | Manual | Hair Care | Phrase | C66: Body & Hair | D66: Enabled | E66: AG | Onion Hair Oil | F66: Sponsored Products | G66: onion hair oil | H66: Phrase | I66: comb for men | J66: SKN-021 | K66: Top of Search | L66: 414 | M66: 3 | N66: 0.0072463768 | O66: 8.35 | P66: 25.05 | Q66: 0 | R66: 0 | S66: 0 | U66: 0 | V66: 0 | W66: 10 | X66: INR | Y66: India
A67: 46266 | B67: SP | Manual | Hair Care | Phrase | C67: Body & Hair | D67: Enabled | E67: AG | Onion Hair Oil | F67: Sponsored Products | G67: onion hair oil | H67: Phrase | I67: hair oil for hair growth for hair growth | J67: SKN-021 | K67: Product Pages | L67: 330 | M67: 3 | N67: 0.0090909091 | O67: 8.3 | P67: 24.9 | Q67: 0 | R67: 0 | S67: 0 | U67: 0 | V67: 0 | W67: 11 | X67: INR | Y67: India
A68: 46266 | B68: SP | Manual | Hair Care | Phrase | C68: Body & Hair | D68: Enabled | E68: AG | Anti Dandruff Shampoo | F68: Sponsored Products | G68: dandruff shampoo | H68: PHRASE | I68: veluna shampoo for dandruff | J68: SKN-022 | K68: Rest of Search | L68: 347 | M68: 1 | N68: 0.0028818444 | O68: 11.18 | P68: 11.18 | Q68: 0 | R68: 0 | S68: 0 | U68: 0 | V68: 0 | W68: 14 | X68: INR | Y68: India
A69: 01-Sep-2026 | B69: SP | Manual | Hair Care | Phrase | C69: Body & Hair | D69: Enabled | E69: AG | Anti Dandruff Shampoo | F69: Sponsored Products | G69: anti dandruff shampoo | H69: Phrase | I69: dandruff shampoo | J69: SKN-022 | K69: Rest of Search | L69: 538 | M69: 2 | N69: 0.0037174721 | O69: 9.75 | P69: 19.5 | Q69: 0 | R69: 0 | S69: 0 | U69: 0 | V69: 0 | W69: 13.5 | X69: INR | Y69: India
A70: 46266 | B70: SP | Manual | Hair Care | Phrase | C70: Body & Hair | D70: Enabled | E70: AG | Hair Serum | F70: Sponsored Products | G70: hair serum | H70: Phrase | I70: smoothening hair serum | J70: SKN-023 | K70: Product Pages | L70: 283 | M70: 5 | N70: 0.017667845 | O70: 6.61 | P70: 33.05 | Q70: 0 | R70: 0 | S70: 0 | U70: 0 | V70: 0 | W70: 12 | X70: INR | Y70: India
A71: 46266 | B71: SP | Manual | Hair Care | Phrase | C71: Body & Hair | D71: Enabled | E71: AG | Hair Serum | F71: Sponsored Products | G71: hair serum for frizzy hair | H71: phrase | I71: dermavault hair serum for frizzy hair | J71: SKN-023 | K71: Product Pages | L71: 437 | M71: 3 | N71: 0.0068649886 | O71: 7.83 | P71: 23.49 | Q71: 0 | R71: 0 | S71: 0 | U71: 0 | V71: 0 | W71: 15 | X71: INR | Y71: India
A72: 46266 | B72: SP | Manual | Hair Care | Phrase | C72: Body & Hair | D72: Enabled | E72: AG | Hair Serum | F72: Sponsored Products | G72: hair serum | H72: Phrase | I72: smoothening hair serum for smooth hair | J72: SKN-023 | K72: Product Pages | L72: 334 | M72: 4 | N72: 0.011976048 | O72: 8.81 | P72: ₹35.24 | Q72: 0 | R72: 0 | S72: 0 | U72: 0 | V72: 0 | W72: 12 | X72: INR | Y72: India
A73: 46266 | B73: SP | Manual | Body Care | Exact | C73: Body & Hair | D73: Enabled | E73: AG | Body Wash | F73: Sponsored Products | G73: body wash fragrance free | H73: Exact | I73: body wash fragrance free | J73: SKN-018 | K73: Top of Search | L73: 338 | M73: 2 | N73: 0.0059171598 | O73: 8.02 | P73: 16.04 | Q73: 0 | R73: 0 | S73: 0 | U73: 0 | V73: 0 | W73: 9 | X73: INR | Y73: India
A74: 46266 | B74: SP | Manual | Body Care | Exact | C74: Body & Hair | D74: Enabled | E74: AG | Body Wash | F74: Sponsored Products | G74: body wash for women paraben free | H74: Exact | I74: body wash for women paraben free | J74: SKN-018 | K74: Top of Search | L74: 286 | M74: 2 | N74: 0.006993007 | O74: 10.48 | P74: 20.96 | Q74: 0 | R74: 0 | S74: 0 | U74: 0 | V74: 0 | W74: 12 | X74: INR | Y74: India
A75: 01-Sep-2026 | B75: SP | Manual | Body Care | Exact | C75: Body & Hair | D75: Enabled | E75: AG | Body Wash | F75: Sponsored Products | G75: body wash | H75: Exact | I75: body wash | J75: SKN-018 | K75: Rest of Search | L75: 1094 | M75: 9 | N75: 0.008226691 | O75: 6.61 | P75: 59.49 | Q75: 349 | R75: 1 | S75: 1 | T75: 0.1705 | U75: 5.87 | V75: 0.1111 | W75: 8.5 | X75: INR | Y75: India
A76: 46266 | B76: SP | Manual | Body Care | Exact | C76: Body & Hair | D76: Enabled | E76: AG | Body Wash | F76: Sponsored Products | G76: shower gel | H76: Exact | I76: shower gel | J76: SKN-018 | K76: Rest of Search | L76: 321 | M76: 2 | N76: 0.0062305296 | O76: 7.89 | P76: 15.78 | Q76: 0 | R76: 0 | S76: 0 | U76: 0 | V76: 0 | W76: 13 | X76: INR | Y76: India
A77: 01-Sep-2026 | B77: SP | Manual | Body Care | Exact | C77: Body & Hair | D77: Enabled | E77: AG | Foot Cream | F77: Sponsored Products | G77: cracked heel cream | H77: Exact | I77: cracked heel cream | J77: SKN-019 | K77: Top of Search | L77: 492 | M77: 2 | N77: 0.0040650407 | O77: 8 | P77: 16 | Q77: 299 | R77: 1 | S77: 1 | T77: 0.0535 | U77: 18.69 | V77: 0.5 | W77: 8 | X77: INR | Y77: India
A78: 46266 | B78: SP | Manual | Body Care | Exact | C78: Body & Hair | D78: Enabled | E78: AG | Foot Cream | F78: Sponsored Products | G78: foot cream for kids | H78: Exact | I78: foot cream for kids | J78: SKN-019 | K78: Product Pages | L78: 199 | M78: 0 | N78: 0 | P78: 0 | Q78: 0 | R78: 0 | S78: 0 | W78: 8 | X78: INR | Y78: India
A79: 46266 | B79: SP | Manual | Body Care | Exact | C79: Body & Hair | D79: Enabled | E79: AG | Hand Cream | F79: Sponsored Products | G79: hand cream | H79: Exact | I79: hand cream | J79: SKN-020 | K79: Product Pages | L79: 1068 | M79: 6 | N79: 0.0056179775 | O79: 6.51 | P79: 39.06 | Q79: 498 | R79: 2 | S79: 2 | T79: 0.0784 | U79: 12.75 | V79: 0.3333 | W79: 9.5 | X79: INR | Y79: India
A80: 46266 | B80: SP | Manual | Body Care | Exact | C80: Body & Hair | D80: Enabled | E80: AG | Hand Cream | F80: Sponsored Products | G80: moisturizing hand cream | H80: Exact | I80: moisturizing hand cream | J80: SKN-020 | K80: Top of Search | L80: 431 | M80: 8 | N80: 0.018561485 | O80: 6 | P80: 48 | Q80: 0 | R80: 0 | S80: 0 | U80: 0 | V80: 0 | W80: 6 | X80: INR | Y80: India
A81: 01-Sep-2026 | B81: SP | Manual | Body Care | Exact | C81: Body & Hair | D81: Enabled | E81: AG | Hand Cream | F81: Sponsored Products | G81: hand cream for dry hands non sticky | H81: Exact | I81: hand cream for dry hands non sticky | J81: SKN-020 | K81: Rest of Search | L81: 290 | M81: 0 | N81: 0 | P81: 0 | Q81: 0 | R81: 0 | S81: 0 | W81: 6.5 | X81: INR | Y81: India
A82: 46266 | B82: SP | Manual | Body Care | Exact | C82: Body & Hair | D82: Enabled | E82: AG | Hand Cream | F82: Sponsored Products | G82: ayurvedic moisturizing hand cream | H82: exact | I82: ayurvedic moisturizing hand cream | J82: SKN-020 | K82: Rest of Search | L82: 412 | M82: 3 | N82: 0.0072815534 | O82: 7.27 | P82: 21.81 | Q82: 498 | R82: 2 | S82: 2 | T82: 0.0438 | U82: 22.83 | V82: 0.6667 | W82: 9 | X82: INR | Y82: India
A83: 46266 | B83: SP | Product Targeting | Competitors | C83: Face Care | D83: Enabled | E83: AG | Vitamin C Serum | F83: Sponsored Products | G83: asin=B0UY3HJ2K9 | H83: Product | I83: b0uy3hj2k9 | J83: SKN-001 | K83: Product Pages | L83: 731 | M83: 5 | N83: 0.0068399453 | O83: 10.74 | P83: 53.7 | Q83: 599 | R83: 1 | S83: 1 | T83: 0.0896 | U83: 11.15 | V83: 0.2 | W83: 15 | X83: INR | Y83: India
A84: 46292 | B84: SP | Manual | Masks & Gels | Broad | C84: Face Care | D84: Paused | E84: AG | Clay Face Mask | F84: Sponsored Products | G84: multani mitti face pack | H84: Broad | I84: face cream for dogs | J84: SKN-012 | K84: Top of Search | L84: 1110 | M84: 10 | N84: 0.009 | O84: 14.49 | P84: 144.9 | Q84: 0 | R84: 0 | S84: 0 | U84: 0 | V84: 0 | W84: 7.5 | X84: INR | Y84: India
A85: 46266 | B85: SP | Product Targeting | Competitors | C85: Face Care | D85: Enabled | E85: AG | Vitamin C Serum | F85: Sponsored Products | G85: asin=B0XANRGQOZ | H85: Product | I85: b0xanrgqoz | J85: SKN-001 | K85: Rest of Search | L85: 1684 | M85: 10 | N85: 0.0059382423 | O85: 7.04 | P85: 70.4 | Q85: 0 | R85: 0 | S85: 0 | U85: 0 | V85: 0 | W85: 12 | X85: INR | Y85: India | Z85: budget raised
A86: 46266 | B86: SP | Product Targeting | Competitors | C86: Face Care | D86: Enabled | E86: AG | Vitamin C Serum | F86: Sponsored Products | G86: asin=B0Y9ZBIY9G | H86: Product | I86: B0Y9ZBIY9G | J86: SKN-001 | K86: Product Pages | L86: 216 | M86: 1 | N86: 0.0046296296 | O86: 12.65 | P86: 12.65 | Q86: 0 | R86: 0 | S86: 0 | U86: 0 | V86: 0 | W86: 16 | X86: INR | Y86: India
A87: 01-Sep-2026 | B87: SP | Product Targeting | Competitors | C87: Face Care | D87: Enabled | E87: AG | Sunscreen Spf 50 | F87: Sponsored Products | G87: asin=B0Q7LDYO0L | H87: Product | I87: b0q7ldyo0l | J87: SKN-006 | K87: Product Pages | L87: 1119 | M87: 5 | N87: 0.0044682752 | O87: 7.99 | P87: 39.95 | Q87: 0 | R87: 0 | S87: 0 | U87: 0 | V87: 0 | W87: 11 | X87: INR | Y87: India
A88: 46266 | B88: SP | Product Targeting | Competitors | C88: Face Care | D88: Enabled | E88: AG | Sunscreen Spf 50 | F88: Sponsored Products | G88: asin=B0KZ0MQAV8 | H88: Product | I88: b0kz0mqav8 | J88: SKN-006 | K88: Product Pages | L88: 2232 | M88: 12 | N88: 0.0053763441 | O88: 5.55 | P88: 66.6 | Q88: 0 | R88: 0 | S88: 0 | U88: 0 | V88: 0 | W88: 7.5 | X88: INR | Y88: IN
A89: 46266 | B89: SP | Product Targeting | Competitors | C89: Face Care | D89: Enabled | E89: AG | Sunscreen Spf 50 | F89: Sponsored Products | G89: asin=B0S40CCJFN | H89: Product | I89: b0s40ccjfn | J89: SKN-006 | K89: Top of Search | L89: 480 | M89: 1 | N89: 0.0020833333 | O89: 8.8 | P89: ₹8.80 | Q89: 0 | R89: 0 | S89: 0 | U89: 0 | V89: 0 | W89: 9.5 | X89: INR | Y89: India
A90: 01-Sep-2026 | B90: SP | Product Targeting | Competitors | C90: Face Care | D90: Enabled | E90: AG | Face Wash | F90: Sponsored Products | G90: asin=B0G26G1I7R | H90: Product | I90: b0g26g1i7r | J90: SKN-008 | K90: Product Pages | L90: 1665 | M90: 9 | N90: 0.0054054054 | O90: 2.89 | P90: 26.01 | Q90: 0 | R90: 0 | S90: 0 | U90: 0 | V90: 0 | W90: 5.5 | X90: INR | Y90: India
A91: 46266 | B91: SP | Product Targeting | Competitors | C91: Face Care | D91: Enabled | E91: AG | Face Wash | F91: Sponsored Products | G91: asin=B0K1VXAHQJ | H91: Product | I91: b0k1vxahqj | J91: SKN-008 | K91: Product Pages | L91: 411 | M91: 3 | N91: 0.0072992701 | O91: 5.1 | P91: 15.3 | Q91: 0 | R91: 0 | S91: 0 | U91: 0 | V91: 0 | W91: 6.5 | X91: INR | Y91: India
A92: 46266 | B92: SP | Product Targeting | Competitors | C92: Face Care | D92: Enabled | E92: AG | Face Wash | F92: Sponsored Products | G92: asin=B0TKJHQZF8 | H92: Product | I92: b0tkjhqzf8 | J92: SKN-008 | K92: Product Pages | L92: 379 | M92: 0 | N92: 0 | P92: 0 | Q92: 0 | R92: 0 | S92: 0 | W92: 8.5 | X92: INR | Y92: India
A93: 46266 | B93: SP | Product Targeting | Competitors | C93: Face Care | D93: Enabled | E93: AG | Face Wash | F93: Sponsored Products | G93: asin=B0KPJX3WRU | H93: Product | I93: b0kpjx3wru | J93: SKN-008 | K93: Product Pages | L93: 523 | M93: 4 | N93: 0.0076481836 | O93: 4.45 | P93: 17.8 | Q93: 0 | R93: 0 | S93: 0 | U93: 0 | V93: 0 | W93: 6.5 | X93: ₹ | Y93: India
A94: 46266 | B94: SP | Product Targeting | Competitors | C94: Face Care | D94: Enabled | E94: AG | Face Wash | F94: Sponsored Products | G94: asin=B0WEZFTACN | H94: Product | I94: b0wezftacn | J94: SKN-008 | K94: Top of Search | L94: 717 | M94: 7 | N94: 0.009762901 | O94: 8.16 | P94: 57.12 | Q94: 0 | R94: 0 | S94: 0 | U94: 0 | V94: 0 | W94: 8.5 | X94: INR | Y94: India
A95: 46266 | B95: SP | Product Targeting | Competitors | C95: Face Care | D95: Enabled | E95: AG | Face Wash | F95: Sponsored Products | G95: asin=B0HA6DL3DM | H95: Product | I95: b0ha6dl3dm | J95: SKN-008 | K95: Product Pages | L95: 288 | M95: 1 | N95: 0.0034722222 | O95: 4.85 | P95: 4.85 | Q95: 0 | R95: 0 | S95: 0 | U95: 0 | V95: 0 | W95: 7 | X95: INR | Y95: India
A96: 46266 | B96: SP | Product Targeting | Competitors | C96: Face Care | D96: Enabled | E96: AG | Face Wash | F96: Sponsored Products | G96: asin=B0KHT5RJ8U | H96: Product | I96: b0kht5rj8u | J96: SKN-008 | K96: Product Pages | L96: 782 | M96: 3 | N96: 0.0038363171 | O96: 4 | P96: 12 | Q96: 0 | R96: 0 | S96: 0 | U96: 0 | V96: 0 | W96: 7 | X96: INR | Y96: India
A97: 46266 | B97: SP | Manual | Lips & Eyes | Exact | C97: Face Care | D97: Enabled | E97: AG | Under Eye Cream | F97: Sponsored Products | G97: under eye cream | H97: Exact | I97: under eye cream | J97: SKN-011 | K97: Top of Search | L97: 364 | M97: 1 | N97: 0.0027472527 | O97: 11.5 | P97: 11.5 | Q97: 0 | R97: 0 | S97: 0 | U97: 0 | V97: 0 | W97: 11.5 | X97: INR | Y97: India
A98: 46266 | B98: SP | Manual | Lips & Eyes | Exact | C98: Face Care | D98: Enabled | E98: AG | Lip Balm | F98: Sponsored Products | G98: lip balm | H98: Exact | I98: lip balm | J98: SKN-015 | K98: Rest of Search | L98: 4228 | M98: 36 | N98: 0.0085146641 | O98: 4.88 | P98: 175.68 | Q98: 199 | R98: 1 | S98: 1 | T98: 0.8828 | U98: 1.13 | V98: 0.0278 | W98: 6 | X98: INR | Y98: India
A99: 46266 | B99: SP | Manual | Lips & Eyes | Exact | C99: Face Care | D99: Enabled | E99: AG | Lip Sleeping Mask | F99: Sponsored Products | G99: lip sleeping mask | H99: Exact | I99: lip sleeping mask | J99: SKN-016 | K99: Rest of Search | L99: 2186 | M99: 13 | N99: 0.005946935 | O99: 7.95 | P99: 103.35 | Q99: 0 | R99: 0 | S99: 0 | U99: 0 | V99: 0 | W99: 10 | X99: INR | Y99: India
A100: 46266 | B100: SP | Manual | Lips & Eyes | Exact | C100: Face Care | D100: Enabled | E100: AG | Lip Sleeping Mask | F100: Sponsored Products | G100: lip sleeping mask for winter | H100: exact | I100: lip sleeping mask for winter | J100: SKN-016 | K100: Rest of Search | L100: 345 | M100: 4 | N100: 0.011594203 | O100: 5.62 | P100: 22.48 | Q100: 598 | R100: 2 | S100: 2 | T100: 0.0376 | U100: 26.6 | V100: 0.5 | W100: 10 | X100: INR | Y100: India
...

Sheet Product_Master
A1: Product_Master
A2: Selling price, cost and Amazon fees are in ₹ per unit. Net margin before ads = Price - Cost - Fees.
A4: SKU | B4: ASIN | C4: Product Name | D4: Sub-Category | E4: Selling Price (₹) | F4: Product Cost (₹) | G4: Amazon Fees (₹) | H4: Stock Status | I4: Rating | J4: Reviews
A5: SKN-001 | B5: B0F29326ML | C5: Auralis Vitamin C Face Serum 30ml | D5: Face Serum | E5: 599 | F5: 216 | G5: 144 | H5: In Stock | I5: 4.5 | J5: 2849
A6: SKN-002 | B6: B0F64LG2TJ | C6: Auralis Niacinamide 10% Face Serum 30ml | D6: Face Serum | E6: 549 | F6: 192 | G6: 139 | H6: In Stock | I6: 4 | J6: 1762
A7: SKN-003 | B7: B0FF8CZ2KA | C7: Auralis Hyaluronic Acid Face Serum 30ml | D7: Face Serum | E7: 649 | F7: 234 | G7: 148 | H7: In Stock | I7: 4.5 | J7: 1122
A8: SKN-004 | B8: B0F7EDCMPB | C8: Auralis Retinol Night Cream 50g | D8: Night Cream | E8: 799 | F8: 272 | G8: 162 | H8: In Stock | I8: 4.1 | J8: 4750
A9: SKN-005 | B9: B0F3U2M7OS | C9: Auralis Oil-Free Gel Moisturiser 100g | D9: Moisturiser | E9: 399 | F9: 148 | G9: 126 | H9: In Stock | I9: 4.6 | J9: 2128
A10: SKN-006 | B10: B0F5AF3R09 | C10: Auralis Sunscreen SPF 50 PA++++ 50g | D10: Sunscreen | E10: 449 | F10: 162 | G10: 130 | H10: In Stock | I10: 4 | J10: 4281
A11: SKN-007 | B11: B0FFQUO6SB | C11: Auralis Tinted Sunscreen SPF 40 50g | D11: Sunscreen | E11: 549 | F11: 203 | G11: 139 | H11: In Stock | I11: 3.9 | J11: 2473
A12: SKN-008 | B12: B0FEGZGSYE | C12: Auralis Foaming Face Wash 150ml | D12: Face Wash | E12: 299 | F12: 114 | G12: 107 | H12: In Stock | I12: 3.9 | J12: 4252
A13: SKN-009 | B13: B0FBANND4Y | C13: Auralis Salicylic Acid Face Wash 100ml | D13: Face Wash | E13: 279 | F13: 106 | G13: 105 | H13: In Stock | I13: 4 | J13: 1746
A14: SKN-010 | B14: B0FZ0EMRVF | C14: Auralis Rose Water Toner 200ml | D14: Toner | E14: 249 | F14: 100 | G14: 102 | H14: In Stock | I14: 4.3 | J14: 3363
A15: SKN-011 | B15: B0FTVA0HIP | C15: Auralis Under Eye Cream 15g | D15: Eye Care | E15: 499 | F15: 180 | G15: 125 | H15: In Stock | I15: 4 | J15: 2813
A16: SKN-012 | B16: B0FGAD35L9 | C16: Auralis Clay Face Mask 100g | D16: Face Mask | E16: 379 | F16: 140 | G16: 114 | H16: In Stock | I16: 4 | J16: 4693
... A29: SKN-026 | B29: B0FQ61J0AC | C29: Auralis Bath Salt Scrub 250g | D29: Body Care | E29: 379 | F29: 140 | G29: 90 | H29: Discontinued | I29: 4 | J29: 310

Sheet Campaign_List
A1: Campaign_List
A2: All Sponsored Products campaigns in the account.
A4: Campaign Name | B4: Targeting Type | C4: Portfolio | D4: Daily Budget (₹) | E4: Status | F4: Paused On | G4: Objective
A5: SP | Auto | Face Care | B5: Auto | C5: Face Care | D5: 950 | E5: Enabled | G5: Discover new search terms
A6: SP | Auto | Body & Hair | B6: Auto | C6: Body & Hair | D6: 650 | E6: Enabled | G6: Discover new search terms
A7: SP | Manual | Face Serums | Exact | B7: Manual | C7: Face Care | D7: 1550 | E7: Enabled | G7: Scale proven terms
A8: SP | Manual | Face Serums | Broad | B8: Manual | C8: Face Care | D8: 600 | E8: Enabled | G8: Explore variations
A9: SP | Manual | Sunscreen | Phrase | B9: Manual | C9: Face Care | D9: 400 | E9: Enabled | G9: Explore variations
A10: SP | Manual | Skincare Essentials | Broad | B10: Manual | C10: Face Care | D10: 550 | E10: Enabled | G10: Explore variations
A11: SP | Manual | Hair Care | Phrase | B11: Manual | C11: Body & Hair | D11: 500 | E11: Enabled | G11: Explore variations
A12: SP | Manual | Body Care | Exact | B12: Manual | C12: Body & Hair | D12: 800 | E12: Enabled | G12: Scale proven terms
A13: SP | Product Targeting | Competitors | B13: Product Targeting | C13: Face Care | D13: 300 | E13: Enabled | G13: Compete on rival product pages
A14: SP | Manual | Lips & Eyes | Exact | B14: Manual | C14: Face Care | D14: 700 | E14: Enabled | G14: Scale proven terms
A15: SP | Manual | Masks & Gels | Broad | B15: Manual | C15: Face Care | D15: 100 | E15: Paused | F15: 46283 | G15: Explore variations
A16: SP | Brand Defence | Exact | B16: Manual | C16: Brand | D16: 450 | E16: Enabled | G16: Protect brand searches

Sheet Seller_Notes
A1: Seller_Notes — message from the seller (Auralis Naturals)
A3: Hi team, thanks for taking this on. Here is the export for September. I want to grow, but profit matters more to me than sales.
A4: My question: my ACOS feels worse towards the end of the month. Is that true, and why?
A5: Please tell me where I am wasting money, what is working, and what you would change first.
A6: Reporting period: 1-28 September 2026. Week 1 = 1-7 Sep, Week 2 = 8-14 Sep, Week 3 = 15-21 Sep, Week 4 = 22-28 Sep.
A8: Rules for the Action_List
A9: Rule | B9: Name | C9: Condition (per campaign + search term, whole period, after cleaning) | D9: Action | E9: Note
A10: R4 | B10: Competitor brand terms | C10: Any search term that contains a competitor brand name (list below) and has spend of ₹100 or more in a campaign. | D10: Negate (add as negative keyword) | E10: Check this rule FIRST. A term caught by R4 should not be counted again under R1-R3.
A11: R1 | B11: Wasted spend | C11: A search term in a campaign with 40 or more clicks and 0 orders over the whole period. | D11: Pause / negate | E11: Saving = spend on that term in the period.
A12: R2 | B12: Under-bid winners | C12: 4 or more orders and ACOS below half of the product's break-even ACOS. | D12: Increase bid by 15% | E12: Estimate the gain only if you can justify it; otherwise leave blank.
A13: R3 | B13: Over-paying | C13: 4 or more orders and ACOS above the product's break-even ACOS. | D13: Reduce bid by 20% | E13: Leave saving blank or estimate with a stated assumption.
A15: Exceptions
A16: 1. Do not recommend any action for the campaign 'SP | Brand Defence | Exact'. I protect my own brand name and want it left alone.
A17: 2. Do not recommend actions for campaigns that are Paused (see Campaign_List).
A18: 3. Search terms are not case sensitive: treat 'Vitamin C Serum' and 'vitamin c serum' as the same term.
A19: 4. Break-even ACOS = (Selling Price - Product Cost - Amazon Fees) / Selling Price, from Product_Master.
A21: Competitor brand names
A22: Dermavault, Glowkind, Pureroots, Botanica Nine, Skinlore, Veluna, Mistral Herbals
A24: Data note: the export contains rows from two columns the tool pre-calculated (CTR, ACOS, ROAS, CVR). I cannot say they are all correct.

Sheet Cleaning_Log
A1: Cleaning_Log
A2: Fill in the yellow cells. One row per issue. Delete the example row.
A4: # | B4: Issue found | C4: Column / where | D4: Approx. rows affected | E4: What I did | F4: Why / assumption
A5: 1 | B5: Completely blank rows | C5: clean_data | D5: 4 | E5: deleted rows with no data in any column | F5: Removed entirely blank rows because they contain no useful information and can interfere with data filtering and analysis
A6: 2 | B6: Duplicate rows | C6: clean _data | D6: 37 | E6: used remove duplicates with all selected | F6: Retained the first occurrence of each identical row
A7: 3 | B7: Inconsistent date formats | C7: clean _data | D7: all | E7: Converted dates using Text to Columns with DMY format | F7: To ensure Excel recognizes dates correctly for weekly analysis.
A8: 4 | B8: total row named row found | C8: clean _data | D8: 1 | E8: removed it | F8: To prevent summary figures from being counted again in the analysis.
A9: 5 | B9: Inconsistent Match Type labels and extra spaces | C9: clean _data (Column H) | D9: all | E9: Used TRIM and UPPER to standardize text, then removed the MATCH suffix where applicable | F9: To ensure equivalent match types use consistent tabels and can be analysed acurately using pivot tables
A10: 6 | B10: Inconsistent SKU capitalization and extra spaces | C10: clean_data (Column J) | D10: all | E10: Used TRIM and UPPER, then pasted the cleaned values into column J | F10: To ensure the same product SKU is represented consistently, avoiding incorrect product-level grouping and lookup mismatches.
A11: 7 | B11: Inconsistent currency labels | C11: clean_data (Column X) | D11: all | E11: Standardized currency labels to INR | F11: The dataset represents Indian rupees, so equivalent currency labels were standardized to avoid inconsistent grouping.
A12: 8 | B12: Currency symbols and text-formatted Spend values | C12: clean_data(Column P) | D12: all | E12: Removed currency symbols and commas and converted values to numbers | F12: To ensure Spend values can be summed and used in advertising calculations while preserving negative refund amounts.
A13: 9 | B13: Missing Campaign Name | C13: Clean_data(Column B) | D13: 5 | E13: Identified and retained five records with blank campaign names for investigation | F13: The records contain useful advertising metrics. Deleting them would lose valid data, and campaign names cannot be reliably inferred from the Ad Group alone.
A14: 10 | B14: Inconsistent Customer Search Term capitalization and extra spaces | C14: Clean_data(Column I) | D14: all | E14: Used LOWER and TRIM to standardize capitalization and remove extra spaces, then pasted cleaned values into column I | F14: To ensure identical search terms are grouped consistently during search-term analysis.
A15: 11 | B15: Inconsistent Targeting Capitalization and extra spaces | C15: Clean Data ( Column G) | D15: all | E15: Used LOWER and TRIM to standardize capitalization and remove extra spaces, then pasted cleaned values into column G | F15: To improve consistency while preserving distinct targeting values and ASINs.
A16: 12 | B16: Impressions stored as text | C16: Clean Data ( Column L) | D16: 60 | E16: Converted text-formatted impression values into numbers | F16: To ensure impressions can be summed and used accurately in advertising performance calculations.
A17: 13 | B17: Inconsistent Region labels | C17: Clean_data( Column Y) | D17: 41 | E17: Standardized IN to India using Find and Replace, with Match entire cell contents enabled. | F17: Consistent region labels are required for accurate grouping and analysis.
A18: 14 | B18: Missing Product SKUs | C18: Clean data(column J) | D18: 6 | E18: Identified and retained six records with blank Product SKU values. Product lookup fields and Break-even ACOS remain blank, and Performance Status is set to Cost missing. | F18: Therecords contain useful advertising metrics, but the correct SKU cannot be confirmed from the available fields. Guessing values could lead to inaccurate product-level profitability analysis.
A19: 15 | B19: Missing Customer Search Term | C19: Clean data (column I) | D19: 6 | E19: Identified and retained six records with blank Customer Search Term values for investigation. | F19: These records contain useful advertising data. For AUTO targeting, a missing customer search term may require investigation; for other targeting types, the source data should be checked before assigning a value.
A20: 16 | B20: CTR greater than 100% | C20: Clean data (column N) | D20: 6 | E20: Identified six records where clicks exceed impressions. Retained the original values and flagged them for investigation. | F20: CTR is calculated as Clicks ÷ Impressions. The source values are inconsistent, and the correct values cannot be determined without verification.
A21: 17 | B21: Incorrect ACOS value | C21: Clean data (Column T) | D21: 1 | E21: Identified a mismatch between the reported ACOS of 480.00% and the value calculated from Spend and Sales (4.83%). Flagged the record for recalculation. | F21: ACOS is calculated as Spend ÷ Sales .The original value will be replaced by a formula during the metric-calculation stage.
A22: 18 | B22: Three dates had an incorrect year | C22: Clean data(column A) | D22: 3 | E22: Cross-checked against the original report and corrected the year to 2026 | F22: The reporting period is 1–28 September 2026
A23: 19 | B23: Paused campaign with post-pause reporting dates | C23: clean_data — Campaign Name, Campaign Status, Date | E23: Identified nine records dated 22–27 September 2026 for SP | Manual | Masks & Gels | Broad, which is marked Paused. Cross-checked Campaign_List, confirming a pause date of 18 September 2026. Retained the records pending clarification | F23: The records contain ₹598.44 in spend and zero reported sales. Their reporting dates are later than the recorded pause date, but the available data does not establish when the advertising activity occurred. The records have therefore been retained rather than deleted
A24: 20 | B24: Calculated metrics and lookup columns | C24: Clean_Data columns N,O,T,U,V,AA,AB,AC,AD:AG | E24: Replaced pre-filled metrics with formulas; used VLOOKUP against Product_lookup for compatibility; status prioritizes negative spend as Review and uses strict ACOS < break-even for Profitable. | F24: Profit is unavailable where SKU economics are missing; no costs were guessed.

Sheet Summary
A1: Summary
A2: Write your note (maximum 150 words) in cell A4. Then, in cell A8, list anything you were unsure about.
A3: Note to the seller:
A4: ACOS worsened at the end of September: it rose from 29.74% in Week 3 to 40.01% in Week 4. Week 4 spend increased to ₹43,970.92 while attributed sales fell to ₹109,907 and orders fell to 204; conversion rate also declined. Overall, the report shows ₹162,371.65 spend against ₹493,863 sales (32.88% ACOS; 3.04 ROAS). The first priority is to stop avoidable spend: review high-click, zero-order search terms and irrelevant searches, then apply the seller's R4 competitor-term rule first. Scale terms that meet R2 and reduce bids on R3 terms with at least four orders but ACOS above break-even. Exact-match traffic has the strongest overall return among match types, while product targeting is weakest. Profit totals are partial where SKU economics are missing, so fill the product-master gap before using those rows for profitability decisions.
A7: What I was unsure about / assumptions:
A8: Assumptions / uncertainties: 56 rows have blank SKU or SKN-024, which is absent from Product_Master; profit after ads is excluded for those rows rather than guessed. The export includes 90 rows for SP | Manual | Masks & Gels | Broad even though Campaign_List says it was paused on 18 Sep; retained in historical analysis but excluded from recommendations. Week definitions follow Seller_Notes. Bid changes are recommendations only; savings/gains are not guaranteed.

Sheet campaign-level PivotTable
A3: Row Labels | B3: Total Orders | C3: Total Units | D3: Impressions | E3: Total Sales (₹) | F3: Total Clicks | G3: Total AD Spend (₹) | H3: Campaign ACOS | I3: Campaign ROAS | J3: Profit after ads (₹)
A4: SP | Auto | Body & Hair | B4: 86 | C4: 91 | D4: 222466 | E4: 37629 | F4: 1994 | G4: 15368.21 | H4: =IF(E4=0,"",G4/E4) -> 0.40841399 | I4: =IF(G4=0,"",E4/G4) -> 2.448496 | J4: -3765.21
A5: SP | Auto | Face Care | B5: 85 | C5: 93 | D5: 278645 | E5: 41257 | F5: 2462 | G5: 20601.43 | H5: =IF(E5=0,"",G5/E5) -> 0.49934387 | I5: =IF(G5=0,"",E5/G5) -> 2.002628 | J5: -6311.43
A6: SP | Brand Defence | Exact | B6: 132 | C6: 148 | D6: 61027 | E6: 105902 | F6: 1310 | G6: 9259.88 | H6: =IF(E6=0,"",G6/E6) -> 0.087438198 | I6: =IF(G6=0,"",E6/G6) -> 11.436649 | J6: 18190.28
A7: SP | Manual | Body Care | Exact | B7: 134 | C7: 144 | D7: 258805 | E7: 46206 | F7: 2041 | G7: 16976.15 | H7: =IF(E7=0,"",G7/E7) -> 0.36740142 | I7: =IF(G7=0,"",E7/G7) -> 2.7218186 | J7: -3972.65
A8: SP | Manual | Face Serums | Broad | B8: 60 | C8: 66 | D8: 129859 | E8: 40884 | F8: 1044 | G8: 12651.35 | H8: =IF(E8=0,"",G8/E8) -> 0.30944502 | I8: =IF(G8=0,"",E8/G8) -> 3.2315919 | J8: 3941.65
A9: SP | Manual | Face Serums | Exact | B9: 121 | C9: 134 | D9: 231533 | E9: 88116 | F9: 2140 | G9: 32417.17 | H9: =IF(E9=0,"",G9/E9) -> 0.36789198 | I9: =IF(G9=0,"",E9/G9) -> 2.7181892 | J9: 4401.07
A10: SP | Manual | Hair Care | Phrase | B10: 40 | C10: 42 | D10: 134137 | E10: 19248 | F10: 1094 | G10: 10362.29 | H10: =IF(E10=0,"",G10/E10) -> 0.53835671 | I10: =IF(G10=0,"",E10/G10) -> 1.8575045 | J10: -3816.29
A11: SP | Manual | Lips & Eyes | Exact | B11: 150 | C11: 169 | D11: 207873 | E11: 53031 | F11: 1791 | G11: 14632.23 | H11: =IF(E11=0,"",G11/E11) -> 0.27591843 | I11: =IF(G11=0,"",E11/G11) -> 3.6242596 | J11: 1564.77
A12: SP | Manual | Masks & Gels | Broad | B12: 14 | C12: 15 | D12: 63997 | E12: 4905 | F12: 426 | G12: 2983.76 | H12: =IF(E12=0,"",G12/E12) -> 0.60830989 | I12: =IF(G12=0,"",E12/G12) -> 1.643899 | J12: -1636.76
A13: SP | Manual | Skincare Essentials | Broad | B13: 91 | C13: 93 | D13: 2685397 | E13: 31337 | F13: 1862 | G13: 12259.85 | H13: =IF(E13=0,"",G13/E13) -> 0.39122603 | I13: =IF(G13=0,"",E13/G13) -> 2.5560672 | J13: -3421.19
A14: SP | Manual | Sunscreen | Phrase | B14: 35 | C14: 38 | D14: 99424 | E14: 19162 | F14: 805 | G14: 8723.67 | H14: =IF(E14=0,"",G14/E14) -> 0.45525885 | I14: =IF(G14=0,"",E14/G14) -> 2.1965526 | J14: -1707.67
A15: SP | Product Targeting | Competitors | B15: 10 | C15: 10 | D15: 189188 | E15: 4790 | F15: 875 | G15: 6016.81 | H15: =IF(E15=0,"",G15/E15) -> 1.256119 | I15: =IF(G15=0,"",E15/G15) -> 0.79610292 | J15: -4273.81
A16: (blank) | B16: 3 | C16: 4 | D16: 2625 | E16: 1396 | F16: 15 | G16: 118.85 | H16: =IF(E16=0,"",G16/E16) -> 0.085136103 | I16: =IF(G16=0,"",E16/G16) -> 11.745898
A17: Grand Total | B17: 961 | C17: 1047 | D17: 4564976 | E17: 493863 | F17: 17859 | G17: 162371.65 | H17: =IF(E17=0,"",G17/E17) -> 0.32877873 | I17: =IF(G17=0,"",E17/G17) -> 3.0415593 | J17: -489.09

Sheet Match-Type Analysis PivotTable
A3: Row Labels | B3: Sum of 7 Day Total Units | C3: Sum of 7 Day Total Orders | D3: Sum of Impressions | E3: Sum of 7 Day Total Sales (₹) | F3: Sum of Clicks | G3: Sum of Spend (₹) | H3: Match_Type_ACOS | I3: Match Type ROAS | J3: Profit after ads (₹)
A4: AUTO | B4: 184 | C4: 171 | D4: 501253 | E4: 78886 | F4: 4456 | G4: 35969.64 | H4: =IF(E4=0,"",G4/E4) -> 0.45596988 | I4: =IF(G4=0,"",E4/G4) -> 2.1931273 | J4: -10076.64
A5: BROAD | B5: 174 | C5: 165 | D5: 2879253 | E5: 77126 | F5: 3332 | G5: 27894.96 | H5: =IF(E5=0,"",G5/E5) -> 0.36168037 | I5: =IF(G5=0,"",E5/G5) -> 2.7648722 | J5: -1116.3
A6: EXACT | B6: 599 | C6: 540 | D6: 761721 | E6: 294651 | F6: 7297 | G6: 73404.28 | H6: =IF(E6=0,"",G6/E6) -> 0.24912279 | I6: =IF(G6=0,"",E6/G6) -> 4.0140847 | J6: 20501.62
A7: PHRASE | B7: 80 | C7: 75 | D7: 233561 | E7: 38410 | F7: 1899 | G7: 19085.96 | H7: =IF(E7=0,"",G7/E7) -> 0.49690081 | I7: =IF(G7=0,"",E7/G7) -> 2.0124741 | J7: -5523.96
A8: PRODUCT | B8: 10 | C8: 10 | D8: 189188 | E8: 4790 | F8: 875 | G8: 6016.81 | H8: =IF(E8=0,"",G8/E8) -> 1.256119 | I8: =IF(G8=0,"",E8/G8) -> 0.79610292 | J8: -4273.81
A9: Grand Total | B9: 1047 | C9: 961 | D9: 4564976 | E9: 493863 | F9: 17859 | G9: 162371.65 | H9: =IF(E9=0,"",G9/E9) -> 0.32877873 | I9: =IF(G9=0,"",E9/G9) -> 3.0415593 | J9: -489.09

Sheet Placement Analysis PivotTable
A3: Row Labels | B3: Sum of 7 Day Total Units | C3: Sum of Impressions | D3: Sum of 7 Day Total Orders | E3: Sum of 7 Day Total Sales (₹) | F3: Sum of Spend (₹) | G3: Sum of Clicks | H3: Placement ACOS | I3: Placement ROAS | J3: Profit after ads (₹)
A4: Product Pages | B4: 223 | C4: 666850 | D4: 207 | E4: 97437 | F4: 34993.87 | G4: 4692 | H4: =IF(E4=0,"",F4/E4) -> 0.35914355 | I4: =IF(F4=0,"",E4/F4) -> 2.784402 | J4: -3055.48
A5: Rest of Search | B5: 374 | C5: 1005042 | D5: 341 | E5: 180536 | F5: 56866.21 | G5: 6890 | H5: =IF(E5=0,"",F5/E5) -> 0.31498543 | I5: =IF(F5=0,"",E5/F5) -> 3.17475 | J5: 1287.92
A6: Top of Search | B6: 450 | C6: 2893084 | D6: 413 | E6: 215890 | F6: 70511.57 | G6: 6277 | H6: =IF(E6=0,"",F6/E6) -> 0.32660878 | I6: =IF(F6=0,"",E6/F6) -> 3.061767 | J6: 1278.47
A7: Grand Total | B7: 1047 | C7: 4564976 | D7: 961 | E7: 493863 | F7: 162371.65 | G7: 17859 | H7: =IF(E7=0,"",F7/E7) -> 0.32877873 | I7: =IF(F7=0,"",E7/F7) -> 3.0415593 | J7: -489.09

Sheet Search_Term_Analysis
A1: Row Labels | B1: Sum of Impressions | C1: Sum of 7 Day Total Units | D1: Sum of 7 Day Total Orders | E1: Sum of 7 Day Total Sales (₹) | F1: Sum of Clicks | G1: Sum of Spend (₹) | H1: Search Term ACOS | I1: Action Check
A2: body lotion | B2: 45626 | C2: 20 | D2: 18 | E2: 8980 | F2: 527 | G2: 6390.5 | H2: =IF(E2=0,"",G2/E2) -> 0.71163697 | I2: =IF(AND(E2=0,G2>0),"Review","")
A3: niacinamide serum | B3: 54128 | C3: 0 | D3: 0 | E3: 0 | F3: 556 | G3: 5911.46 | H3: =IF(E3=0,"",G3/E3) | I3: =IF(AND(E3=0,G3>0),"Review","") -> Review
A4: hyaluronic acid serum | B4: 45109 | C4: 38 | D4: 35 | E4: 24662 | F4: 394 | G4: 5321.04 | H4: =IF(E4=0,"",G4/E4) -> 0.21575866 | I4: =IF(AND(E4=0,G4>0),"Review","")
A5: vitamin c serum | B5: 35988 | C5: 19 | D5: 17 | E5: 11381 | F5: 378 | G5: 5286.13 | H5: =IF(E5=0,"",G5/E5) -> 0.46446973 | I5: =IF(AND(E5=0,G5>0),"Review","")
A6: retinol night cream | B6: 37906 | C6: 15 | D6: 13 | E6: 11985 | F6: 313 | G6: 4913.2 | H6: =IF(E6=0,"",G6/E6) -> 0.40994577 | I6: =IF(AND(E6=0,G6>0),"Review","")
A7: hyaluronic serum | B7: 24437 | C7: 45 | D7: 40 | E7: 29205 | F7: 298 | G7: 4851.51 | H7: =IF(E7=0,"",G7/E7) -> 0.16611916 | I7: =IF(AND(E7=0,G7>0),"Review","")
A8: gel moisturizer | B8: 48630 | C8: 19 | D8: 19 | E8: 7581 | F8: 458 | G8: 4127.99 | H8: =IF(E8=0,"",G8/E8) -> 0.54451787 | I8: =IF(AND(E8=0,G8>0),"Review","")
A9: lip sleeping mask | B9: 40604 | C9: 4 | D9: 3 | E9: 1196 | F9: 402 | G9: 3018.02 | H9: =IF(E9=0,"",G9/E9) -> 2.5234281 | I9: =IF(AND(E9=0,G9>0),"Review","")
A10: vit c face serum | B10: 21780 | C10: 12 | D10: 11 | E10: 7188 | F10: 268 | G10: 2864.44 | H10: =IF(E10=0,"",G10/E10) -> 0.39850306 | I10: =IF(AND(E10=0,G10>0),"Review","")
A11: retinol cream | B11: 15167 | C11: 1 | D11: 1 | E11: 799 | F11: 165 | G11: 2794.44 | H11: =IF(E11=0,"",G11/E11) -> 3.4974218 | I11: =IF(AND(E11=0,G11>0),"Review","")
A12: sunscreen | B12: 15301 | C12: 2 | D12: 2 | E12: 898 | F12: 208 | G12: 2476.44 | H12: =IF(E12=0,"",G12/E12) -> 2.7577283 | I12: =IF(AND(E12=0,G12>0),"Review","")
A13: body wash | B13: 47088 | C13: 17 | D13: 16 | E13: 5933 | F13: 372 | G13: 2410.28 | H13: =IF(E13=0,"",G13/E13) -> 0.40624979 | I13: =IF(AND(E13=0,G13>0),"Review","")
... A72: spf 50 sunscreen for face | B72: 7536 | C72: 0 | D72: 0 | E72: 0 | F72: 60 | G72: 562.61 | H72: =IF(E72=0,"",G72/E72) | I72: =IF(AND(E72=0,G72>0),"Review","") -> Review
B73: 7493 | C73: 6 | D73: 6 | E73: 2494 | F73: 64 | G73: 562.15 | H73: =IF(E73=0,"",G73/E73) -> 0.22540096 | I73: =IF(AND(E73=0,G73>0),"Review","")
A74: auralis naturals kumkumadi oil | B74: 3245 | C74: 5 | D74: 3 | E74: 6495 | F74: 47 | G74: 558.08 | H74: =IF(E74=0,"",G74/E74) -> 0.085924557 | I74: =IF(AND(E74=0,G74>0),"Review","")
A75: oil free moisturizer | B75: 9392 | C75: 9 | D75: 8 | E75: 3591 | F75: 68 | G75: 554.97 | H75: =IF(E75=0,"",G75/E75) -> 0.1545447 | I75: =IF(AND(E75=0,G75>0),"Review","")
A76: hyaluronic serum for sensitive skin | B76: 5305 | C76: 0 | D76: 0 | E76: 0 | F76: 31 | G76: 542.44 | H76: =IF(E76=0,"",G76/E76) | I76: =IF(AND(E76=0,G76>0),"Review","") -> Review
A77: night cream for face for dry skin | B77: 3317 | C77: 2 | D77: 2 | E77: 1598 | F77: 28 | G77: 539.18 | H77: =IF(E77=0,"",G77/E77) -> 0.33740926 | I77: =IF(AND(E77=0,G77>0),"Review","")
A78: spf 50 sunscreen for face price | B78: 2733 | C78: 6 | D78: 4 | E78: 2694 | F78: 88 | G78: 538.99 | H78: =IF(E78=0,"",G78/E78) -> 0.20007053 | I78: =IF(AND(E78=0,G78>0),"Review","")
A79: auralis sunscreen | B79: 4258 | C79: 7 | D79: 7 | E79: 3143 | F79: 118 | G79: 537.14 | H79: =IF(E79=0,"",G79/E79) -> 0.17090041 | I79: =IF(AND(E79=0,G79>0),"Review","")
A80: retinol cream combo | B80: 3154 | C80: 0 | D80: 0 | E80: 0 | F80: 38 | G80: 535.04 | H80: =IF(E80=0,"",G80/E80) | I80: =IF(AND(E80=0,G80>0),"Review","") -> Review
A81: face cream for dogs | B81: 9573 | C81: 0 | D81: 0 | E81: 0 | F81: 61 | G81: 521.81 | H81: =IF(E81=0,"",G81/E81) | I81: =IF(AND(E81=0,G81>0),"Review","") -> Review
A82: gel moisturizer dermatologist tested | B82: 4843 | C82: 2 | D82: 2 | E82: 798 | F82: 58 | G82: 508.69 | H82: =IF(E82=0,"",G82/E82) -> 0.63745614 | I82: =IF(AND(E82=0,G82>0),"Review","")
A83: niacinamide serum for teenagers | B83: 7368 | C83: 0 | D83: 0 | E83: 0 | F83: 41 | G83: 498.45 | H83: =IF(E83=0,"",G83/E83) | I83: =IF(AND(E83=0,G83>0),"Review","") -> Review
A84: b0q7ldyo0l | B84: 11524 | C84: 0 | D84: 0 | E84: 0 | F84: 66 | G84: 495.85 | H84: =IF(E84=0,"",G84/E84) | I84: =IF(AND(E84=0,G84>0),"Review","") -> Review
A85: dark circles cream for beginners | B85: 4335 | C85: 0 | D85: 0 | E85: 0 | F85: 46 | G85: 485.88 | H85: =IF(E85=0,"",G85/E85) | I85: =IF(AND(E85=0,G85>0),"Review","") -> Review
... A530: Grand Total | B530: 4564976 | C530: 1047 | D530: 961 | E530: 493863 | F530: 17859 | G530: 162371.65 | H530: =IF(E530=0,"",G530/E530) -> 0.32877873 | I530: =IF(AND(E530=0,G530>0),"Review","")

Sheet Clean_Data
A1: Date | B1: Campaign Name | C1: Portfolio | D1: Campaign Status | E1: Ad Group | F1: Ad Format | G1: Targeting | H1: Match Type | I1: Customer Search Term | J1: Product SKU | K1: Placement | L1: Impressions | M1: Clicks | N1: CTR | O1: CPC (₹) | P1: Spend (₹) | Q1: 7 Day Total Sales (₹) | R1: 7 Day Total Orders | S1: 7 Day Total Units | T1: ACOS | U1: ROAS | V1: CVR | W1: Bid (₹) | X1: Currency | Y1: Region | Z1: Notes | AA1: Week No. | AB1: Profit after ads (₹) | AC1: Row Status | AD1: Selling_Price | AE1: Product_cost | AF1: Amazon_fees | AG1: Break-even ACOS
A2: 46266 | B2: SP | Auto | Face Care | C2: Face Care | D2: Enabled | E2: AG | Vitamin C Serum | F2: Sponsored Products | G2: close-match | H2: AUTO | I2: best face serum vitamin c | J2: SKN-001 | K2: Top of Search | L2: 125 | M2: 4 | N2: =IF(L2=0,"",M2/L2) -> 0.032 | O2: =IF(M2=0,"",P2/M2) -> 15.54 | P2: 62.16 | Q2: 0 | R2: 0 | S2: 0 | T2: =IF(Q2=0,"",P2/Q2) | U2: =IF(P2=0,"",Q2/P2) -> 0 | V2: =IF(M2=0,"",R2/M2) -> 0 | W2: 17.5 | X2: INR | Y2: India | AA2: =IF(OR(A2<DATE(2026,9,1),A2>DATE(2026,9,28)),"Check Date",INT((A2-DATE(2026,9,1))/7)+1) -> 1 | AB2: =IF(OR(AD2="",AE2="",AF2=""),"",S2*(AD2-AE2-AF2)-P2) -> -62.16 | AC2: =IF(P2<0,"Review",IF(OR(AD2="",AE2="",AF2=""),"Cost missing",IF(P2=0,"No Spend",IF(Q2=0,"No Sales",IF(P2/Q2<AG2,"Profitable","Losing"))))) -> No Sales | AD2: =IFERROR(VLOOKUP(J2,Product_lookup!$A:$G,5,FALSE),"") -> 599 | AE2: =IFERROR(VLOOKUP(J2,Product_lookup!$A:$G,6,FALSE),"") -> 216 | AF2: =IFERROR(VLOOKUP(J2,Product_lookup!$A:$G,7,FALSE),"") -> 144 | AG2: =IFERROR((AD2-AE2-AF2)/AD2,"") -> 0.39899833
A3: 46266 | B3: SP | Auto | Face Care | C3: Face Care | D3: Enabled | E3: AG | Niacinamide Serum | F3: Sponsored Products | G3: loose-match | H3: AUTO | I3: niacinamide serum with vitamin e | J3: SKN-002 | K3: Top of Search | L3: 300 | M3: 4 | N3: =IF(L3=0,"",M3/L3) -> 0.013333333 | O3: =IF(M3=0,"",P3/M3) -> 16.5 | P3: 66 | Q3: 0 | R3: 0 | S3: 0 | T3: =IF(Q3=0,"",P3/Q3) | U3: =IF(P3=0,"",Q3/P3) -> 0 | V3: =IF(M3=0,"",R3/M3) -> 0 | W3: 16.5 | X3: INR | Y3: India | AA3: =IF(OR(A3<DATE(2026,9,1),A3>DATE(2026,9,28)),"Check Date",INT((A3-DATE(2026,9,1))/7)+1) -> 1 | AB3: =IF(OR(AD3="",AE3="",AF3=""),"",S3*(AD3-AE3-AF3)-P3) -> -66 | AC3: =IF(P3<0,"Review",IF(OR(AD3="",AE3="",AF3=""),"Cost missing",IF(P3=0,"No Spend",IF(Q3=0,"No Sales",IF(P3/Q3<AG3,"Profitable","Losing"))))) -> No Sales | AD3: =IFERROR(VLOOKUP(J3,Product_lookup!$A:$G,5,FALSE),"") -> 549 | AE3: =IFERROR(VLOOKUP(J3,Product_lookup!$A:$G,6,FALSE),"") -> 192 | AF3: =IFERROR(VLOOKUP(J3,Product_lookup!$A:$G,7,FALSE),"") -> 139 | AG3: =IFERROR((AD3-AE3-AF3)/AD3,"") -> 0.39708561
A4: 46266 | B4: SP | Auto | Face Care | C4: Face Care | D4: Enabled | E4: AG | Niacinamide Serum | F4: Sponsored Products | G4: close-match | H4: AUTO | I4: organic niacinamide 10% serum | J4: SKN-002 | K4: Product Pages | L4: 201 | M4: 5 | N4: =IF(L4=0,"",M4/L4) -> 0.024875622 | O4: =IF(M4=0,"",P4/M4) -> 6.14 | P4: 30.7 | Q4: 0 | R4: 0 | S4: 0 | T4: =IF(Q4=0,"",P4/Q4) | U4: =IF(P4=0,"",Q4/P4) -> 0 | V4: =IF(M4=0,"",R4/M4) -> 0 | W4: 10.5 | X4: INR | Y4: India | AA4: =IF(OR(A4<DATE(2026,9,1),A4>DATE(2026,9,28)),"Check Date",INT((A4-DATE(2026,9,1))/7)+1) -> 1 | AB4: =IF(OR(AD4="",AE4="",AF4=""),"",S4*(AD4-AE4-AF4)-P4) -> -30.7 | AC4: =IF(P4<0,"Review",IF(OR(AD4="",AE4="",AF4=""),"Cost missing",IF(P4=0,"No Spend",IF(Q4=0,"No Sales",IF(P4/Q4<AG4,"Profitable","Losing"))))) -> No Sales | AD4: =IFERROR(VLOOKUP(J4,Product_lookup!$A:$G,5,FALSE),"") -> 549 | AE4: =IFERROR(VLOOKUP(J4,Product_lookup!$A:$G,6,FALSE),"") -> 192 | AF4: =IFERROR(VLOOKUP(J4,Product_lookup!$A:$G,7,FALSE),"") -> 139 | AG4: =IFERROR((AD4-AE4-AF4)/AD4,"") -> 0.39708561
A5: 46266 | B5: SP | Auto | Face Care | C5: Face Care | D5: Enabled | E5: AG | Niacinamide Serum | F5: Sponsored Products | G5: loose-match | H5: AUTO | I5: niacinamide 10% serum | J5: SKN-002 | K5: Rest of Search | L5: 808 | M5: 4 | N5: =IF(L5=0,"",M5/L5) -> 0.004950495 | O5: =IF(M5=0,"",P5/M5) -> 6.82 | P5: 27.28 | Q5: 0 | R5: 0 | S5: 0 | T5: =IF(Q5=0,"",P5/Q5) | U5: =IF(P5=0,"",Q5/P5) -> 0 | V5: =IF(M5=0,"",R5/M5) -> 0 | W5: 10 | X5: INR | Y5: India | AA5: =IF(OR(A5<DATE(2026,9,1),A5>DATE(2026,9,28)),"Check Date",INT((A5-DATE(2026,9,1))/7)+1) -> 1 | AB5: =IF(OR(AD5="",AE5="",AF5=""),"",S5*(AD5-AE5-AF5)-P5) -> -27.28 | AC5: =IF(P5<0,"Review",IF(OR(AD5="",AE5="",AF5=""),"Cost missing",IF(P5=0,"No Spend",IF(Q5=0,"No Sales",IF(P5/Q5<AG5,"Profitable","Losing"))))) -> No Sales | AD5: =IFERROR(VLOOKUP(J5,Product_lookup!$A:$G,5,FALSE),"") -> 549 | AE5: =IFERROR(VLOOKUP(J5,Product_lookup!$A:$G,6,FALSE),"") -> 192 | AF5: =IFERROR(VLOOKUP(J5,Product_lookup!$A:$G,7,FALSE),"") -> 139 | AG5: =IFERROR((AD5-AE5-AF5)/AD5,"") -> 0.39708561
A6: 46266 | B6: SP | Auto | Face Care | C6: Face Care | D6: Enabled | E6: AG | Gel Moisturizer | F6: Sponsored Products | G6: loose-match | H6: AUTO | I6: organic gel moisturizer | J6: SKN-005 | K6: Product Pages | L6: 216 | M6: 0 | N6: =IF(L6=0,"",M6/L6) -> 0 | O6: =IF(M6=0,"",P6/M6) | P6: 0 | Q6: 0 | R6: 0 | S6: 0 | T6: =IF(Q6=0,"",P6/Q6) | U6: =IF(P6=0,"",Q6/P6) | V6: =IF(M6=0,"",R6/M6) | W6: 12 | X6: INR | Y6: India | AA6: =IF(OR(A6<DATE(2026,9,1),A6>DATE(2026,9,28)),"Check Date",INT((A6-DATE(2026,9,1))/7)+1) -> 1 | AB6: =IF(OR(AD6="",AE6="",AF6=""),"",S6*(AD6-AE6-AF6)-P6) -> 0 | AC6: =IF(P6<0,"Review",IF(OR(AD6="",AE6="",AF6=""),"Cost missing",IF(P6=0,"No Spend",IF(Q6=0,"No Sales",IF(P6/Q6<AG6,"Profitable","Losing"))))) -> No Spend | AD6: =IFERROR(VLOOKUP(J6,Product_lookup!$A:$G,5,FALSE),"") -> 399 | AE6: =IFERROR(VLOOKUP(J6,Product_lookup!$A:$G,6,FALSE),"") -> 148 | AF6: =IFERROR(VLOOKUP(J6,Product_lookup!$A:$G,7,FALSE),"") -> 126 | AG6: =IFERROR((AD6-AE6-AF6)/AD6,"") -> 0.31328321
A7: 46266 | B7: SP | Auto | Face Care | C7: Face Care | D7: Enabled | E7: AG | Gel Moisturizer | F7: Sponsored Products | G7: close-match | H7: AUTO | I7: face moisturizer | J7: SKN-005 | K7: Rest of Search | L7: 1431 | M7: 17 | N7: =IF(L7=0,"",M7/L7) -> 0.011879804 | O7: =IF(M7=0,"",P7/M7) -> 6 | P7: 102 | Q7: 399 | R7: 1 | S7: 1 | T7: =IF(Q7=0,"",P7/Q7) -> 0.2556391 | U7: =IF(P7=0,"",Q7/P7) -> 3.9117647 | V7: =IF(M7=0,"",R7/M7) -> 0.058823529 | W7: 10.5 | X7: INR | Y7: India | AA7: =IF(OR(A7<DATE(2026,9,1),A7>DATE(2026,9,28)),"Check Date",INT((A7-DATE(2026,9,1))/7)+1) -> 1 | AB7: =IF(OR(AD7="",AE7="",AF7=""),"",S7*(AD7-AE7-AF7)-P7) -> 23 | AC7: =IF(P7<0,"Review",IF(OR(AD7="",AE7="",AF7=""),"Cost missing",IF(P7=0,"No Spend",IF(Q7=0,"No Sales",IF(P7/Q7<AG7,"Profitable","Losing"))))) -> Profitable | AD7: =IFERROR(VLOOKUP(J7,Product_lookup!$A:$G,5,FALSE),"") -> 399 | AE7: =IFERROR(VLOOKUP(J7,Product_lookup!$A:$G,6,FALSE),"") -> 148 | AF7: =IFERROR(VLOOKUP(J7,Product_lookup!$A:$G,7,FALSE),"") -> 126 | AG7: =IFERROR((AD7-AE7-AF7)/AD7,"") -> 0.31328321
A8: 46266 | B8: SP | Auto | Face Care | C8: Face Care | D8: Enabled | E8: AG | Gel Moisturizer | F8: Sponsored Products | G8: close-match | H8: AUTO | I8: gel moisturizer | J8: SKN-005 | K8: Top of Search | L8: 1449 | M8: 22 | N8: =IF(L8=0,"",M8/L8) -> 0.015182885 | O8: =IF(M8=0,"",P8/M8) -> 11.5 | P8: 253 | Q8: 1197 | R8: 3 | S8: 3 | T8: =IF(Q8=0,"",P8/Q8) -> 0.21136174 | U8: =IF(P8=0,"",Q8/P8) -> 4.7312253 | V8: =IF(M8=0,"",R8/M8) -> 0.13636364 | W8: 12 | X8: INR | Y8: India | AA8: =IF(OR(A8<DATE(2026,9,1),A8>DATE(2026,9,28)),"Check Date",INT((A8-DATE(2026,9,1))/7)+1) -> 1 | AB8: =IF(OR(AD8="",AE8="",AF8=""),"",S8*(AD8-AE8-AF8)-P8) -> 122 | AC8: =IF(P8<0,"Review",IF(OR(AD8="",AE8="",AF8=""),"Cost missing",IF(P8=0,"No Spend",IF(Q8=0,"No Sales",IF(P8/Q8<AG8,"Profitable","Losing"))))) -> Profitable | AD8: =IFERROR(VLOOKUP(J8,Product_lookup!$A:$G,5,FALSE),"") -> 399 | AE8: =IFERROR(VLOOKUP(J8,Product_lookup!$A:$G,6,FALSE),"") -> 148 | AF8: =IFERROR(VLOOKUP(J8,Product_lookup!$A:$G,7,FALSE),"") -> 126 | AG8: =IFERROR((AD8-AE8-AF8)/AD8,"") -> 0.31328321
A9: 46266 | B9: SP | Auto | Face Care | C9: Face Care | D9: Enabled | E9: AG | Sunscreen Spf 50 | F9: Sponsored Products | G9: close-match | H9: AUTO | I9: sunscreen spf 50 | J9: SKN-006 | K9: Product Pages | L9: 2603 | M9: 14 | N9: =IF(L9=0,"",M9/L9) -> 0.0053784095 | O9: =IF(M9=0,"",P9/M9) -> 7.67 | P9: 107.38 | Q9: 0 | R9: 0 | S9: 0 | T9: =IF(Q9=0,"",P9/Q9) | U9: =IF(P9=0,"",Q9/P9) -> 0 | V9: =IF(M9=0,"",R9/M9) -> 0 | W9: 12 | X9: INR | Y9: India | AA9: =IF(OR(A9<DATE(2026,9,1),A9>DATE(2026,9,28)),"Check Date",INT((A9-DATE(2026,9,1))/7)+1) -> 1 | AB9: =IF(OR(AD9="",AE9="",AF9=""),"",S9*(AD9-AE9-AF9)-P9) -> -107.38 | AC9: =IF(P9<0,"Review",IF(OR(AD9="",AE9="",AF9=""),"Cost missing",IF(P9=0,"No Spend",IF(Q9=0,"No Sales",IF(P9/Q9<AG9,"Profitable","Losing"))))) -> No Sales | AD9: =IFERROR(VLOOKUP(J9,Product_lookup!$A:$G,5,FALSE),"") -> 449 | AE9: =IFERROR(VLOOKUP(J9,Product_lookup!$A:$G,6,FALSE),"") -> 162 | AF9: =IFERROR(VLOOKUP(J9,Product_lookup!$A:$G,7,FALSE),"") -> 130 | AG9: =IFERROR((AD9-AE9-AF9)/AD9,"") -> 0.34966592
A10: 46266 | B10: SP | Auto | Face Care | C10: Face Care | D10: Enabled | E10: AG | Rose Water Toner | F10: Sponsored Products | G10: close-match | H10: AUTO | I10: rose water toner | J10: SKN-010 | K10: Top of Search | L10: 993 | M10: 3 | N10: =IF(L10=0,"",M10/L10) -> 0.003021148 | O10: =IF(M10=0,"",P10/M10) -> 7.49 | P10: 22.47 | Q10: 0 | R10: 0 | S10: 0 | T10: =IF(Q10=0,"",P10/Q10) | U10: =IF(P10=0,"",Q10/P10) -> 0 | V10: =IF(M10=0,"",R10/M10) -> 0 | W10: 8 | X10: INR | Y10: India | AA10: =IF(OR(A10<DATE(2026,9,1),A10>DATE(2026,9,28)),"Check Date",INT((A10-DATE(2026,9,1))/7)+1) -> 1 | AB10: =IF(OR(AD10="",AE10="",AF10=""),"",S10*(AD10-AE10-AF10)-P10) -> -22.47 | AC10: =IF(P10<0,"Review",IF(OR(AD10="",AE10="",AF10=""),"Cost missing",IF(P10=0,"No Spend",IF(Q10=0,"No Sales",IF(P10/Q10<AG10,"Profitable","Losing"))))) -> No Sales | AD10: =IFERROR(VLOOKUP(J10,Product_lookup!$A:$G,5,FALSE),"") -> 249 | AE10: =IFERROR(VLOOKUP(J10,Product_lookup!$A:$G,6,FALSE),"") -> 100 | AF10: =IFERROR(VLOOKUP(J10,Product_lookup!$A:$G,7,FALSE),"") -> 102 | AG10: =IFERROR((AD10-AE10-AF10)/AD10,"") -> 0.18875502
A11: 46266 | B11: SP | Auto | Face Care | C11: Face Care | D11: Enabled | E11: AG | Rose Water Toner | F11: Sponsored Products | G11: complements | H11: AUTO | I11: face cream for dogs | J11: SKN-010 | K11: Product Pages | L11: 233 | M11: 2 | N11: =IF(L11=0,"",M11/L11) -> 0.008583691 | O11: =IF(M11=0,"",P11/M11) -> 2.95 | P11: 5.9 | Q11: 0 | R11: 0 | S11: 0 | T11: =IF(Q11=0,"",P11/Q11) | U11: =IF(P11=0,"",Q11/P11) -> 0 | V11: =IF(M11=0,"",R11/M11) -> 0 | W11: 5.5 | X11: INR | Y11: India | AA11: =IF(OR(A11<DATE(2026,9,1),A11>DATE(2026,9,28)),"Check Date",INT((A11-DATE(2026,9,1))/7)+1) -> 1 | AB11: =IF(OR(AD11="",AE11="",AF11=""),"",S11*(AD11-AE11-AF11)-P11) -> -5.9 | AC11: =IF(P11<0,"Review",IF(OR(AD11="",AE11="",AF11=""),"Cost missing",IF(P11=0,"No Spend",IF(Q11=0,"No Sales",IF(P11/Q11<AG11,"Profitable","Losing"))))) -> No Sales | AD11: =IFERROR(VLOOKUP(J11,Product_lookup!$A:$G,5,FALSE),"") -> 249 | AE11: =IFERROR(VLOOKUP(J11,Product_lookup!$A:$G,6,FALSE),"") -> 100 | AF11: =IFERROR(VLOOKUP(J11,Product_lookup!$A:$G,7,FALSE),"") -> 102 | AG11: =IFERROR((AD11-AE11-AF11)/AD11,"") -> 0.18875502
A12: 46266 | B12: SP | Auto | Face Care | C12: Face Care | D12: Enabled | E12: AG | Rose Water Toner | F12: Sponsored Products | G12: close-match | H12: AUTO | I12: face toner price | J12: SKN-010 | K12: Top of Search | L12: 247 | M12: 1 | N12: =IF(L12=0,"",M12/L12) -> 0.004048583 | O12: =IF(M12=0,"",P12/M12) -> 6 | P12: 6 | Q12: 0 | R12: 0 | S12: 0 | T12: =IF(Q12=0,"",P12/Q12) | U12: =IF(P12=0,"",Q12/P12) -> 0 | V12: =IF(M12=0,"",R12/M12) -> 0 | W12: 6 | X12: INR | Y12: India | AA12: =IF(OR(A12<DATE(2026,9,1),A12>DATE(2026,9,28)),"Check Date",INT((A12-DATE(2026,9,1))/7)+1) -> 1 | AB12: =IF(OR(AD12="",AE12="",AF12=""),"",S12*(AD12-AE12-AF12)-P12) -> -6 | AC12: =IF(P12<0,"Review",IF(OR(AD12="",AE12="",AF12=""),"Cost missing",IF(P12=0,"No Spend",IF(Q12=0,"No Sales",IF(P12/Q12<AG12,"Profitable","Losing"))))) -> No Sales | AD12: =IFERROR(VLOOKUP(J12,Product_lookup!$A:$G,5,FALSE),"") -> 249 | AE12: =IFERROR(VLOOKUP(J12,Product_lookup!$A:$G,6,FALSE),"") -> 100 | AF12: =IFERROR(VLOOKUP(J12,Product_lookup!$A:$G,7,FALSE),"") -> 102 | AG12: =IFERROR((AD12-AE12-AF12)/AD12,"") -> 0.18875502
A13: 46266 | B13: SP | Auto | Body & Hair | C13: Body & Hair | D13: Enabled | E13: AG | Body Lotion | F13: Sponsored Products | G13: close-match | H13: AUTO | I13: body lotion for dry skin | J13: SKN-017 | K13: Rest of Search | L13: 1128 | M13: 5 | N13: =IF(L13=0,"",M13/L13) -> 0.0044326241 | O13: =IF(M13=0,"",P13/M13) -> 7.2 | P13: 36 | Q13: 0 | R13: 0 | S13: 0 | T13: =IF(Q13=0,"",P13/Q13) | U13: =IF(P13=0,"",Q13/P13) -> 0 | V13: =IF(M13=0,"",R13/M13) -> 0 | W13: 12 | X13: INR | Y13: India | Z13: seller wants to monitor | AA13: =IF(OR(A13<DATE(2026,9,1),A13>DATE(2026,9,28)),"Check Date",INT((A13-DATE(2026,9,1))/7)+1) -> 1 | AB13: =IF(OR(AD13="",AE13="",AF13=""),"",S13*(AD13-AE13-AF13)-P13) -> -36 | AC13: =IF(P13<0,"Review",IF(OR(AD13="",AE13="",AF13=""),"Cost missing",IF(P13=0,"No Spend",IF(Q13=0,"No Sales",IF(P13/Q13<AG13,"Profitable","Losing"))))) -> No Sales | AD13: =IFERROR(VLOOKUP(J13,Product_lookup!$A:$G,5,FALSE),"") -> 449 | AE13: =IFERROR(VLOOKUP(J13,Product_lookup!$A:$G,6,FALSE),"") -> 166 | AF13: =IFERROR(VLOOKUP(J13,Product_lookup!$A:$G,7,FALSE),"") -> 140 | AG13: =IFERROR((AD13-AE13-AF13)/AD13,"") -> 0.31848552
A14: 46266 | B14: SP | Auto | Body & Hair | C14: Body & Hair | D14: Enabled | E14: AG | Body Lotion | F14: Sponsored Products | G14: substitutes | H14: AUTO | I14: veluna shea body lotion | J14: SKN-017 | K14: Top of Search | L14: 115 | M14: 1 | N14: =IF(L14=0,"",M14/L14) -> 0.0086956522 | O14: =IF(M14=0,"",P14/M14) -> 14 | P14: 14 | Q14: 0 | R14: 0 | S14: 0 | T14: =IF(Q14=0,"",P14/Q14) | U14: =IF(P14=0,"",Q14/P14) -> 0 | V14: =IF(M14=0,"",R14/M14) -> 0 | W14: 14 | X14: INR | Y14: India | AA14: =IF(OR(A14<DATE(2026,9,1),A14>DATE(2026,9,28)),"Check Date",INT((A14-DATE(2026,9,1))/7)+1) -> 1 | AB14: =IF(OR(AD14="",AE14="",AF14=""),"",S14*(AD14-AE14-AF14)-P14) -> -14 | AC14: =IF(P14<0,"Review",IF(OR(AD14="",AE14="",AF14=""),"Cost missing",IF(P14=0,"No Spend",IF(Q14=0,"No Sales",IF(P14/Q14<AG14,"Profitable","Losing"))))) -> No Sales | AD14: =IFERROR(VLOOKUP(J14,Product_lookup!$A:$G,5,FALSE),"") -> 449 | AE14: =IFERROR(VLOOKUP(J14,Product_lookup!$A:$G,6,FALSE),"") -> 166 | AF14: =IFERROR(VLOOKUP(J14,Product_lookup!$A:$G,7,FALSE),"") -> 140 | AG14: =IFERROR((AD14-AE14-AF14)/AD14,"") -> 0.31848552
A15: 46287 | B15: SP | Manual | Masks & Gels | Broad | C15: Face Care | D15: Paused | E15: AG | Clay Face Mask | F15: Sponsored Products | G15: multani mitti face pack | H15: BROAD | I15: face cream for dogs | J15: SKN-012 | K15: Top of Search | L15: 176 | M15: 2 | N15: =IF(L15=0,"",M15/L15) -> 0.011363636 | O15: =IF(M15=0,"",P15/M15) -> 13.87 | P15: 27.74 | Q15: 0 | R15: 0 | S15: 0 | T15: =IF(Q15=0,"",P15/Q15) | U15: =IF(P15=0,"",Q15/P15) -> 0 | V15: =IF(M15=0,"",R15/M15) -> 0 | W15: 7.5 | X15: INR | Y15: India | AA15: =IF(OR(A15<DATE(2026,9,1),A15>DATE(2026,9,28)),"Check Date",INT((A15-DATE(2026,9,1))/7)+1) -> 4 | AB15: =IF(OR(AD15="",AE15="",AF15=""),"",S15*(AD15-AE15-AF15)-P15) -> -27.74 | AC15: =IF(P15<0,"Review",IF(OR(AD15="",AE15="",AF15=""),"Cost missing",IF(P15=0,"No Spend",IF(Q15=0,"No Sales",IF(P15/Q15<AG15,"Profitable","Losing"))))) -> No Sales | AD15: =IFERROR(VLOOKUP(J15,Product_lookup!$A:$G,5,FALSE),"") -> 379 | AE15: =IFERROR(VLOOKUP(J15,Product_lookup!$A:$G,6,FALSE),"") -> 140 | AF15: =IFERROR(VLOOKUP(J15,Product_lookup!$A:$G,7,FALSE),"") -> 114 | AG15: =IFERROR((AD15-AE15-AF15)/AD15,"") -> 0.3298153
A16: 46266 | B16: SP | Auto | Body & Hair | C16: Body & Hair | D16: Enabled | E16: AG | Body Lotion | F16: Sponsored Products | G16: loose-match | H16: AUTO | I16: baby lotion | J16: SKN-017 | K16: Top of Search | L16: 914 | M16: 15 | N16: =IF(L16=0,"",M16/L16) -> 0.016411379 | O16: =IF(M16=0,"",P16/M16) -> 9 | P16: 135 | Q16: 0 | R16: 0 | S16: 0 | T16: =IF(Q16=0,"",P16/Q16) | U16: =IF(P16=0,"",Q16/P16) -> 0 | V16: =IF(M16=0,"",R16/M16) -> 0 | W16: 9 | X16: INR | Y16: India | AA16: =IF(OR(A16<DATE(2026,9,1),A16>DATE(2026,9,28)),"Check Date",INT((A16-DATE(2026,9,1))/7)+1) -> 1 | AB16: =IF(OR(AD16="",AE16="",AF16=""),"",S16*(AD16-AE16-AF16)-P16) -> -135 | AC16: =IF(P16<0,"Review",IF(OR(AD16="",AE16="",AF16=""),"Cost missing",IF(P16=0,"No Spend",IF(Q16=0,"No Sales",IF(P16/Q16<AG16,"Profitable","Losing"))))) -> No Sales | AD16: =IFERROR(VLOOKUP(J16,Product_lookup!$A:$G,5,FALSE),"") -> 449 | AE16: =IFERROR(VLOOKUP(J16,Product_lookup!$A:$G,6,FALSE),"") -> 166 | AF16: =IFERROR(VLOOKUP(J16,Product_lookup!$A:$G,7,FALSE),"") -> 140 | AG16: =IFERROR((AD16-AE16-AF16)/AD16,"") -> 0.31848552
A17: 46266 | B17: SP | Auto | Body & Hair | C17: Body & Hair | D17: Enabled | E17: AG | Body Wash | F17: Sponsored Products | G17: close-match | H17: AUTO | I17: body wash under 300 | J17: SKN-018 | K17: Product Pages | L17: 172 | M17: 1 | N17: =IF(L17=0,"",M17/L17) -> 0.0058139535 | O17: =IF(M17=0,"",P17/M17) -> 4.72 | P17: 4.72 | Q17: 0 | R17: 0 | S17: 0 | T17: =IF(Q17=0,"",P17/Q17) | U17: =IF(P17=0,"",Q17/P17) -> 0 | V17: =IF(M17=0,"",R17/M17) -> 0 | W17: 8.5 | X17: INR | Y17: India | AA17: =IF(OR(A17<DATE(2026,9,1),A17>DATE(2026,9,28)),"Check Date",INT((A17-DATE(2026,9,1))/7)+1) -> 1 | AB17: =IF(OR(AD17="",AE17="",AF17=""),"",S17*(AD17-AE17-AF17)-P17) -> -4.72 | AC17: =IF(P17<0,"Review",IF(OR(AD17="",AE17="",AF17=""),"Cost missing",IF(P17=0,"No Spend",IF(Q17=0,"No Sales",IF(P17/Q17<AG17,"Profitable","Losing"))))) -> No Sales | AD17: =IFERROR(VLOOKUP(J17,Product_lookup!$A:$G,5,FALSE),"") -> 349 | AE17: =IFERROR(VLOOKUP(J17,Product_lookup!$A:$G,6,FALSE),"") -> 133 | AF17: =IFERROR(VLOOKUP(J17,Product_lookup!$A:$G,7,FALSE),"") -> 121 | AG17: =IFERROR((AD17-AE17-AF17)/AD17,"") -> 0.2722063
A18: 46266 | B18: SP | Auto | Body & Hair | C18: Body & Hair | D18: Enabled | E18: AG | Body Wash | F18: Sponsored Products | G18: close-match | H18: AUTO | I18: body wash | J18: SKN-018 | K18: Product Pages | L18: 1183 | M18: 7 | N18: =IF(L18=0,"",M18/L18) -> 0.0059171598 | O18: =IF(M18=0,"",P18/M18) -> 4.38 | P18: 30.66 | Q18: 0 | R18: 0 | S18: 0 | T18: =IF(Q18=0,"",P18/Q18) | U18: =IF(P18=0,"",Q18/P18) -> 0 | V18: =IF(M18=0,"",R18/M18) -> 0 | W18: 8.5 | X18: INR | Y18: India | AA18: =IF(OR(A18<DATE(2026,9,1),A18>DATE(2026,9,28)),"Check Date",INT((A18-DATE(2026,9,1))/7)+1) -> 1 | AB18: =IF(OR(AD18="",AE18="",AF18=""),"",S18*(AD18-AE18-AF18)-P18) -> -30.66 | AC18: =IF(P18<0,"Review",IF(OR(AD18="",AE18="",AF18=""),"Cost missing",IF(P18=0,"No Spend",IF(Q18=0,"No Sales",IF(P18/Q18<AG18,"Profitable","Losing"))))) -> No Sales | AD18: =IFERROR(VLOOKUP(J18,Product_lookup!$A:$G,5,FALSE),"") -> 349 | AE18: =IFERROR(VLOOKUP(J18,Product_lookup!$A:$G,6,FALSE),"") -> 133 | AF18: =IFERROR(VLOOKUP(J18,Product_lookup!$A:$G,7,FALSE),"") -> 121 | AG18: =IFERROR((AD18-AE18-AF18)/AD18,"") -> 0.2722063
A19: 46266 | B19: SP | Auto | Body & Hair | C19: Body & Hair | D19: Enabled | E19: AG | Body Wash | F19: Sponsored Products | G19: close-match | H19: AUTO | I19: body wash for women under 300 | J19: SKN-018 | K19: Top of Search | L19: 772 | M19: 12 | N19: =IF(L19=0,"",M19/L19) -> 0.015544041 | O19: =IF(M19=0,"",P19/M19) -> 7.5 | P19: 90 | Q19: 0 | R19: 0 | S19: 0 | T19: =IF(Q19=0,"",P19/Q19) | U19: =IF(P19=0,"",Q19/P19) -> 0 | V19: =IF(M19=0,"",R19/M19) -> 0 | W19: 7.5 | X19: INR | Y19: India | AA19: =IF(OR(A19<DATE(2026,9,1),A19>DATE(2026,9,28)),"Check Date",INT((A19-DATE(2026,9,1))/7)+1) -> 1 | AB19: =IF(OR(AD19="",AE19="",AF19=""),"",S19*(AD19-AE19-AF19)-P19) -> -90 | AC19: =IF(P19<0,"Review",IF(OR(AD19="",AE19="",AF19=""),"Cost missing",IF(P19=0,"No Spend",IF(Q19=0,"No Sales",IF(P19/Q19<AG19,"Profitable","Losing"))))) -> No Sales | AD19: =IFERROR(VLOOKUP(J19,Product_lookup!$A:$G,5,FALSE),"") -> 349 | AE19: =IFERROR(VLOOKUP(J19,Product_lookup!$A:$G,6,FALSE),"") -> 133 | AF19: =IFERROR(VLOOKUP(J19,Product_lookup!$A:$G,7,FALSE),"") -> 121 | AG19: =IFERROR((AD19-AE19-AF19)/AD19,"") -> 0.2722063
A20: 46266 | B20: SP | Auto | Body & Hair | C20: Body & Hair | D20: Enabled | E20: AG | Body Wash | F20: Sponsored Products | G20: loose-match | H20: AUTO | I20: body wash for women paraben free | J20: SKN-018 | K20: Rest of Search | L20: 927 | M20: 4 | N20: =IF(L20=0,"",M20/L20) -> 0.0043149946 | O20: =IF(M20=0,"",P20/M20) -> 6.04 | P20: 24.16 | Q20: 0 | R20: 0 | S20: 0 | T20: =IF(Q20=0,"",P20/Q20) | U20: =IF(P20=0,"",Q20/P20) -> 0 | V20: =IF(M20=0,"",R20/M20) -> 0 | W20: 8.5 | X20: INR | Y20: India | AA20: =IF(OR(A20<DATE(2026,9,1),A20>DATE(2026,9,28)),"Check Date",INT((A20-DATE(2026,9,1))/7)+1) -> 1 | AB20: =IF(OR(AD20="",AE20="",AF20=""),"",S20*(AD20-AE20-AF20)-P20) -> -24.16 | AC20: =IF(P20<0,"Review",IF(OR(AD20="",AE20="",AF20=""),"Cost missing",IF(P20=0,"No Spend",IF(Q20=0,"No Sales",IF(P20/Q20<AG20,"Profitable","Losing"))))) -> No Sales | AD20: =IFERROR(VLOOKUP(J20,Product_lookup!$A:$G,5,FALSE),"") -> 349 | AE20: =IFERROR(VLOOKUP(J20,Product_lookup!$A:$G,6,FALSE),"") -> 133 | AF20: =IFERROR(VLOOKUP(J20,Product_lookup!$A:$G,7,FALSE),"") -> 121 | AG20: =IFERROR((AD20-AE20-AF20)/AD20,"") -> 0.2722063
A21: 46266 | B21: SP | Auto | Body & Hair | C21: Body & Hair | D21: Enabled | E21: AG | Body Wash | F21: Sponsored Products | G21: complements | H21: AUTO | I21: baby lotion | J21: SKN-018 | K21: Top of Search | L21: 150 | M21: 0 | N21: =IF(L21=0,"",M21/L21) -> 0 | O21: =IF(M21=0,"",P21/M21) | P21: 0 | Q21: 0 | R21: 0 | S21: 0 | T21: =IF(Q21=0,"",P21/Q21) | U21: =IF(P21=0,"",Q21/P21) | V21: =IF(M21=0,"",R21/M21) | W21: 8 | X21: INR | Y21: India | AA21: =IF(OR(A21<DATE(2026,9,1),A21>DATE(2026,9,28)),"Check Date",INT((A21-DATE(2026,9,1))/7)+1) -> 1 | AB21: =IF(OR(AD21="",AE21="",AF21=""),"",S21*(AD21-AE21-AF21)-P21) -> 0 | AC21: =IF(P21<0,"Review",IF(OR(AD21="",AE21="",AF21=""),"Cost missing",IF(P21=0,"No Spend",IF(Q21=0,"No Sales",IF(P21/Q21<AG21,"Profitable","Losing"))))) -> No Spend | AD21: =IFERROR(VLOOKUP(J21,Product_lookup!$A:$G,5,FALSE),"") -> 349 | AE21: =IFERROR(VLOOKUP(J21,Product_lookup!$A:$G,6,FALSE),"") -> 133 | AF21: =IFERROR(VLOOKUP(J21,Product_lookup!$A:$G,7,FALSE),"") -> 121 | AG21: =IFERROR((AD21-AE21-AF21)/AD21,"") -> 0.2722063
A22: 46266 | B22: SP | Auto | Body & Hair | C22: Body & Hair | D22: Enabled | E22: AG | Onion Hair Oil | F22: Sponsored Products | G22: loose-match | H22: AUTO | I22: onion hair oil | J22: SKN-021 | K22: Top of Search | L22: 405 | M22: 4 | N22: =IF(L22=0,"",M22/L22) -> 0.0098765432 | O22: =IF(M22=0,"",P22/M22) -> 9.5 | P22: 38 | Q22: 798 | R22: 1 | S22: 2 | T22: =IF(Q22=0,"",P22/Q22) -> 0.047619048 | U22: =IF(P22=0,"",Q22/P22) -> 21 | V22: =IF(M22=0,"",R22/M22) -> 0.25 | W22: 9.5 | X22: INR | Y22: India | AA22: =IF(OR(A22<DATE(2026,9,1),A22>DATE(2026,9,28)),"Check Date",INT((A22-DATE(2026,9,1))/7)+1) -> 1 | AB22: =IF(OR(AD22="",AE22="",AF22=""),"",S22*(AD22-AE22-AF22)-P22) -> 212 | AC22: =IF(P22<0,"Review",IF(OR(AD22="",AE22="",AF22=""),"Cost missing",IF(P22=0,"No Spend",IF(Q22=0,"No Sales",IF(P22/Q22<AG22,"Profitable","Losing"))))) -> Profitable | AD22: =IFERROR(VLOOKUP(J22,Product_lookup!$A:$G,5,FALSE),"") -> 399 | AE22: =IFERROR(VLOOKUP(J22,Product_lookup!$A:$G,6,FALSE),"") -> 148 | AF22: =IFERROR(VLOOKUP(J22,Product_lookup!$A:$G,7,FALSE),"") -> 126 | AG22: =IFERROR((AD22-AE22-AF22)/AD22,"") -> 0.31328321
A23: 46266 | B23: SP | Auto | Body & Hair | C23: Body & Hair | D23: Enabled | E23: AG | Onion Hair Oil | F23: Sponsored Products | G23: close-match | H23: AUTO | I23: hair oil for hair growth | J23: SKN-021 | K23: Rest of Search | L23: 1645 | M23: 13 | N23: =IF(L23=0,"",M23/L23) -> 0.0079027356 | O23: =IF(M23=0,"",P23/M23) -> 6.16 | P23: 80.08 | Q23: 798 | R23: 2 | S23: 2 | T23: =IF(Q23=0,"",P23/Q23) -> 0.10035088 | U23: =IF(P23=0,"",Q23/P23) -> 9.965035 | V23: =IF(M23=0,"",R23/M23) -> 0.15384615 | W23: 7.5 | X23: INR | Y23: India | AA23: =IF(OR(A23<DATE(2026,9,1),A23>DATE(2026,9,28)),"Check Date",INT((A23-DATE(2026,9,1))/7)+1) -> 1 | AB23: =IF(OR(AD23="",AE23="",AF23=""),"",S23*(AD23-AE23-AF23)-P23) -> 169.92 | AC23: =IF(P23<0,"Review",IF(OR(AD23="",AE23="",AF23=""),"Cost missing",IF(P23=0,"No Spend",IF(Q23=0,"No Sales",IF(P23/Q23<AG23,"Profitable","Losing"))))) -> Profitable | AD23: =IFERROR(VLOOKUP(J23,Product_lookup!$A:$G,5,FALSE),"") -> 399 | AE23: =IFERROR(VLOOKUP(J23,Product_lookup!$A:$G,6,FALSE),"") -> 148 | AF23: =IFERROR(VLOOKUP(J23,Product_lookup!$A:$G,7,FALSE),"") -> 126 | AG23: =IFERROR((AD23-AE23-AF23)/AD23,"") -> 0.31328321
A24: 46266 | B24: SP | Auto | Body & Hair | C24: Body & Hair | D24: Enabled | E24: AG | Onion Hair Oil | F24: Sponsored Products | G24: close-match | H24: AUTO | I24: hair oil for hair growth for oily scalp | J24: SKN-021 | K24: Rest of Search | L24: 415 | M24: 3 | N24: =IF(L24=0,"",M24/L24) -> 0.0072289157 | O24: =IF(M24=0,"",P24/M24) -> 6.16 | P24: 18.48 | Q24: 399 | R24: 1 | S24: 1 | T24: =IF(Q24=0,"",P24/Q24) -> 0.046315789 | U24: =IF(P24=0,"",Q24/P24) -> 21.590909 | V24: =IF(M24=0,"",R24/M24) -> 0.33333333 | W24: 11 | X24: INR | Y24: India | AA24: =IF(OR(A24<DATE(2026,9,1),A24>DATE(2026,9,28)),"Check Date",INT((A24-DATE(2026,9,1))/7)+1) -> 1 | AB24: =IF(OR(AD24="",AE24="",AF24=""),"",S24*(AD24-AE24-AF24)-P24) -> 106.52 | AC24: =IF(P24<0,"Review",IF(OR(AD24="",AE24="",AF24=""),"Cost missing",IF(P24=0,"No Spend",IF(Q24=0,"No Sales",IF(P24/Q24<AG24,"Profitable","Losing"))))) -> Profitable | AD24: =IFERROR(VLOOKUP(J24,Product_lookup!$A:$G,5,FALSE),"") -> 399 | AE24: =IFERROR(VLOOKUP(J24,Product_lookup!$A:$G,6,FALSE),"") -> 148 | AF24: =IFERROR(VLOOKUP(J24,Product_lookup!$A:$G,7,FALSE),"") -> 126 | AG24: =IFERROR((AD24-AE24-AF24)/AD24,"") -> 0.31328321
A25: 46266 | B25: SP | Auto | Body & Hair | C25: Body & Hair | D25: Enabled | E25: AG | Onion Hair Oil | F25: Sponsored Products | G25: loose-match | H25: AUTO | I25: hair dryer | J25: SKN-021 | K25: Product Pages | L25: 569 | M25: 4 | N25: =IF(L25=0,"",M25/L25) -> 0.007029877 | O25: =IF(M25=0,"",P25/M25) -> 6.74 | P25: 26.96 | Q25: 0 | R25: 0 | S25: 0 | T25: =IF(Q25=0,"",P25/Q25) | U25: =IF(P25=0,"",Q25/P25) -> 0 | V25: =IF(M25=0,"",R25/M25) -> 0 | W25: 12.5 | X25: INR | Y25: India | AA25: =IF(OR(A25<DATE(2026,9,1),A25>DATE(2026,9,28)),"Check Date",INT((A25-DATE(2026,9,1))/7)+1) -> 1 | AB25: =IF(OR(AD25="",AE25="",AF25=""),"",S25*(AD25-AE25-AF25)-P25) -> -26.96 | AC25: =IF(P25<0,"Review",IF(OR(AD25="",AE25="",AF25=""),"Cost missing",IF(P25=0,"No Spend",IF(Q25=0,"No Sales",IF(P25/Q25<AG25,"Profitable","Losing"))))) -> No Sales | AD25: =IFERROR(VLOOKUP(J25,Product_lookup!$A:$G,5,FALSE),"") -> 399 | AE25: =IFERROR(VLOOKUP(J25,Product_lookup!$A:$G,6,FALSE),"") -> 148 | AF25: =IFERROR(VLOOKUP(J25,Product_lookup!$A:$G,7,FALSE),"") -> 126 | AG25: =IFERROR((AD25-AE25-AF25)/AD25,"") -> 0.31328321
... A56: 46266 | B56: SP | Manual | Skincare Essentials | Broad | C56: Face Care | D56: Enabled | E56: AG | Salicylic Acid Face Wash | F56: Sponsored Products | G56: acne face wash | H56: BROAD | I56: salicylic acid face wash for acne | J56: SKN-009 | K56: Top of Search | L56: 66 | M56: 2 | N56: =IF(L56=0,"",M56/L56) -> 0.03030303 | O56: =IF(M56=0,"",P56/M56) -> 6 | P56: 12 | Q56: 0 | R56: 0 | S56: 0 | T56: =IF(Q56=0,"",P56/Q56) | U56: =IF(P56=0,"",Q56/P56) -> 0 | V56: =IF(M56=0,"",R56/M56) -> 0 | W56: 6 | X56: INR | Y56: India | AA56: =IF(OR(A56<DATE(2026,9,1),A56>DATE(2026,9,28)),"Check Date",INT((A56-DATE(2026,9,1))/7)+1) -> 1 | AB56: =IF(OR(AD56="",AE56="",AF56=""),"",S56*(AD56-AE56-AF56)-P56) -> -12 | AC56: =IF(P56<0,"Review",IF(OR(AD56="",AE56="",AF56=""),"Cost missing",IF(P56=0,"No Spend",IF(Q56=0,"No Sales",IF(P56/Q56<AG56,"Profitable","Losing"))))) -> No Sales | AD56: =IFERROR(VLOOKUP(J56,Product_lookup!$A:$G,5,FALSE),"") -> 279 | AE56: =IFERROR(VLOOKUP(J56,Product_lookup!$A:$G,6,FALSE),"") -> 106 | AF56: =IFERROR(VLOOKUP(J56,Product_lookup!$A:$G,7,FALSE),"") -> 105 | AG56: =IFERROR((AD56-AE56-AF56)/AD56,"") -> 0.2437276
A57: 46292 | B57: SP | Brand Defence | Exact | C57: Brand | D57: Enabled | E57: AG | Vitamin C Serum | F57: Sponsored Products | G57: auralis face serum vitamin c | H57: EXACT | I57: auralis face serum vitamin c | J57: SKN-001 | K57: Top of Search | L57: 0 | M57: 0 | N57: =IF(L57=0,"",M57/L57) | O57: =IF(M57=0,"",P57/M57) | P57: -130.81 | Q57: 0 | R57: 0 | S57: 0 | T57: =IF(Q57=0,"",P57/Q57) | U57: =IF(P57=0,"",Q57/P57) -> 0 | V57: =IF(M57=0,"",R57/M57) | W57: 8 | X57: INR | Y57: India | Z57: refund | AA57: =IF(OR(A57<DATE(2026,9,1),A57>DATE(2026,9,28)),"Check Date",INT((A57-DATE(2026,9,1))/7)+1) -> 4 | AB57: =IF(OR(AD57="",AE57="",AF57=""),"",S57*(AD57-AE57-AF57)-P57) -> 130.81 | AC57: =IF(P57<0,"Review",IF(OR(AD57="",AE57="",AF57=""),"Cost missing",IF(P57=0,"No Spend",IF(Q57=0,"No Sales",IF(P57/Q57<AG57,"Profitable","Losing"))))) -> Review | AD57: =IFERROR(VLOOKUP(J57,Product_lookup!$A:$G,5,FALSE),"") -> 599 | AE57: =IFERROR(VLOOKUP(J57,Product_lookup!$A:$G,6,FALSE),"") -> 216 | AF57: =IFERROR(VLOOKUP(J57,Product_lookup!$A:$G,7,FALSE),"") -> 144 | AG57: =IFERROR((AD57-AE57-AF57)/AD57,"") -> 0.39899833
A58: 46266 | B58: SP | Manual | Skincare Essentials | Broad | C58: Face Care | D58: Enabled | E58: AG | Salicylic Acid Face Wash | F58: Sponsored Products | G58: acne face wash | H58: BROAD | I58: salicylic face wash price | J58: SKN-009 | K58: Top of Search | L58: 224 | M58: 1 | N58: =IF(L58=0,"",M58/L58) -> 0.0044642857 | O58: =IF(M58=0,"",P58/M58) -> 7 | P58: 7 | Q58: 0 | R58: 0 | S58: 0 | T58: =IF(Q58=0,"",P58/Q58) | U58: =IF(P58=0,"",Q58/P58) -> 0 | V58: =IF(M58=0,"",R58/M58) -> 0 | W58: 7 | X58: INR | Y58: India | AA58: =IF(OR(A58<DATE(2026,9,1),A58>DATE(2026,9,28)),"Check Date",INT((A58-DATE(2026,9,1))/7)+1) -> 1 | AB58: =IF(OR(AD58="",AE58="",AF58=""),"",S58*(AD58-AE58-AF58)-P58) -> -7 | AC58: =IF(P58<0,"Review",IF(OR(AD58="",AE58="",AF58=""),"Cost missing",IF(P58=0,"No Spend",IF(Q58=0,"No Sales",IF(P58/Q58<AG58,"Profitable","Losing"))))) -> No Sales | AD58: =IFERROR(VLOOKUP(J58,Product_lookup!$A:$G,5,FALSE),"") -> 279 | AE58: =IFERROR(VLOOKUP(J58,Product_lookup!$A:$G,6,FALSE),"") -> 106 | AF58: =IFERROR(VLOOKUP(J58,Product_lookup!$A:$G,7,FALSE),"") -> 105 | AG58: =IFERROR((AD58-AE58-AF58)/AD58,"") -> 0.2437276
A59: 46266 | B59: SP | Manual | Skincare Essentials | Broad | C59: Face Care | D59: Enabled | E59: AG | Salicylic Acid Face Wash | F59: Sponsored Products | G59: acne face wash | H59: BROAD | I59: salicylic acid face wash for night use | J59: SKN-009 | K59: Top of Search | L59: 212 | M59: 4 | N59: =IF(L59=0,"",M59/L59) -> 0.018867925 | O59: =IF(M59=0,"",P59/M59) -> 5.5 | P59: 22 | Q59: 0 | R59: 0 | S59: 0 | T59: =IF(Q59=0,"",P59/Q59) | U59: =IF(P59=0,"",Q59/P59) -> 0 | V59: =IF(M59=0,"",R59/M59) -> 0 | W59: 5.5 | X59: INR | Y59: India | AA59: =IF(OR(A59<DATE(2026,9,1),A59>DATE(2026,9,28)),"Check Date",INT((A59-DATE(2026,9,1))/7)+1) -> 1 | AB59: =IF(OR(AD59="",AE59="",AF59=""),"",S59*(AD59-AE59-AF59)-P59) -> -22 | AC59: =IF(P59<0,"Review",IF(OR(AD59="",AE59="",AF59=""),"Cost missing",IF(P59=0,"No Spend",IF(Q59=0,"No Sales",IF(P59/Q59<AG59,"Profitable","Losing"))))) -> No Sales | AD59: =IFERROR(VLOOKUP(J59,Product_lookup!$A:$G,5,FALSE),"") -> 279 | AE59: =IFERROR(VLOOKUP(J59,Product_lookup!$A:$G,6,FALSE),"") -> 106 | AF59: =IFERROR(VLOOKUP(J59,Product_lookup!$A:$G,7,FALSE),"") -> 105 | AG59: =IFERROR((AD59-AE59-AF59)/AD59,"") -> 0.2437276
A60: 46266 | B60: SP | Manual | Skincare Essentials | Broad | C60: Face Care | D60: Enabled | E60: AG | Rose Water Toner | F60: Sponsored Products | G60: rose water toner | H60: BROAD | I60: ayurvedic rose water toner | J60: SKN-010 | K60: Rest of Search | L60: 444 | M60: 1 | N60: =IF(L60=0,"",M60/L60) -> 0.0022522523 | O60: =IF(M60=0,"",P60/M60) -> 3.92 | P60: 3.92 | Q60: 0 | R60: 0 | S60: 0 | T60: =IF(Q60=0,"",P60/Q60) | U60: =IF(P60=0,"",Q60/P60) -> 0 | V60: =IF(M60=0,"",R60/M60) -> 0 | W60: 5.5 | X60: INR | Y60: India | AA60: =IF(OR(A60<DATE(2026,9,1),A60>DATE(2026,9,28)),"Check Date",INT((A60-DATE(2026,9,1))/7)+1) -> 1 | AB60: =IF(OR(AD60="",AE60="",AF60=""),"",S60*(AD60-AE60-AF60)-P60) -> -3.92 | AC60: =IF(P60<0,"Review",IF(OR(AD60="",AE60="",AF60=""),"Cost missing",IF(P60=0,"No Spend",IF(Q60=0,"No Sales",IF(P60/Q60<AG60,"Profitable","Losing"))))) -> No Sales | AD60: =IFERROR(VLOOKUP(J60,Product_lookup!$A:$G,5,FALSE),"") -> 249 | AE60: =IFERROR(VLOOKUP(J60,Product_lookup!$A:$G,6,FALSE),"") -> 100 | AF60: =IFERROR(VLOOKUP(J60,Product_lookup!$A:$G,7,FALSE),"") -> 102 | AG60: =IFERROR((AD60-AE60-AF60)/AD60,"") -> 0.18875502
A61: 46266 | B61: SP | Manual | Skincare Essentials | Broad | C61: Face Care | D61: Enabled | E61: AG | Rose Water Toner | F61: Sponsored Products | G61: face toner | H61: BROAD | I61: rose water spray | J61: SKN-010 | K61: Top of Search | L61: 478 | M61: 3 | N61: =IF(L61=0,"",M61/L61) -> 0.0062761506 | O61: =IF(M61=0,"",P61/M61) -> 5.36 | P61: 16.08 | Q61: 0 | R61: 0 | S61: 0 | T61: =IF(Q61=0,"",P61/Q61) | U61: =IF(P61=0,"",Q61/P61) -> 0 | V61: =IF(M61=0,"",R61/M61) -> 0 | W61: 6 | X61: INR | Y61: India | AA61: =IF(OR(A61<DATE(2026,9,1),A61>DATE(2026,9,28)),"Check Date",INT((A61-DATE(2026,9,1))/7)+1) -> 1 | AB61: =IF(OR(AD61="",AE61="",AF61=""),"",S61*(AD61-AE61-AF61)-P61) -> -16.08 | AC61: =IF(P61<0,"Review",IF(OR(AD61="",AE61="",AF61=""),"Cost missing",IF(P61=0,"No Spend",IF(Q61=0,"No Sales",IF(P61/Q61<AG61,"Profitable","Losing"))))) -> No Sales | AD61: =IFERROR(VLOOKUP(J61,Product_lookup!$A:$G,5,FALSE),"") -> 249 | AE61: =IFERROR(VLOOKUP(J61,Product_lookup!$A:$G,6,FALSE),"") -> 100 | AF61: =IFERROR(VLOOKUP(J61,Product_lookup!$A:$G,7,FALSE),"") -> 102 | AG61: =IFERROR((AD61-AE61-AF61)/AD61,"") -> 0.18875502
A62: 46266 | B62: SP | Manual | Skincare Essentials | Broad | C62: Face Care | D62: Enabled | E62: AG | Sheet Mask | F62: Sponsored Products | G62: sheet mask | H62: BROAD | I62: face sheet mask for sensitive skin | J62: SKN-014 | K62: Top of Search | L62: 409 | M62: 9 | N62: =IF(L62=0,"",M62/L62) -> 0.02200489 | O62: =IF(M62=0,"",P62/M62) -> 8.72 | P62: 78.48 | Q62: 1047 | R62: 2 | S62: 3 | T62: =IF(Q62=0,"",P62/Q62) -> 0.07495702 | U62: =IF(P62=0,"",Q62/P62) -> 13.340979 | V62: =IF(M62=0,"",R62/M62) -> 0.22222222 | W62: 10.5 | X62: INR | Y62: India | AA62: =IF(OR(A62<DATE(2026,9,1),A62>DATE(2026,9,28)),"Check Date",INT((A62-DATE(2026,9,1))/7)+1) -> 1 | AB62: =IF(OR(AD62="",AE62="",AF62=""),"",S62*(AD62-AE62-AF62)-P62) -> 236.52 | AC62: =IF(P62<0,"Review",IF(OR(AD62="",AE62="",AF62=""),"Cost missing",IF(P62=0,"No Spend",IF(Q62=0,"No Sales",IF(P62/Q62<AG62,"Profitable","Losing"))))) -> Profitable | AD62: =IFERROR(VLOOKUP(J62,Product_lookup!$A:$G,5,FALSE),"") -> 349 | AE62: =IFERROR(VLOOKUP(J62,Product_lookup!$A:$G,6,FALSE),"") -> 133 | AF62: =IFERROR(VLOOKUP(J62,Product_lookup!$A:$G,7,FALSE),"") -> 111 | AG62: =IFERROR((AD62-AE62-AF62)/AD62,"") -> 0.3008596
A63: 46266 | B63: SP | Manual | Skincare Essentials | Broad | C63: Face Care | D63: Enabled | E63: AG | Sheet Mask | F63: Sponsored Products | G63: sheet mask | H63: BROAD | I63: free sample face cream | J63: SKN-014 | K63: Product Pages | L63: 409 | M63: 0 | N63: =IF(L63=0,"",M63/L63) -> 0 | O63: =IF(M63=0,"",P63/M63) | P63: 0 | Q63: 0 | R63: 0 | S63: 0 | T63: =IF(Q63=0,"",P63/Q63) | U63: =IF(P63=0,"",Q63/P63) | V63: =IF(M63=0,"",R63/M63) | W63: 10 | X63: INR | Y63: India | AA63: =IF(OR(A63<DATE(2026,9,1),A63>DATE(2026,9,28)),"Check Date",INT((A63-DATE(2026,9,1))/7)+1) -> 1 | AB63: =IF(OR(AD63="",AE63="",AF63=""),"",S63*(AD63-AE63-AF63)-P63) -> 0 | AC63: =IF(P63<0,"Review",IF(OR(AD63="",AE63="",AF63=""),"Cost missing",IF(P63=0,"No Spend",IF(Q63=0,"No Sales",IF(P63/Q63<AG63,"Profitable","Losing"))))) -> No Spend | AD63: =IFERROR(VLOOKUP(J63,Product_lookup!$A:$G,5,FALSE),"") -> 349 | AE63: =IFERROR(VLOOKUP(J63,Product_lookup!$A:$G,6,FALSE),"") -> 133 | AF63: =IFERROR(VLOOKUP(J63,Product_lookup!$A:$G,7,FALSE),"") -> 111 | AG63: =IFERROR((AD63-AE63-AF63)/AD63,"") -> 0.3008596
A64: 46266 | B64: SP | Manual | Skincare Essentials | Broad | C64: Face Care | D64: Enabled | E64: AG | Sheet Mask | F64: Sponsored Products | G64: face sheet mask | H64: BROAD | I64: face sheet mask for night use | J64: SKN-014 | K64: Product Pages | L64: 271 | M64: 3 | N64: =IF(L64=0,"",M64/L64) -> 0.011070111 | O64: =IF(M64=0,"",P64/M64) -> 5.62 | P64: 16.86 | Q64: 349 | R64: 1 | S64: 1 | T64: =IF(Q64=0,"",P64/Q64) -> 0.048309456 | U64: =IF(P64=0,"",Q64/P64) -> 20.699881 | V64: =IF(M64=0,"",R64/M64) -> 0.33333333 | W64: 7.5 | X64: INR | Y64: India | AA64: =IF(OR(A64<DATE(2026,9,1),A64>DATE(2026,9,28)),"Check Date",INT((A64-DATE(2026,9,1))/7)+1) -> 1 | AB64: =IF(OR(AD64="",AE64="",AF64=""),"",S64*(AD64-AE64-AF64)-P64) -> 88.14 | AC64: =IF(P64<0,"Review",IF(OR(AD64="",AE64="",AF64=""),"Cost missing",IF(P64=0,"No Spend",IF(Q64=0,"No Sales",IF(P64/Q64<AG64,"Profitable","Losing"))))) -> Profitable | AD64: =IFERROR(VLOOKUP(J64,Product_lookup!$A:$G,5,FALSE),"") -> 349 | AE64: =IFERROR(VLOOKUP(J64,Product_lookup!$A:$G,6,FALSE),"") -> 133 | AF64: =IFERROR(VLOOKUP(J64,Product_lookup!$A:$G,7,FALSE),"") -> 111 | AG64: =IFERROR((AD64-AE64-AF64)/AD64,"") -> 0.3008596
A65: 46266 | B65: SP | Manual | Hair Care | Phrase | C65: Body & Hair | D65: Enabled | E65: AG | Onion Hair Oil | F65: Sponsored Products | G65: hair oil | H65: PHRASE | I65: skinlore hair oil for hair growth | J65: SKN-021 | K65: Rest of Search | L65: 766 | M65: 3 | N65: =IF(L65=0,"",M65/L65) -> 0.0039164491 | O65: =IF(M65=0,"",P65/M65) -> 6.71 | P65: 20.13 | Q65: 0 | R65: 0 | S65: 0 | T65: =IF(Q65=0,"",P65/Q65) | U65: =IF(P65=0,"",Q65/P65) -> 0 | V65: =IF(M65=0,"",R65/M65) -> 0 | W65: 10.5 | X65: INR | Y65: India | AA65: =IF(OR(A65<DATE(2026,9,1),A65>DATE(2026,9,28)),"Check Date",INT((A65-DATE(2026,9,1))/7)+1) -> 1 | AB65: =IF(OR(AD65="",AE65="",AF65=""),"",S65*(AD65-AE65-AF65)-P65) -> -20.13 | AC65: =IF(P65<0,"Review",IF(OR(AD65="",AE65="",AF65=""),"Cost missing",IF(P65=0,"No Spend",IF(Q65=0,"No Sales",IF(P65/Q65<AG65,"Profitable","Losing"))))) -> No Sales | AD65: =IFERROR(VLOOKUP(J65,Product_lookup!$A:$G,5,FALSE),"") -> 399 | AE65: =IFERROR(VLOOKUP(J65,Product_lookup!$A:$G,6,FALSE),"") -> 148 | AF65: =IFERROR(VLOOKUP(J65,Product_lookup!$A:$G,7,FALSE),"") -> 126 | AG65: =IFERROR((AD65-AE65-AF65)/AD65,"") -> 0.31328321
A66: 46266 | B66: SP | Manual | Hair Care | Phrase | C66: Body & Hair | D66: Enabled | E66: AG | Onion Hair Oil | F66: Sponsored Products | G66: onion hair oil | H66: PHRASE | I66: comb for men | J66: SKN-021 | K66: Top of Search | L66: 414 | M66: 3 | N66: =IF(L66=0,"",M66/L66) -> 0.0072463768 | O66: =IF(M66=0,"",P66/M66) -> 8.35 | P66: 25.05 | Q66: 0 | R66: 0 | S66: 0 | T66: =IF(Q66=0,"",P66/Q66) | U66: =IF(P66=0,"",Q66/P66) -> 0 | V66: =IF(M66=0,"",R66/M66) -> 0 | W66: 10 | X66: INR | Y66: India | AA66: =IF(OR(A66<DATE(2026,9,1),A66>DATE(2026,9,28)),"Check Date",INT((A66-DATE(2026,9,1))/7)+1) -> 1 | AB66: =IF(OR(AD66="",AE66="",AF66=""),"",S66*(AD66-AE66-AF66)-P66) -> -25.05 | AC66: =IF(P66<0,"Review",IF(OR(AD66="",AE66="",AF66=""),"Cost missing",IF(P66=0,"No Spend",IF(Q66=0,"No Sales",IF(P66/Q66<AG66,"Profitable","Losing"))))) -> No Sales | AD66: =IFERROR(VLOOKUP(J66,Product_lookup!$A:$G,5,FALSE),"") -> 399 | AE66: =IFERROR(VLOOKUP(J66,Product_lookup!$A:$G,6,FALSE),"") -> 148 | AF66: =IFERROR(VLOOKUP(J66,Product_lookup!$A:$G,7,FALSE),"") -> 126 | AG66: =IFERROR((AD66-AE66-AF66)/AD66,"") -> 0.31328321
A67: 46266 | B67: SP | Manual | Hair Care | Phrase | C67: Body & Hair | D67: Enabled | E67: AG | Onion Hair Oil | F67: Sponsored Products | G67: onion hair oil | H67: PHRASE | I67: hair oil for hair growth for hair growth | J67: SKN-021 | K67: Product Pages | L67: 330 | M67: 3 | N67: =IF(L67=0,"",M67/L67) -> 0.0090909091 | O67: =IF(M67=0,"",P67/M67) -> 8.3 | P67: 24.9 | Q67: 0 | R67: 0 | S67: 0 | T67: =IF(Q67=0,"",P67/Q67) | U67: =IF(P67=0,"",Q67/P67) -> 0 | V67: =IF(M67=0,"",R67/M67) -> 0 | W67: 11 | X67: INR | Y67: India | AA67: =IF(OR(A67<DATE(2026,9,1),A67>DATE(2026,9,28)),"Check Date",INT((A67-DATE(2026,9,1))/7)+1) -> 1 | AB67: =IF(OR(AD67="",AE67="",AF67=""),"",S67*(AD67-AE67-AF67)-P67) -> -24.9 | AC67: =IF(P67<0,"Review",IF(OR(AD67="",AE67="",AF67=""),"Cost missing",IF(P67=0,"No Spend",IF(Q67=0,"No Sales",IF(P67/Q67<AG67,"Profitable","Losing"))))) -> No Sales | AD67: =IFERROR(VLOOKUP(J67,Product_lookup!$A:$G,5,FALSE),"") -> 399 | AE67: =IFERROR(VLOOKUP(J67,Product_lookup!$A:$G,6,FALSE),"") -> 148 | AF67: =IFERROR(VLOOKUP(J67,Product_lookup!$A:$G,7,FALSE),"") -> 126 | AG67: =IFERROR((AD67-AE67-AF67)/AD67,"") -> 0.31328321
A68: 46266 | B68: SP | Manual | Hair Care | Phrase | C68: Body & Hair | D68: Enabled | E68: AG | Anti Dandruff Shampoo | F68: Sponsored Products | G68: dandruff shampoo | H68: PHRASE | I68: veluna shampoo for dandruff | J68: SKN-022 | K68: Rest of Search | L68: 347 | M68: 1 | N68: =IF(L68=0,"",M68/L68) -> 0.0028818444 | O68: =IF(M68=0,"",P68/M68) -> 11.18 | P68: 11.18 | Q68: 0 | R68: 0 | S68: 0 | T68: =IF(Q68=0,"",P68/Q68) | U68: =IF(P68=0,"",Q68/P68) -> 0 | V68: =IF(M68=0,"",R68/M68) -> 0 | W68: 14 | X68: INR | Y68: India | AA68: =IF(OR(A68<DATE(2026,9,1),A68>DATE(2026,9,28)),"Check Date",INT((A68-DATE(2026,9,1))/7)+1) -> 1 | AB68: =IF(OR(AD68="",AE68="",AF68=""),"",S68*(AD68-AE68-AF68)-P68) -> -11.18 | AC68: =IF(P68<0,"Review",IF(OR(AD68="",AE68="",AF68=""),"Cost missing",IF(P68=0,"No Spend",IF(Q68=0,"No Sales",IF(P68/Q68<AG68,"Profitable","Losing"))))) -> No Sales | AD68: =IFERROR(VLOOKUP(J68,Product_lookup!$A:$G,5,FALSE),"") -> 429 | AE68: =IFERROR(VLOOKUP(J68,Product_lookup!$A:$G,6,FALSE),"") -> 159 | AF68: =IFERROR(VLOOKUP(J68,Product_lookup!$A:$G,7,FALSE),"") -> 139 | AG68: =IFERROR((AD68-AE68-AF68)/AD68,"") -> 0.30536131
A69: 46266 | B69: SP | Manual | Hair Care | Phrase | C69: Body & Hair | D69: Enabled | E69: AG | Anti Dandruff Shampoo | F69: Sponsored Products | G69: anti dandruff shampoo | H69: PHRASE | I69: dandruff shampoo | J69: SKN-022 | K69: Rest of Search | L69: 538 | M69: 2 | N69: =IF(L69=0,"",M69/L69) -> 0.0037174721 | O69: =IF(M69=0,"",P69/M69) -> 9.75 | P69: 19.5 | Q69: 0 | R69: 0 | S69: 0 | T69: =IF(Q69=0,"",P69/Q69) | U69: =IF(P69=0,"",Q69/P69) -> 0 | V69: =IF(M69=0,"",R69/M69) -> 0 | W69: 13.5 | X69: INR | Y69: India | AA69: =IF(OR(A69<DATE(2026,9,1),A69>DATE(2026,9,28)),"Check Date",INT((A69-DATE(2026,9,1))/7)+1) -> 1 | AB69: =IF(OR(AD69="",AE69="",AF69=""),"",S69*(AD69-AE69-AF69)-P69) -> -19.5 | AC69: =IF(P69<0,"Review",IF(OR(AD69="",AE69="",AF69=""),"Cost missing",IF(P69=0,"No Spend",IF(Q69=0,"No Sales",IF(P69/Q69<AG69,"Profitable","Losing"))))) -> No Sales | AD69: =IFERROR(VLOOKUP(J69,Product_lookup!$A:$G,5,FALSE),"") -> 429 | AE69: =IFERROR(VLOOKUP(J69,Product_lookup!$A:$G,6,FALSE),"") -> 159 | AF69: =IFERROR(VLOOKUP(J69,Product_lookup!$A:$G,7,FALSE),"") -> 139 | AG69: =IFERROR((AD69-AE69-AF69)/AD69,"") -> 0.30536131
... A84: 46292 | B84: SP | Manual | Masks & Gels | Broad | C84: Face Care | D84: Paused | E84: AG | Clay Face Mask | F84: Sponsored Products | G84: multani mitti face pack | H84: BROAD | I84: face cream for dogs | J84: SKN-012 | K84: Top of Search | L84: 1110 | M84: 10 | N84: =IF(L84=0,"",M84/L84) -> 0.009009009 | O84: =IF(M84=0,"",P84/M84) -> 14.49 | P84: 144.9 | Q84: 0 | R84: 0 | S84: 0 | T84: =IF(Q84=0,"",P84/Q84) | U84: =IF(P84=0,"",Q84/P84) -> 0 | V84: =IF(M84=0,"",R84/M84) -> 0 | W84: 7.5 | X84: INR | Y84: India | AA84: =IF(OR(A84<DATE(2026,9,1),A84>DATE(2026,9,28)),"Check Date",INT((A84-DATE(2026,9,1))/7)+1) -> 4 | AB84: =IF(OR(AD84="",AE84="",AF84=""),"",S84*(AD84-AE84-AF84)-P84) -> -144.9 | AC84: =IF(P84<0,"Review",IF(OR(AD84="",AE84="",AF84=""),"Cost missing",IF(P84=0,"No Spend",IF(Q84=0,"No Sales",IF(P84/Q84<AG84,"Profitable","Losing"))))) -> No Sales | AD84: =IFERROR(VLOOKUP(J84,Product_lookup!$A:$G,5,FALSE),"") -> 379 | AE84: =IFERROR(VLOOKUP(J84,Product_lookup!$A:$G,6,FALSE),"") -> 140 | AF84: =IFERROR(VLOOKUP(J84,Product_lookup!$A:$G,7,FALSE),"") -> 114 | AG84: =IFERROR((AD84-AE84-AF84)/AD84,"") -> 0.3298153
A85: 46266 | B85: SP | Product Targeting | Competitors | C85: Face Care | D85: Enabled | E85: AG | Vitamin C Serum | F85: Sponsored Products | G85: asin=b0xanrgqoz | H85: PRODUCT | I85: b0xanrgqoz | J85: SKN-001 | K85: Rest of Search | L85: 1684 | M85: 10 | N85: =IF(L85=0,"",M85/L85) -> 0.0059382423 | O85: =IF(M85=0,"",P85/M85) -> 7.04 | P85: 70.4 | Q85: 0 | R85: 0 | S85: 0 | T85: =IF(Q85=0,"",P85/Q85) | U85: =IF(P85=0,"",Q85/P85) -> 0 | V85: =IF(M85=0,"",R85/M85) -> 0 | W85: 12 | X85: INR | Y85: India | Z85: budget raised | AA85: =IF(OR(A85<DATE(2026,9,1),A85>DATE(2026,9,28)),"Check Date",INT((A85-DATE(2026,9,1))/7)+1) -> 1 | AB85: =IF(OR(AD85="",AE85="",AF85=""),"",S85*(AD85-AE85-AF85)-P85) -> -70.4 | AC85: =IF(P85<0,"Review",IF(OR(AD85="",AE85="",AF85=""),"Cost missing",IF(P85=0,"No Spend",IF(Q85=0,"No Sales",IF(P85/Q85<AG85,"Profitable","Losing"))))) -> No Sales | AD85: =IFERROR(VLOOKUP(J85,Product_lookup!$A:$G,5,FALSE),"") -> 599 | AE85: =IFERROR(VLOOKUP(J85,Product_lookup!$A:$G,6,FALSE),"") -> 216 | AF85: =IFERROR(VLOOKUP(J85,Product_lookup!$A:$G,7,FALSE),"") -> 144 | AG85: =IFERROR((AD85-AE85-AF85)/AD85,"") -> 0.39899833
A86: 46266 | B86: SP | Product Targeting | Competitors | C86: Face Care | D86: Enabled | E86: AG | Vitamin C Serum | F86: Sponsored Products | G86: asin=b0y9zbiy9g | H86: PRODUCT | I86: b0y9zbiy9g | J86: SKN-001 | K86: Product Pages | L86: 216 | M86: 1 | N86: =IF(L86=0,"",M86/L86) -> 0.0046296296 | O86: =IF(M86=0,"",P86/M86) -> 12.65 | P86: 12.65 | Q86: 0 | R86: 0 | S86: 0 | T86: =IF(Q86=0,"",P86/Q86) | U86: =IF(P86=0,"",Q86/P86) -> 0 | V86: =IF(M86=0,"",R86/M86) -> 0 | W86: 16 | X86: INR | Y86: India | AA86: =IF(OR(A86<DATE(2026,9,1),A86>DATE(2026,9,28)),"Check Date",INT((A86-DATE(2026,9,1))/7)+1) -> 1 | AB86: =IF(OR(AD86="",AE86="",AF86=""),"",S86*(AD86-AE86-AF86)-P86) -> -12.65 | AC86: =IF(P86<0,"Review",IF(OR(AD86="",AE86="",AF86=""),"Cost missing",IF(P86=0,"No Spend",IF(Q86=0,"No Sales",IF(P86/Q86<AG86,"Profitable","Losing"))))) -> No Sales | AD86: =IFERROR(VLOOKUP(J86,Product_lookup!$A:$G,5,FALSE),"") -> 599 | AE86: =IFERROR(VLOOKUP(J86,Product_lookup!$A:$G,6,FALSE),"") -> 216 | AF86: =IFERROR(VLOOKUP(J86,Product_lookup!$A:$G,7,FALSE),"") -> 144 | AG86: =IFERROR((AD86-AE86-AF86)/AD86,"") -> 0.39899833
A87: 46266 | B87: SP | Product Targeting | Competitors | C87: Face Care | D87: Enabled | E87: AG | Sunscreen Spf 50 | F87: Sponsored Products | G87: asin=b0q7ldyo0l | H87: PRODUCT | I87: b0q7ldyo0l | J87: SKN-006 | K87: Product Pages | L87: 1119 | M87: 5 | N87: =IF(L87=0,"",M87/L87) -> 0.0044682752 | O87: =IF(M87=0,"",P87/M87) -> 7.99 | P87: 39.95 | Q87: 0 | R87: 0 | S87: 0 | T87: =IF(Q87=0,"",P87/Q87) | U87: =IF(P87=0,"",Q87/P87) -> 0 | V87: =IF(M87=0,"",R87/M87) -> 0 | W87: 11 | X87: INR | Y87: India | AA87: =IF(OR(A87<DATE(2026,9,1),A87>DATE(2026,9,28)),"Check Date",INT((A87-DATE(2026,9,1))/7)+1) -> 1 | AB87: =IF(OR(AD87="",AE87="",AF87=""),"",S87*(AD87-AE87-AF87)-P87) -> -39.95 | AC87: =IF(P87<0,"Review",IF(OR(AD87="",AE87="",AF87=""),"Cost missing",IF(P87=0,"No Spend",IF(Q87=0,"No Sales",IF(P87/Q87<AG87,"Profitable","Losing"))))) -> No Sales | AD87: =IFERROR(VLOOKUP(J87,Product_lookup!$A:$G,5,FALSE),"") -> 449 | AE87: =IFERROR(VLOOKUP(J87,Product_lookup!$A:$G,6,FALSE),"") -> 162 | AF87: =IFERROR(VLOOKUP(J87,Product_lookup!$A:$G,7,FALSE),"") -> 130 | AG87: =IFERROR((AD87-AE87-AF87)/AD87,"") -> 0.34966592
A88: 46266 | B88: SP | Product Targeting | Competitors | C88: Face Care | D88: Enabled | E88: AG | Sunscreen Spf 50 | F88: Sponsored Products | G88: asin=b0kz0mqav8 | H88: PRODUCT | I88: b0kz0mqav8 | J88: SKN-006 | K88: Product Pages | L88: 2232 | M88: 12 | N88: =IF(L88=0,"",M88/L88) -> 0.0053763441 | O88: =IF(M88=0,"",P88/M88) -> 5.55 | P88: 66.6 | Q88: 0 | R88: 0 | S88: 0 | T88: =IF(Q88=0,"",P88/Q88) | U88: =IF(P88=0,"",Q88/P88) -> 0 | V88: =IF(M88=0,"",R88/M88) -> 0 | W88: 7.5 | X88: INR | Y88: India | AA88: =IF(OR(A88<DATE(2026,9,1),A88>DATE(2026,9,28)),"Check Date",INT((A88-DATE(2026,9,1))/7)+1) -> 1 | AB88: =IF(OR(AD88="",AE88="",AF88=""),"",S88*(AD88-AE88-AF88)-P88) -> -66.6 | AC88: =IF(P88<0,"Review",IF(OR(AD88="",AE88="",AF88=""),"Cost missing",IF(P88=0,"No Spend",IF(Q88=0,"No Sales",IF(P88/Q88<AG88,"Profitable","Losing"))))) -> No Sales | AD88: =IFERROR(VLOOKUP(J88,Product_lookup!$A:$G,5,FALSE),"") -> 449 | AE88: =IFERROR(VLOOKUP(J88,Product_lookup!$A:$G,6,FALSE),"") -> 162 | AF88: =IFERROR(VLOOKUP(J88,Product_lookup!$A:$G,7,FALSE),"") -> 130 | AG88: =IFERROR((AD88-AE88-AF88)/AD88,"") -> 0.34966592
A89: 46266 | B89: SP | Product Targeting | Competitors | C89: Face Care | D89: Enabled | E89: AG | Sunscreen Spf 50 | F89: Sponsored Products | G89: asin=b0s40ccjfn | H89: PRODUCT | I89: b0s40ccjfn | J89: SKN-006 | K89: Top of Search | L89: 480 | M89: 1 | N89: =IF(L89=0,"",M89/L89) -> 0.0020833333 | O89: =IF(M89=0,"",P89/M89) -> 8.8 | P89: 8.8 | Q89: 0 | R89: 0 | S89: 0 | T89: =IF(Q89=0,"",P89/Q89) | U89: =IF(P89=0,"",Q89/P89) -> 0 | V89: =IF(M89=0,"",R89/M89) -> 0 | W89: 9.5 | X89: INR | Y89: India | AA89: =IF(OR(A89<DATE(2026,9,1),A89>DATE(2026,9,28)),"Check Date",INT((A89-DATE(2026,9,1))/7)+1) -> 1 | AB89: =IF(OR(AD89="",AE89="",AF89=""),"",S89*(AD89-AE89-AF89)-P89) -> -8.8 | AC89: =IF(P89<0,"Review",IF(OR(AD89="",AE89="",AF89=""),"Cost missing",IF(P89=0,"No Spend",IF(Q89=0,"No Sales",IF(P89/Q89<AG89,"Profitable","Losing"))))) -> No Sales | AD89: =IFERROR(VLOOKUP(J89,Product_lookup!$A:$G,5,FALSE),"") -> 449 | AE89: =IFERROR(VLOOKUP(J89,Product_lookup!$A:$G,6,FALSE),"") -> 162 | AF89: =IFERROR(VLOOKUP(J89,Product_lookup!$A:$G,7,FALSE),"") -> 130 | AG89: =IFERROR((AD89-AE89-AF89)/AD89,"") -> 0.34966592
A90: 46266 | B90: SP | Product Targeting | Competitors | C90: Face Care | D90: Enabled | E90: AG | Face Wash | F90: Sponsored Products | G90: asin=b0g26g1i7r | H90: PRODUCT | I90: b0g26g1i7r | J90: SKN-008 | K90: Product Pages | L90: 1665 | M90: 9 | N90: =IF(L90=0,"",M90/L90) -> 0.0054054054 | O90: =IF(M90=0,"",P90/M90) -> 2.89 | P90: 26.01 | Q90: 0 | R90: 0 | S90: 0 | T90: =IF(Q90=0,"",P90/Q90) | U90: =IF(P90=0,"",Q90/P90) -> 0 | V90: =IF(M90=0,"",R90/M90) -> 0 | W90: 5.5 | X90: INR | Y90: India | AA90: =IF(OR(A90<DATE(2026,9,1),A90>DATE(2026,9,28)),"Check Date",INT((A90-DATE(2026,9,1))/7)+1) -> 1 | AB90: =IF(OR(AD90="",AE90="",AF90=""),"",S90*(AD90-AE90-AF90)-P90) -> -26.01 | AC90: =IF(P90<0,"Review",IF(OR(AD90="",AE90="",AF90=""),"Cost missing",IF(P90=0,"No Spend",IF(Q90=0,"No Sales",IF(P90/Q90<AG90,"Profitable","Losing"))))) -> No Sales | AD90: =IFERROR(VLOOKUP(J90,Product_lookup!$A:$G,5,FALSE),"") -> 299 | AE90: =IFERROR(VLOOKUP(J90,Product_lookup!$A:$G,6,FALSE),"") -> 114 | AF90: =IFERROR(VLOOKUP(J90,Product_lookup!$A:$G,7,FALSE),"") -> 107 | AG90: =IFERROR((AD90-AE90-AF90)/AD90,"") -> 0.26086957
A91: 46266 | B91: SP | Product Targeting | Competitors | C91: Face Care | D91: Enabled | E91: AG | Face Wash | F91: Sponsored Products | G91: asin=b0k1vxahqj | H91: PRODUCT | I91: b0k1vxahqj | J91: SKN-008 | K91: Product Pages | L91: 411 | M91: 3 | N91: =IF(L91=0,"",M91/L91) -> 0.0072992701 | O91: =IF(M91=0,"",P91/M91) -> 5.1 | P91: 15.3 | Q91: 0 | R91: 0 | S91: 0 | T91: =IF(Q91=0,"",P91/Q91) | U91: =IF(P91=0,"",Q91/P91) -> 0 | V91: =IF(M91=0,"",R91/M91) -> 0 | W91: 6.5 | X91: INR | Y91: India | AA91: =IF(OR(A91<DATE(2026,9,1),A91>DATE(2026,9,28)),"Check Date",INT((A91-DATE(2026,9,1))/7)+1) -> 1 | AB91: =IF(OR(AD91="",AE91="",AF91=""),"",S91*(AD91-AE91-AF91)-P91) -> -15.3 | AC91: =IF(P91<0,"Review",IF(OR(AD91="",AE91="",AF91=""),"Cost missing",IF(P91=0,"No Spend",IF(Q91=0,"No Sales",IF(P91/Q91<AG91,"Profitable","Losing"))))) -> No Sales | AD91: =IFERROR(VLOOKUP(J91,Product_lookup!$A:$G,5,FALSE),"") -> 299 | AE91: =IFERROR(VLOOKUP(J91,Product_lookup!$A:$G,6,FALSE),"") -> 114 | AF91: =IFERROR(VLOOKUP(J91,Product_lookup!$A:$G,7,FALSE),"") -> 107 | AG91: =IFERROR((AD91-AE91-AF91)/AD91,"") -> 0.26086957
A92: 46266 | B92: SP | Product Targeting | Competitors | C92: Face Care | D92: Enabled | E92: AG | Face Wash | F92: Sponsored Products | G92: asin=b0tkjhqzf8 | H92: PRODUCT | I92: b0tkjhqzf8 | J92: SKN-008 | K92: Product Pages | L92: 379 | M92: 0 | N92: =IF(L92=0,"",M92/L92) -> 0 | O92: =IF(M92=0,"",P92/M92) | P92: 0 | Q92: 0 | R92: 0 | S92: 0 | T92: =IF(Q92=0,"",P92/Q92) | U92: =IF(P92=0,"",Q92/P92) | V92: =IF(M92=0,"",R92/M92) | W92: 8.5 | X92: INR | Y92: India | AA92: =IF(OR(A92<DATE(2026,9,1),A92>DATE(2026,9,28)),"Check Date",INT((A92-DATE(2026,9,1))/7)+1) -> 1 | AB92: =IF(OR(AD92="",AE92="",AF92=""),"",S92*(AD92-AE92-AF92)-P92) -> 0 | AC92: =IF(P92<0,"Review",IF(OR(AD92="",AE92="",AF92=""),"Cost missing",IF(P92=0,"No Spend",IF(Q92=0,"No Sales",IF(P92/Q92<AG92,"Profitable","Losing"))))) -> No Spend | AD92: =IFERROR(VLOOKUP(J92,Product_lookup!$A:$G,5,FALSE),"") -> 299 | AE92: =IFERROR(VLOOKUP(J92,Product_lookup!$A:$G,6,FALSE),"") -> 114 | AF92: =IFERROR(VLOOKUP(J92,Product_lookup!$A:$G,7,FALSE),"") -> 107 | AG92: =IFERROR((AD92-AE92-AF92)/AD92,"") -> 0.26086957
A93: 46266 | B93: SP | Product Targeting | Competitors | C93: Face Care | D93: Enabled | E93: AG | Face Wash | F93: Sponsored Products | G93: asin=b0kpjx3wru | H93: PRODUCT | I93: b0kpjx3wru | J93: SKN-008 | K93: Product Pages | L93: 523 | M93: 4 | N93: =IF(L93=0,"",M93/L93) -> 0.0076481836 | O93: =IF(M93=0,"",P93/M93) -> 4.45 | P93: 17.8 | Q93: 0 | R93: 0 | S93: 0 | T93: =IF(Q93=0,"",P93/Q93) | U93: =IF(P93=0,"",Q93/P93) -> 0 | V93: =IF(M93=0,"",R93/M93) -> 0 | W93: 6.5 | X93: INR | Y93: India | AA93: =IF(OR(A93<DATE(2026,9,1),A93>DATE(2026,9,28)),"Check Date",INT((A93-DATE(2026,9,1))/7)+1) -> 1 | AB93: =IF(OR(AD93="",AE93="",AF93=""),"",S93*(AD93-AE93-AF93)-P93) -> -17.8 | AC93: =IF(P93<0,"Review",IF(OR(AD93="",AE93="",AF93=""),"Cost missing",IF(P93=0,"No Spend",IF(Q93=0,"No Sales",IF(P93/Q93<AG93,"Profitable","Losing"))))) -> No Sales | AD93: =IFERROR(VLOOKUP(J93,Product_lookup!$A:$G,5,FALSE),"") -> 299 | AE93: =IFERROR(VLOOKUP(J93,Product_lookup!$A:$G,6,FALSE),"") -> 114 | AF93: =IFERROR(VLOOKUP(J93,Product_lookup!$A:$G,7,FALSE),"") -> 107 | AG93: =IFERROR((AD93-AE93-AF93)/AD93,"") -> 0.26086957
A94: 46266 | B94: SP | Product Targeting | Competitors | C94: Face Care | D94: Enabled | E94: AG | Face Wash | F94: Sponsored Products | G94: asin=b0wezftacn | H94: PRODUCT | I94: b0wezftacn | J94: SKN-008 | K94: Top of Search | L94: 717 | M94: 7 | N94: =IF(L94=0,"",M94/L94) -> 0.009762901 | O94: =IF(M94=0,"",P94/M94) -> 8.16 | P94: 57.12 | Q94: 0 | R94: 0 | S94: 0 | T94: =IF(Q94=0,"",P94/Q94) | U94: =IF(P94=0,"",Q94/P94) -> 0 | V94: =IF(M94=0,"",R94/M94) -> 0 | W94: 8.5 | X94: INR | Y94: India | AA94: =IF(OR(A94<DATE(2026,9,1),A94>DATE(2026,9,28)),"Check Date",INT((A94-DATE(2026,9,1))/7)+1) -> 1 | AB94: =IF(OR(AD94="",AE94="",AF94=""),"",S94*(AD94-AE94-AF94)-P94) -> -57.12 | AC94: =IF(P94<0,"Review",IF(OR(AD94="",AE94="",AF94=""),"Cost missing",IF(P94=0,"No Spend",IF(Q94=0,"No Sales",IF(P94/Q94<AG94,"Profitable","Losing"))))) -> No Sales | AD94: =IFERROR(VLOOKUP(J94,Product_lookup!$A:$G,5,FALSE),"") -> 299 | AE94: =IFERROR(VLOOKUP(J94,Product_lookup!$A:$G,6,FALSE),"") -> 114 | AF94: =IFERROR(VLOOKUP(J94,Product_lookup!$A:$G,7,FALSE),"") -> 107 | AG94: =IFERROR((AD94-AE94-AF94)/AD94,"") -> 0.26086957
A95: 46266 | B95: SP | Product Targeting | Competitors | C95: Face Care | D95: Enabled | E95: AG | Face Wash | F95: Sponsored Products | G95: asin=b0ha6dl3dm | H95: PRODUCT | I95: b0ha6dl3dm | J95: SKN-008 | K95: Product Pages | L95: 288 | M95: 1 | N95: =IF(L95=0,"",M95/L95) -> 0.0034722222 | O95: =IF(M95=0,"",P95/M95) -> 4.85 | P95: 4.85 | Q95: 0 | R95: 0 | S95: 0 | T95: =IF(Q95=0,"",P95/Q95) | U95: =IF(P95=0,"",Q95/P95) -> 0 | V95: =IF(M95=0,"",R95/M95) -> 0 | W95: 7 | X95: INR | Y95: India | AA95: =IF(OR(A95<DATE(2026,9,1),A95>DATE(2026,9,28)),"Check Date",INT((A95-DATE(2026,9,1))/7)+1) -> 1 | AB95: =IF(OR(AD95="",AE95="",AF95=""),"",S95*(AD95-AE95-AF95)-P95) -> -4.85 | AC95: =IF(P95<0,"Review",IF(OR(AD95="",AE95="",AF95=""),"Cost missing",IF(P95=0,"No Spend",IF(Q95=0,"No Sales",IF(P95/Q95<AG95,"Profitable","Losing"))))) -> No Sales | AD95: =IFERROR(VLOOKUP(J95,Product_lookup!$A:$G,5,FALSE),"") -> 299 | AE95: =IFERROR(VLOOKUP(J95,Product_lookup!$A:$G,6,FALSE),"") -> 114 | AF95: =IFERROR(VLOOKUP(J95,Product_lookup!$A:$G,7,FALSE),"") -> 107 | AG95: =IFERROR((AD95-AE95-AF95)/AD95,"") -> 0.26086957
A96: 46266 | B96: SP | Product Targeting | Competitors | C96: Face Care | D96: Enabled | E96: AG | Face Wash | F96: Sponsored Products | G96: asin=b0kht5rj8u | H96: PRODUCT | I96: b0kht5rj8u | J96: SKN-008 | K96: Product Pages | L96: 782 | M96: 3 | N96: =IF(L96=0,"",M96/L96) -> 0.0038363171 | O96: =IF(M96=0,"",P96/M96) -> 4 | P96: 12 | Q96: 0 | R96: 0 | S96: 0 | T96: =IF(Q96=0,"",P96/Q96) | U96: =IF(P96=0,"",Q96/P96) -> 0 | V96: =IF(M96=0,"",R96/M96) -> 0 | W96: 7 | X96: INR | Y96: India | AA96: =IF(OR(A96<DATE(2026,9,1),A96>DATE(2026,9,28)),"Check Date",INT((A96-DATE(2026,9,1))/7)+1) -> 1 | AB96: =IF(OR(AD96="",AE96="",AF96=""),"",S96*(AD96-AE96-AF96)-P96) -> -12 | AC96: =IF(P96<0,"Review",IF(OR(AD96="",AE96="",AF96=""),"Cost missing",IF(P96=0,"No Spend",IF(Q96=0,"No Sales",IF(P96/Q96<AG96,"Profitable","Losing"))))) -> No Sales | AD96: =IFERROR(VLOOKUP(J96,Product_lookup!$A:$G,5,FALSE),"") -> 299 | AE96: =IFERROR(VLOOKUP(J96,Product_lookup!$A:$G,6,FALSE),"") -> 114 | AF96: =IFERROR(VLOOKUP(J96,Product_lookup!$A:$G,7,FALSE),"") -> 107 | AG96: =IFERROR((AD96-AE96-AF96)/AD96,"") -> 0.26086957
A97: 46266 | B97: SP | Manual | Lips & Eyes | Exact | C97: Face Care | D97: Enabled | E97: AG | Under Eye Cream | F97: Sponsored Products | G97: under eye cream | H97: EXACT | I97: under eye cream | J97: SKN-011 | K97: Top of Search | L97: 364 | M97: 1 | N97: =IF(L97=0,"",M97/L97) -> 0.0027472527 | O97: =IF(M97=0,"",P97/M97) -> 11.5 | P97: 11.5 | Q97: 0 | R97: 0 | S97: 0 | T97: =IF(Q97=0,"",P97/Q97) | U97: =IF(P97=0,"",Q97/P97) -> 0 | V97: =IF(M97=0,"",R97/M97) -> 0 | W97: 11.5 | X97: INR | Y97: India | AA97: =IF(OR(A97<DATE(2026,9,1),A97>DATE(2026,9,28)),"Check Date",INT((A97-DATE(2026,9,1))/7)+1) -> 1 | AB97: =IF(OR(AD97="",AE97="",AF97=""),"",S97*(AD97-AE97-AF97)-P97) -> -11.5 | AC97: =IF(P97<0,"Review",IF(OR(AD97="",AE97="",AF97=""),"Cost missing",IF(P97=0,"No Spend",IF(Q97=0,"No Sales",IF(P97/Q97<AG97,"Profitable","Losing"))))) -> No Sales | AD97: =IFERROR(VLOOKUP(J97,Product_lookup!$A:$G,5,FALSE),"") -> 499 | AE97: =IFERROR(VLOOKUP(J97,Product_lookup!$A:$G,6,FALSE),"") -> 180 | AF97: =IFERROR(VLOOKUP(J97,Product_lookup!$A:$G,7,FALSE),"") -> 125 | AG97: =IFERROR((AD97-AE97-AF97)/AD97,"") -> 0.38877756
... A150: 46267 | B150: SP | Manual | Skincare Essentials | Broad | C150: Face Care | D150: Enabled | E150: AG | Gel Moisturizer | F150: Sponsored Products | G150: oil free moisturizer | H150: BROAD | I150: gel moisturizer dermatologist tested | J150: SKN-005 | K150: Product Pages | L150: 151 | M150: 2 | N150: =IF(L150=0,"",M150/L150) -> 0.013245033 | O150: =IF(M150=0,"",P150/M150) -> 8.02 | P150: 16.04 | Q150: 0 | R150: 0 | S150: 0 | T150: =IF(Q150=0,"",P150/Q150) | U150: =IF(P150=0,"",Q150/P150) -> 0 | V150: =IF(M150=0,"",R150/M150) -> 0 | W150: 11 | X150: INR | Y150: India | AA150: =IF(OR(A150<DATE(2026,9,1),A150>DATE(2026,9,28)),"Check Date",INT((A150-DATE(2026,9,1))/7)+1) -> 1 | AB150: =IF(OR(AD150="",AE150="",AF150=""),"",S150*(AD150-AE150-AF150)-P150) -> -16.04 | AC150: =IF(P150<0,"Review",IF(OR(AD150="",AE150="",AF150=""),"Cost missing",IF(P150=0,"No Spend",IF(Q150=0,"No Sales",IF(P150/Q150<AG150,"Profitable","Losing"))))) -> No Sales | AD150: =IFERROR(VLOOKUP(J150,Product_lookup!$A:$G,5,FALSE),"") -> 399 | AE150: =IFERROR(VLOOKUP(J150,Product_lookup!$A:$G,6,FALSE),"") -> 148 | AF150: =IFERROR(VLOOKUP(J150,Product_lookup!$A:$G,7,FALSE),"") -> 126 | AG150: =IFERROR((AD150-AE150-AF150)/AD150,"") -> 0.31328321
A151: 46267 | B151: SP | Manual | Skincare Essentials | Broad | C151: Face Care | D151: Enabled | E151: AG | Gel Moisturizer | F151: Sponsored Products | G151: gel moisturizer | H151: BROAD | I151: face moisturizer | J151: SKN-005 | K151: Rest of Search | L151: 671 | M151: 4 | N151: =IF(L151=0,"",M151/L151) -> 0.0059612519 | O151: =IF(M151=0,"",P151/M151) -> 8.63 | P151: 34.52 | Q151: 0 | R151: 0 | S151: 0 | T151: =IF(Q151=0,"",P151/Q151) | U151: =IF(P151=0,"",Q151/P151) -> 0 | V151: =IF(M151=0,"",R151/M151) -> 0 | W151: 11.5 | X151: INR | Y151: India | Z151: price test | AA151: =IF(OR(A151<DATE(2026,9,1),A151>DATE(2026,9,28)),"Check Date",INT((A151-DATE(2026,9,1))/7)+1) -> 1 | AB151: =IF(OR(AD151="",AE151="",AF151=""),"",S151*(AD151-AE151-AF151)-P151) -> -34.52 | AC151: =IF(P151<0,"Review",IF(OR(AD151="",AE151="",AF151=""),"Cost missing",IF(P151=0,"No Spend",IF(Q151=0,"No Sales",IF(P151/Q151<AG151,"Profitable","Losing"))))) -> No Sales | AD151: =IFERROR(VLOOKUP(J151,Product_lookup!$A:$G,5,FALSE),"") -> 399 | AE151: =IFERROR(VLOOKUP(J151,Product_lookup!$A:$G,6,FALSE),"") -> 148 | AF151: =IFERROR(VLOOKUP(J151,Product_lookup!$A:$G,7,FALSE),"") -> 126 | AG151: =IFERROR((AD151-AE151-AF151)/AD151,"") -> 0.31328321
A152: 46267 | B152: SP | Manual | Skincare Essentials | Broad | C152: Face Care | D152: Enabled | E152: AG | Face Wash | F152: Sponsored Products | G152: foaming face wash | H152: BROAD | I152: face wash | J152: SKN-008 | K152: Top of Search | L152: 1097 | M152: 15 | N152: =IF(L152=0,"",M152/L152) -> 0.013673655 | O152: =IF(M152=0,"",P152/M152) -> 9 | P152: 135 | Q152: 0 | R152: 0 | S152: 0 | T152: =IF(Q152=0,"",P152/Q152) | U152: =IF(P152=0,"",Q152/P152) -> 0 | V152: =IF(M152=0,"",R152/M152) -> 0 | W152: 9 | X152: INR | Y152: India | AA152: =IF(OR(A152<DATE(2026,9,1),A152>DATE(2026,9,28)),"Check Date",INT((A152-DATE(2026,9,1))/7)+1) -> 1 | AB152: =IF(OR(AD152="",AE152="",AF152=""),"",S152*(AD152-AE152-AF152)-P152) -> -135 | AC152: =IF(P152<0,"Review",IF(OR(AD152="",AE152="",AF152=""),"Cost missing",IF(P152=0,"No Spend",IF(Q152=0,"No Sales",IF(P152/Q152<AG152,"Profitable","Losing"))))) -> No Sales | AD152: =IFERROR(VLOOKUP(J152,Product_lookup!$A:$G,5,FALSE),"") -> 299 | AE152: =IFERROR(VLOOKUP(J152,Product_lookup!$A:$G,6,FALSE),"") -> 114 | AF152: =IFERROR(VLOOKUP(J152,Product_lookup!$A:$G,7,FALSE),"") -> 107 | AG152: =IFERROR((AD152-AE152-AF152)/AD152,"") -> 0.26086957
A153: 46267 | B153: SP | Manual | Skincare Essentials | Broad | C153: Face Care | D153: Enabled | E153: AG | Face Wash | F153: Sponsored Products | G153: foaming face wash | H153: BROAD | I153: face wash for oily skin for combination skin | J153: SKN-008 | K153: Product Pages | L153: 369 | M153: 3 | N153: =IF(L153=0,"",M153/L153) -> 0.0081300813 | O153: =IF(M153=0,"",P153/M153) -> 4.64 | P153: 13.92 | Q153: 0 | R153: 0 | S153: 0 | T153: =IF(Q153=0,"",P153/Q153) | U153: =IF(P153=0,"",Q153/P153) -> 0 | V153: =IF(M153=0,"",R153/M153) -> 0 | W153: 9 | X153: INR | Y153: India | AA153: =IF(OR(A153<DATE(2026,9,1),A153>DATE(2026,9,28)),"Check Date",INT((A153-DATE(2026,9,1))/7)+1) -> 1 | AB153: =IF(OR(AD153="",AE153="",AF153=""),"",S153*(AD153-AE153-AF153)-P153) -> -13.92 | AC153: =IF(P153<0,"Review",IF(OR(AD153="",AE153="",AF153=""),"Cost missing",IF(P153=0,"No Spend",IF(Q153=0,"No Sales",IF(P153/Q153<AG153,"Profitable","Losing"))))) -> No Sales | AD153: =IFERROR(VLOOKUP(J153,Product_lookup!$A:$G,5,FALSE),"") -> 299 | AE153: =IFERROR(VLOOKUP(J153,Product_lookup!$A:$G,6,FALSE),"") -> 114 | AF153: =IFERROR(VLOOKUP(J153,Product_lookup!$A:$G,7,FALSE),"") -> 107 | AG153: =IFERROR((AD153-AE153-AF153)/AD153,"") -> 0.26086957
A154: 46267 | B154: SP | Manual | Skincare Essentials | Broad | C154: Face Care | D154: Enabled | E154: AG | Face Wash | F154: Sponsored Products | G154: foaming face wash | H154: BROAD | I154: face wash for oily skin | J154: SKN-008 | K154: Product Pages | L154: 526 | M154: 5 | N154: =IF(L154=0,"",M154/L154) -> 0.0095057034 | O154: =IF(M154=0,"",P154/M154) -> 5.39 | P154: 26.95 | Q154: 0 | R154: 0 | S154: 0 | T154: =IF(Q154=0,"",P154/Q154) | U154: =IF(P154=0,"",Q154/P154) -> 0 | V154: =IF(M154=0,"",R154/M154) -> 0 | W154: 9 | X154: INR | Y154: India | AA154: =IF(OR(A154<DATE(2026,9,1),A154>DATE(2026,9,28)),"Check Date",INT((A154-DATE(2026,9,1))/7)+1) -> 1 | AB154: =IF(OR(AD154="",AE154="",AF154=""),"",S154*(AD154-AE154-AF154)-P154) -> -26.95 | AC154: =IF(P154<0,"Review",IF(OR(AD154="",AE154="",AF154=""),"Cost missing",IF(P154=0,"No Spend",IF(Q154=0,"No Sales",IF(P154/Q154<AG154,"Profitable","Losing"))))) -> No Sales | AD154: =IFERROR(VLOOKUP(J154,Product_lookup!$A:$G,5,FALSE),"") -> 299 | AE154: =IFERROR(VLOOKUP(J154,Product_lookup!$A:$G,6,FALSE),"") -> 114 | AF154: =IFERROR(VLOOKUP(J154,Product_lookup!$A:$G,7,FALSE),"") -> 107 | AG154: =IFERROR((AD154-AE154-AF154)/AD154,"") -> 0.26086957
A155: 46267 | B155: SP | Manual | Skincare Essentials | Broad | C155: Face Care | D155: Enabled | E155: AG | Face Wash | F155: Sponsored Products | G155: foaming face wash | H155: BROAD | I155: face wash under 500 | J155: SKN-008 | K155: Product Pages | L155: 232 | M155: 3 | N155: =IF(L155=0,"",M155/L155) -> 0.012931034 | O155: =IF(M155=0,"",P155/M155) -> 5.39 | P155: 16.17 | Q155: 299 | R155: 1 | S155: 1 | T155: =IF(Q155=0,"",P155/Q155) -> 0.054080268 | U155: =IF(P155=0,"",Q155/P155) -> 18.491033 | V155: =IF(M155=0,"",R155/M155) -> 0.33333333 | W155: 7.5 | X155: INR | Y155: India | AA155: =IF(OR(A155<DATE(2026,9,1),A155>DATE(2026,9,28)),"Check Date",INT((A155-DATE(2026,9,1))/7)+1) -> 1 | AB155: =IF(OR(AD155="",AE155="",AF155=""),"",S155*(AD155-AE155-AF155)-P155) -> 61.83 | AC155: =IF(P155<0,"Review",IF(OR(AD155="",AE155="",AF155=""),"Cost missing",IF(P155=0,"No Spend",IF(Q155=0,"No Sales",IF(P155/Q155<AG155,"Profitable","Losing"))))) -> Profitable | AD155: =IFERROR(VLOOKUP(J155,Product_lookup!$A:$G,5,FALSE),"") -> 299 | AE155: =IFERROR(VLOOKUP(J155,Product_lookup!$A:$G,6,FALSE),"") -> 114 | AF155: =IFERROR(VLOOKUP(J155,Product_lookup!$A:$G,7,FALSE),"") -> 107 | AG155: =IFERROR((AD155-AE155-AF155)/AD155,"") -> 0.26086957
A156: 46267 | B156: SP | Manual | Skincare Essentials | Broad | C156: Face Care | D156: Enabled | E156: AG | Face Wash | F156: Sponsored Products | G156: foaming face wash | H156: BROAD | I156: foaming face wash for summer | J156: SKN-008 | K156: Top of Search | L156: 127 | M156: 4 | N156: =IF(L156=0,"",M156/L156) -> 0.031496063 | O156: =IF(M156=0,"",P156/M156) -> 9 | P156: 36 | Q156: 299 | R156: 1 | S156: 1 | T156: =IF(Q156=0,"",P156/Q156) -> 0.12040134 | U156: =IF(P156=0,"",Q156/P156) -> 8.3055556 | V156: =IF(M156=0,"",R156/M156) -> 0.25 | W156: 9 | X156: INR | Y156: India | AA156: =IF(OR(A156<DATE(2026,9,1),A156>DATE(2026,9,28)),"Check Date",INT((A156-DATE(2026,9,1))/7)+1) -> 1 | AB156: =IF(OR(AD156="",AE156="",AF156=""),"",S156*(AD156-AE156-AF156)-P156) -> 42 | AC156: =IF(P156<0,"Review",IF(OR(AD156="",AE156="",AF156=""),"Cost missing",IF(P156=0,"No Spend",IF(Q156=0,"No Sales",IF(P156/Q156<AG156,"Profitable","Losing"))))) -> Profitable | AD156: =IFERROR(VLOOKUP(J156,Product_lookup!$A:$G,5,FALSE),"") -> 299 | AE156: =IFERROR(VLOOKUP(J156,Product_lookup!$A:$G,6,FALSE),"") -> 114 | AF156: =IFERROR(VLOOKUP(J156,Product_lookup!$A:$G,7,FALSE),"") -> 107 | AG156: =IFERROR((AD156-AE156-AF156)/AD156,"") -> 0.26086957
A157: 46286 | C157: Face Care | D157: Enabled | E157: AG | Vitamin C Serum | F157: Sponsored Products | G157: face serum vitamin c for winter | H157: EXACT | I157: face serum vitamin c for winter | J157: SKN-001 | K157: Product Pages | L157: 234 | M157: 0 | N157: =IF(L157=0,"",M157/L157) -> 0 | O157: =IF(M157=0,"",P157/M157) | P157: 0 | Q157: 0 | R157: 0 | S157: 0 | T157: =IF(Q157=0,"",P157/Q157) | U157: =IF(P157=0,"",Q157/P157) | V157: =IF(M157=0,"",R157/M157) | W157: 23 | X157: INR | Y157: India | AA157: =IF(OR(A157<DATE(2026,9,1),A157>DATE(2026,9,28)),"Check Date",INT((A157-DATE(2026,9,1))/7)+1) -> 3 | AB157: =IF(OR(AD157="",AE157="",AF157=""),"",S157*(AD157-AE157-AF157)-P157) -> 0 | AC157: =IF(P157<0,"Review",IF(OR(AD157="",AE157="",AF157=""),"Cost missing",IF(P157=0,"No Spend",IF(Q157=0,"No Sales",IF(P157/Q157<AG157,"Profitable","Losing"))))) -> No Spend | AD157: =IFERROR(VLOOKUP(J157,Product_lookup!$A:$G,5,FALSE),"") -> 599 | AE157: =IFERROR(VLOOKUP(J157,Product_lookup!$A:$G,6,FALSE),"") -> 216 | AF157: =IFERROR(VLOOKUP(J157,Product_lookup!$A:$G,7,FALSE),"") -> 144 | AG157: =IFERROR((AD157-AE157-AF157)/AD157,"") -> 0.39899833
A158: 46267 | B158: SP | Manual | Skincare Essentials | Broad | C158: Face Care | D158: Enabled | E158: AG | Salicylic Acid Face Wash | F158: Sponsored Products | G158: salicylic acid face wash | H158: BROAD | I158: salicylic acid face wash | J158: SKN-009 | K158: Rest of Search | L158: 2045 | M158: 16 | N158: =IF(L158=0,"",M158/L158) -> 0.0078239609 | O158: =IF(M158=0,"",P158/M158) -> 3.88 | P158: 62.08 | Q158: 279 | R158: 1 | S158: 1 | T158: =IF(Q158=0,"",P158/Q158) -> 0.22250896 | U158: =IF(P158=0,"",Q158/P158) -> 4.494201 | V158: =IF(M158=0,"",R158/M158) -> 0.0625 | W158: 5.5 | X158: INR | Y158: India | AA158: =IF(OR(A158<DATE(2026,9,1),A158>DATE(2026,9,28)),"Check Date",INT((A158-DATE(2026,9,1))/7)+1) -> 1 | AB158: =IF(OR(AD158="",AE158="",AF158=""),"",S158*(AD158-AE158-AF158)-P158) -> 5.92 | AC158: =IF(P158<0,"Review",IF(OR(AD158="",AE158="",AF158=""),"Cost missing",IF(P158=0,"No Spend",IF(Q158=0,"No Sales",IF(P158/Q158<AG158,"Profitable","Losing"))))) -> Profitable | AD158: =IFERROR(VLOOKUP(J158,Product_lookup!$A:$G,5,FALSE),"") -> 279 | AE158: =IFERROR(VLOOKUP(J158,Product_lookup!$A:$G,6,FALSE),"") -> 106 | AF158: =IFERROR(VLOOKUP(J158,Product_lookup!$A:$G,7,FALSE),"") -> 105 | AG158: =IFERROR((AD158-AE158-AF158)/AD158,"") -> 0.2437276
A159: 46267 | B159: SP | Manual | Skincare Essentials | Broad | C159: Face Care | D159: Enabled | E159: AG | Rose Water Toner | F159: Sponsored Products | G159: rose water toner | H159: BROAD | I159: rose water toner for open pores | J159: SKN-010 | K159: Rest of Search | L159: 224 | M159: 2 | N159: =IF(L159=0,"",M159/L159) -> 0.0089285714 | O159: =IF(M159=0,"",P159/M159) -> 3.17 | P159: 6.34 | Q159: 0 | R159: 0 | S159: 0 | T159: =IF(Q159=0,"",P159/Q159) | U159: =IF(P159=0,"",Q159/P159) -> 0 | V159: =IF(M159=0,"",R159/M159) -> 0 | W159: 5.5 | X159: INR | Y159: India | Z159: seller wants to monitor | AA159: =IF(OR(A159<DATE(2026,9,1),A159>DATE(2026,9,28)),"Check Date",INT((A159-DATE(2026,9,1))/7)+1) -> 1 | AB159: =IF(OR(AD159="",AE159="",AF159=""),"",S159*(AD159-AE159-AF159)-P159) -> -6.34 | AC159: =IF(P159<0,"Review",IF(OR(AD159="",AE159="",AF159=""),"Cost missing",IF(P159=0,"No Spend",IF(Q159=0,"No Sales",IF(P159/Q159<AG159,"Profitable","Losing"))))) -> No Sales | AD159: =IFERROR(VLOOKUP(J159,Product_lookup!$A:$G,5,FALSE),"") -> 249 | AE159: =IFERROR(VLOOKUP(J159,Product_lookup!$A:$G,6,FALSE),"") -> 100 | AF159: =IFERROR(VLOOKUP(J159,Product_lookup!$A:$G,7,FALSE),"") -> 102 | AG159: =IFERROR((AD159-AE159-AF159)/AD159,"") -> 0.18875502
A160: 46267 | B160: SP | Manual | Skincare Essentials | Broad | C160: Face Care | D160: Enabled | E160: AG | Rose Water Toner | F160: Sponsored Products | G160: rose water toner | H160: BROAD | I160: face toner pack of 2 | J160: SKN-010 | K160: Rest of Search | L160: 636 | M160: 8 | N160: =IF(L160=0,"",M160/L160) -> 0.012578616 | O160: =IF(M160=0,"",P160/M160) -> 4.39 | P160: 35.12 | Q160: 0 | R160: 0 | S160: 0 | T160: =IF(Q160=0,"",P160/Q160) | U160: =IF(P160=0,"",Q160/P160) -> 0 | V160: =IF(M160=0,"",R160/M160) -> 0 | W160: 7 | X160: INR | Y160: India | AA160: =IF(OR(A160<DATE(2026,9,1),A160>DATE(2026,9,28)),"Check Date",INT((A160-DATE(2026,9,1))/7)+1) -> 1 | AB160: =IF(OR(AD160="",AE160="",AF160=""),"",S160*(AD160-AE160-AF160)-P160) -> -35.12 | AC160: =IF(P160<0,"Review",IF(OR(AD160="",AE160="",AF160=""),"Cost missing",IF(P160=0,"No Spend",IF(Q160=0,"No Sales",IF(P160/Q160<AG160,"Profitable","Losing"))))) -> No Sales | AD160: =IFERROR(VLOOKUP(J160,Product_lookup!$A:$G,5,FALSE),"") -> 249 | AE160: =IFERROR(VLOOKUP(J160,Product_lookup!$A:$G,6,FALSE),"") -> 100 | AF160: =IFERROR(VLOOKUP(J160,Product_lookup!$A:$G,7,FALSE),"") -> 102 | AG160: =IFERROR((AD160-AE160-AF160)/AD160,"") -> 0.18875502
A161: 46267 | B161: SP | Manual | Skincare Essentials | Broad | C161: Face Care | D161: Enabled | E161: AG | Rose Water Toner | F161: Sponsored Products | G161: face toner | H161: BROAD | I161: rose water spray | J161: SKN-010 | K161: Top of Search | L161: 508 | M161: 3 | N161: =IF(L161=0,"",M161/L161) -> 0.0059055118 | O161: =IF(M161=0,"",P161/M161) -> 4.75 | P161: 14.25 | Q161: 0 | R161: 0 | S161: 0 | T161: =IF(Q161=0,"",P161/Q161) | U161: =IF(P161=0,"",Q161/P161) -> 0 | V161: =IF(M161=0,"",R161/M161) -> 0 | W161: 6 | X161: INR | Y161: India | AA161: =IF(OR(A161<DATE(2026,9,1),A161>DATE(2026,9,28)),"Check Date",INT((A161-DATE(2026,9,1))/7)+1) -> 1 | AB161: =IF(OR(AD161="",AE161="",AF161=""),"",S161*(AD161-AE161-AF161)-P161) -> -14.25 | AC161: =IF(P161<0,"Review",IF(OR(AD161="",AE161="",AF161=""),"Cost missing",IF(P161=0,"No Spend",IF(Q161=0,"No Sales",IF(P161/Q161<AG161,"Profitable","Losing"))))) -> No Sales | AD161: =IFERROR(VLOOKUP(J161,Product_lookup!$A:$G,5,FALSE),"") -> 249 | AE161: =IFERROR(VLOOKUP(J161,Product_lookup!$A:$G,6,FALSE),"") -> 100 | AF161: =IFERROR(VLOOKUP(J161,Product_lookup!$A:$G,7,FALSE),"") -> 102 | AG161: =IFERROR((AD161-AE161-AF161)/AD161,"") -> 0.18875502
A162: 46267 | B162: SP | Manual | Skincare Essentials | Broad | C162: Face Care | D162: Enabled | E162: AG | Rose Water Toner | F162: Sponsored Products | G162: face toner | H162: BROAD | I162: rose water toner for sensitive skin | J162: SKN-010 | K162: Rest of Search | L162: 76 | M162: 0 | N162: =IF(L162=0,"",M162/L162) -> 0 | O162: =IF(M162=0,"",P162/M162) | P162: 0 | Q162: 0 | R162: 0 | S162: 0 | T162: =IF(Q162=0,"",P162/Q162) | U162: =IF(P162=0,"",Q162/P162) | V162: =IF(M162=0,"",R162/M162) | W162: 5.5 | X162: INR | Y162: India | AA162: =IF(OR(A162<DATE(2026,9,1),A162>DATE(2026,9,28)),"Check Date",INT((A162-DATE(2026,9,1))/7)+1) -> 1 | AB162: =IF(OR(AD162="",AE162="",AF162=""),"",S162*(AD162-AE162-AF162)-P162) -> 0 | AC162: =IF(P162<0,"Review",IF(OR(AD162="",AE162="",AF162=""),"Cost missing",IF(P162=0,"No Spend",IF(Q162=0,"No Sales",IF(P162/Q162<AG162,"Profitable","Losing"))))) -> No Spend | AD162: =IFERROR(VLOOKUP(J162,Product_lookup!$A:$G,5,FALSE),"") -> 249 | AE162: =IFERROR(VLOOKUP(J162,Product_lookup!$A:$G,6,FALSE),"") -> 100 | AF162: =IFERROR(VLOOKUP(J162,Product_lookup!$A:$G,7,FALSE),"") -> 102 | AG162: =IFERROR((AD162-AE162-AF162)/AD162,"") -> 0.18875502
A163: 46267 | B163: SP | Manual | Skincare Essentials | Broad | C163: Face Care | D163: Enabled | E163: AG | Rose Water Toner | F163: Sponsored Products | G163: rose water toner | H163: BROAD | I163: face toner price | J163: SKN-010 | K163: Product Pages | L163: 431 | M163: 2 | N163: =IF(L163=0,"",M163/L163) -> 0.0046403712 | O163: =IF(M163=0,"",P163/M163) -> 3.9 | P163: 7.8 | Q163: 0 | R163: 0 | S163: 0 | T163: =IF(Q163=0,"",P163/Q163) | U163: =IF(P163=0,"",Q163/P163) -> 0 | V163: =IF(M163=0,"",R163/M163) -> 0 | W163: 7 | X163: INR | Y163: India | AA163: =IF(OR(A163<DATE(2026,9,1),A163>DATE(2026,9,28)),"Check Date",INT((A163-DATE(2026,9,1))/7)+1) -> 1 | AB163: =IF(OR(AD163="",AE163="",AF163=""),"",S163*(AD163-AE163-AF163)-P163) -> -7.8 | AC163: =IF(P163<0,"Review",IF(OR(AD163="",AE163="",AF163=""),"Cost missing",IF(P163=0,"No Spend",IF(Q163=0,"No Sales",IF(P163/Q163<AG163,"Profitable","Losing"))))) -> No Sales | AD163: =IFERROR(VLOOKUP(J163,Product_lookup!$A:$G,5,FALSE),"") -> 249 | AE163: =IFERROR(VLOOKUP(J163,Product_lookup!$A:$G,6,FALSE),"") -> 100 | AF163: =IFERROR(VLOOKUP(J163,Product_lookup!$A:$G,7,FALSE),"") -> 102 | AG163: =IFERROR((AD163-AE163-AF163)/AD163,"") -> 0.18875502
A164: 46267 | B164: SP | Manual | Skincare Essentials | Broad | C164: Face Care | D164: Enabled | E164: AG | Sheet Mask | F164: Sponsored Products | G164: sheet mask | H164: BROAD | I164: free sample face cream | J164: SKN-014 | K164: Top of Search | L164: 372 | M164: 4 | N164: =IF(L164=0,"",M164/L164) -> 0.010752688 | O164: =IF(M164=0,"",P164/M164) -> 9.52 | P164: 38.08 | Q164: 0 | R164: 0 | S164: 0 | T164: =IF(Q164=0,"",P164/Q164) | U164: =IF(P164=0,"",Q164/P164) -> 0 | V164: =IF(M164=0,"",R164/M164) -> 0 | W164: 10 | X164: INR | Y164: India | AA164: =IF(OR(A164<DATE(2026,9,1),A164>DATE(2026,9,28)),"Check Date",INT((A164-DATE(2026,9,1))/7)+1) -> 1 | AB164: =IF(OR(AD164="",AE164="",AF164=""),"",S164*(AD164-AE164-AF164)-P164) -> -38.08 | AC164: =IF(P164<0,"Review",IF(OR(AD164="",AE164="",AF164=""),"Cost missing",IF(P164=0,"No Spend",IF(Q164=0,"No Sales",IF(P164/Q164<AG164,"Profitable","Losing"))))) -> No Sales | AD164: =IFERROR(VLOOKUP(J164,Product_lookup!$A:$G,5,FALSE),"") -> 349 | AE164: =IFERROR(VLOOKUP(J164,Product_lookup!$A:$G,6,FALSE),"") -> 133 | AF164: =IFERROR(VLOOKUP(J164,Product_lookup!$A:$G,7,FALSE),"") -> 111 | AG164: =IFERROR((AD164-AE164-AF164)/AD164,"") -> 0.3008596
A165: 46267 | B165: SP | Manual | Skincare Essentials | Broad | C165: Face Care | D165: Enabled | E165: AG | Sheet Mask | F165: Sponsored Products | G165: face sheet mask | H165: BROAD | I165: korean sheet mask | J165: SKN-014 | K165: Product Pages | L165: 328 | M165: 1 | N165: =IF(L165=0,"",M165/L165) -> 0.0030487805 | O165: =IF(M165=0,"",P165/M165) -> 4.29 | P165: 4.29 | Q165: 0 | R165: 0 | S165: 0 | T165: =IF(Q165=0,"",P165/Q165) | U165: =IF(P165=0,"",Q165/P165) -> 0 | V165: =IF(M165=0,"",R165/M165) -> 0 | W165: 7 | X165: INR | Y165: India | AA165: =IF(OR(A165<DATE(2026,9,1),A165>DATE(2026,9,28)),"Check Date",INT((A165-DATE(2026,9,1))/7)+1) -> 1 | AB165: =IF(OR(AD165="",AE165="",AF165=""),"",S165*(AD165-AE165-AF165)-P165) -> -4.29 | AC165: =IF(P165<0,"Review",IF(OR(AD165="",AE165="",AF165=""),"Cost missing",IF(P165=0,"No Spend",IF(Q165=0,"No Sales",IF(P165/Q165<AG165,"Profitable","Losing"))))) -> No Sales | AD165: =IFERROR(VLOOKUP(J165,Product_lookup!$A:$G,5,FALSE),"") -> 349 | AE165: =IFERROR(VLOOKUP(J165,Product_lookup!$A:$G,6,FALSE),"") -> 133 | AF165: =IFERROR(VLOOKUP(J165,Product_lookup!$A:$G,7,FALSE),"") -> 111 | AG165: =IFERROR((AD165-AE165-AF165)/AD165,"") -> 0.3008596
A166: 46286 | B166: SP | Auto | Face Care | C166: Face Care | D166: Enabled | E166: AG | Niacinamide Serum | F166: Sponsored Products | G166: close-match | H166: AUTO | I166: 10% niacinamide face serum | J166: SKN-002 | K166: Rest of Search | L166: 2254 | M166: 16 | N166: =IF(L166=0,"",M166/L166) -> 0.0070984916 | O166: =IF(M166=0,"",P166/M166) -> 10.54 | P166: 168.64 | Q166: 549 | R166: 1 | S166: 1 | T166: =IF(Q166=0,"",P166/Q166) -> 0.30717668 | U166: =IF(P166=0,"",Q166/P166) -> 3.2554554 | V166: =IF(M166=0,"",R166/M166) -> 0.0625 | W166: 12.5 | X166: INR | Y166: India | AA166: =IF(OR(A166<DATE(2026,9,1),A166>DATE(2026,9,28)),"Check Date",INT((A166-DATE(2026,9,1))/7)+1) -> 3 | AB166: =IF(OR(AD166="",AE166="",AF166=""),"",S166*(AD166-AE166-AF166)-P166) -> 49.36 | AC166: =IF(P166<0,"Review",IF(OR(AD166="",AE166="",AF166=""),"Cost missing",IF(P166=0,"No Spend",IF(Q166=0,"No Sales",IF(P166/Q166<AG166,"Profitable","Losing"))))) -> Profitable | AD166: =IFERROR(VLOOKUP(J166,Product_lookup!$A:$G,5,FALSE),"") -> 549 | AE166: =IFERROR(VLOOKUP(J166,Product_lookup!$A:$G,6,FALSE),"") -> 192 | AF166: =IFERROR(VLOOKUP(J166,Product_lookup!$A:$G,7,FALSE),"") -> 139 | AG166: =IFERROR((AD166-AE166-AF166)/AD166,"") -> 0.39708561
A167: 46267 | B167: SP | Manual | Skincare Essentials | Broad | C167: Face Care | D167: Enabled | E167: AG | Sheet Mask | F167: Sponsored Products | G167: face sheet mask | H167: BROAD | I167: korean sheet mask combo | J167: SKN-014 | K167: Product Pages | L167: 336 | M167: 3 | N167: =IF(L167=0,"",M167/L167) -> 0.0089285714 | O167: =IF(M167=0,"",P167/M167) -> 5.5 | P167: 16.5 | Q167: 0 | R167: 0 | S167: 0 | T167: =IF(Q167=0,"",P167/Q167) | U167: =IF(P167=0,"",Q167/P167) -> 0 | V167: =IF(M167=0,"",R167/M167) -> 0 | W167: 8.5 | X167: INR | Y167: India | AA167: =IF(OR(A167<DATE(2026,9,1),A167>DATE(2026,9,28)),"Check Date",INT((A167-DATE(2026,9,1))/7)+1) -> 1 | AB167: =IF(OR(AD167="",AE167="",AF167=""),"",S167*(AD167-AE167-AF167)-P167) -> -16.5 | AC167: =IF(P167<0,"Review",IF(OR(AD167="",AE167="",AF167=""),"Cost missing",IF(P167=0,"No Spend",IF(Q167=0,"No Sales",IF(P167/Q167<AG167,"Profitable","Losing"))))) -> No Sales | AD167: =IFERROR(VLOOKUP(J167,Product_lookup!$A:$G,5,FALSE),"") -> 349 | AE167: =IFERROR(VLOOKUP(J167,Product_lookup!$A:$G,6,FALSE),"") -> 133 | AF167: =IFERROR(VLOOKUP(J167,Product_lookup!$A:$G,7,FALSE),"") -> 111 | AG167: =IFERROR((AD167-AE167-AF167)/AD167,"") -> 0.3008596
A168: 46267 | B168: SP | Manual | Skincare Essentials | Broad | C168: Face Care | D168: Enabled | E168: AG | Sheet Mask | F168: Sponsored Products | G168: face sheet mask | H168: BROAD | I168: korean sheet mask under 500 | J168: SKN-014 | K168: Product Pages | L168: 228 | M168: 2 | N168: =IF(L168=0,"",M168/L168) -> 0.0087719298 | O168: =IF(M168=0,"",P168/M168) -> 5.33 | P168: 10.66 | Q168: 0 | R168: 0 | S168: 0 | T168: =IF(Q168=0,"",P168/Q168) | U168: =IF(P168=0,"",Q168/P168) -> 0 | V168: =IF(M168=0,"",R168/M168) -> 0 | W168: 7.5 | X168: INR | Y168: India | AA168: =IF(OR(A168<DATE(2026,9,1),A168>DATE(2026,9,28)),"Check Date",INT((A168-DATE(2026,9,1))/7)+1) -> 1 | AB168: =IF(OR(AD168="",AE168="",AF168=""),"",S168*(AD168-AE168-AF168)-P168) -> -10.66 | AC168: =IF(P168<0,"Review",IF(OR(AD168="",AE168="",AF168=""),"Cost missing",IF(P168=0,"No Spend",IF(Q168=0,"No Sales",IF(P168/Q168<AG168,"Profitable","Losing"))))) -> No Sales | AD168: =IFERROR(VLOOKUP(J168,Product_lookup!$A:$G,5,FALSE),"") -> 349 | AE168: =IFERROR(VLOOKUP(J168,Product_lookup!$A:$G,6,FALSE),"") -> 133 | AF168: =IFERROR(VLOOKUP(J168,Product_lookup!$A:$G,7,FALSE),"") -> 111 | AG168: =IFERROR((AD168-AE168-AF168)/AD168,"") -> 0.3008596
A169: 46267 | B169: SP | Manual | Skincare Essentials | Broad | C169: Face Care | D169: Enabled | E169: AG | Sheet Mask | F169: Sponsored Products | G169: face sheet mask | H169: BROAD | I169: sheet mask for acne | J169: SKN-014 | K169: Top of Search | L169: 316 | M169: 4 | N169: =IF(L169=0,"",M169/L169) -> 0.012658228 | O169: =IF(M169=0,"",P169/M169) -> 5.92 | P169: 23.68 | Q169: 0 | R169: 0 | S169: 0 | T169: =IF(Q169=0,"",P169/Q169) | U169: =IF(P169=0,"",Q169/P169) -> 0 | V169: =IF(M169=0,"",R169/M169) -> 0 | W169: 7.5 | X169: INR | Y169: India | AA169: =IF(OR(A169<DATE(2026,9,1),A169>DATE(2026,9,28)),"Check Date",INT((A169-DATE(2026,9,1))/7)+1) -> 1 | AB169: =IF(OR(AD169="",AE169="",AF169=""),"",S169*(AD169-AE169-AF169)-P169) -> -23.68 | AC169: =IF(P169<0,"Review",IF(OR(AD169="",AE169="",AF169=""),"Cost missing",IF(P169=0,"No Spend",IF(Q169=0,"No Sales",IF(P169/Q169<AG169,"Profitable","Losing"))))) -> No Sales | AD169: =IFERROR(VLOOKUP(J169,Product_lookup!$A:$G,5,FALSE),"") -> 349 | AE169: =IFERROR(VLOOKUP(J169,Product_lookup!$A:$G,6,FALSE),"") -> 133 | AF169: =IFERROR(VLOOKUP(J169,Product_lookup!$A:$G,7,FALSE),"") -> 111 | AG169: =IFERROR((AD169-AE169-AF169)/AD169,"") -> 0.3008596
A170: 46267 | B170: SP | Manual | Hair Care | Phrase | C170: Body & Hair | D170: Enabled | E170: AG | Onion Hair Oil | F170: Sponsored Products | G170: hair oil | H170: PHRASE | I170: onion hair oil | J170: SKN-021 | K170: Rest of Search | L170: 645 | M170: 1 | N170: =IF(L170=0,"",M170/L170) -> 0.0015503876 | O170: =IF(M170=0,"",P170/M170) -> 7.32 | P170: 7.32 | Q170: 0 | R170: 0 | S170: 0 | T170: =IF(Q170=0,"",P170/Q170) | U170: =IF(P170=0,"",Q170/P170) -> 0 | V170: =IF(M170=0,"",R170/M170) -> 0 | W170: 13.5 | X170: INR | Y170: India | AA170: =IF(OR(A170<DATE(2026,9,1),A170>DATE(2026,9,28)),"Check Date",INT((A170-DATE(2026,9,1))/7)+1) -> 1 | AB170: =IF(OR(AD170="",AE170="",AF170=""),"",S170*(AD170-AE170-AF170)-P170) -> -7.32 | AC170: =IF(P170<0,"Review",IF(OR(AD170="",AE170="",AF170=""),"Cost missing",IF(P170=0,"No Spend",IF(Q170=0,"No Sales",IF(P170/Q170<AG170,"Profitable","Losing"))))) -> No Sales | AD170: =IFERROR(VLOOKUP(J170,Product_lookup!$A:$G,5,FALSE),"") -> 399 | AE170: =IFERROR(VLOOKUP(J170,Product_lookup!$A:$G,6,FALSE),"") -> 148 | AF170: =IFERROR(VLOOKUP(J170,Product_lookup!$A:$G,7,FALSE),"") -> 126 | AG170: =IFERROR((AD170-AE170-AF170)/AD170,"") -> 0.31328321
A171: 46267 | B171: SP | Manual | Hair Care | Phrase | C171: Body & Hair | D171: Enabled | E171: AG | Onion Hair Oil | F171: Sponsored Products | G171: onion hair oil | H171: PHRASE | I171: hair oil for kids | J171: SKN-021 | K171: Product Pages | L171: 166 | M171: 1 | N171: =IF(L171=0,"",M171/L171) -> 0.0060240964 | O171: =IF(M171=0,"",P171/M171) -> 5.51 | P171: 5.51 | Q171: 0 | R171: 0 | S171: 0 | T171: =IF(Q171=0,"",P171/Q171) | U171: =IF(P171=0,"",Q171/P171) -> 0 | V171: =IF(M171=0,"",R171/M171) -> 0 | W171: 8.5 | X171: INR | Y171: India | Z171: festive offer live | AA171: =IF(OR(A171<DATE(2026,9,1),A171>DATE(2026,9,28)),"Check Date",INT((A171-DATE(2026,9,1))/7)+1) -> 1 | AB171: =IF(OR(AD171="",AE171="",AF171=""),"",S171*(AD171-AE171-AF171)-P171) -> -5.51 | AC171: =IF(P171<0,"Review",IF(OR(AD171="",AE171="",AF171=""),"Cost missing",IF(P171=0,"No Spend",IF(Q171=0,"No Sales",IF(P171/Q171<AG171,"Profitable","Losing"))))) -> No Sales | AD171: =IFERROR(VLOOKUP(J171,Product_lookup!$A:$G,5,FALSE),"") -> 399 | AE171: =IFERROR(VLOOKUP(J171,Product_lookup!$A:$G,6,FALSE),"") -> 148 | AF171: =IFERROR(VLOOKUP(J171,Product_lookup!$A:$G,7,FALSE),"") -> 126 | AG171: =IFERROR((AD171-AE171-AF171)/AD171,"") -> 0.31328321
A172: 46267 | B172: SP | Manual | Hair Care | Phrase | C172: Body & Hair | D172: Enabled | E172: AG | Hair Serum | F172: Sponsored Products | G172: hair serum | H172: PHRASE | I172: hair serum for frizzy hair for hair fall | J172: SKN-023 | K172: Rest of Search | L172: 403 | M172: 1 | N172: =IF(L172=0,"",M172/L172) -> 0.0024813896 | O172: =IF(M172=0,"",P172/M172) -> 9.67 | P172: 9.67 | Q172: 0 | R172: 0 | S172: 0 | T172: =IF(Q172=0,"",P172/Q172) | U172: =IF(P172=0,"",Q172/P172) -> 0 | V172: =IF(M172=0,"",R172/M172) -> 0 | W172: 13.5 | X172: INR | Y172: India | AA172: =IF(OR(A172<DATE(2026,9,1),A172>DATE(2026,9,28)),"Check Date",INT((A172-DATE(2026,9,1))/7)+1) -> 1 | AB172: =IF(OR(AD172="",AE172="",AF172=""),"",S172*(AD172-AE172-AF172)-P172) -> -9.67 | AC172: =IF(P172<0,"Review",IF(OR(AD172="",AE172="",AF172=""),"Cost missing",IF(P172=0,"No Spend",IF(Q172=0,"No Sales",IF(P172/Q172<AG172,"Profitable","Losing"))))) -> No Sales | AD172: =IFERROR(VLOOKUP(J172,Product_lookup!$A:$G,5,FALSE),"") -> 549 | AE172: =IFERROR(VLOOKUP(J172,Product_lookup!$A:$G,6,FALSE),"") -> 198 | AF172: =IFERROR(VLOOKUP(J172,Product_lookup!$A:$G,7,FALSE),"") -> 139 | AG172: =IFERROR((AD172-AE172-AF172)/AD172,"") -> 0.38615665
A173: 46267 | B173: SP | Manual | Hair Care | Phrase | C173: Body & Hair | D173: Enabled | E173: AG | Hair Serum | F173: Sponsored Products | G173: hair serum for frizzy hair | H173: PHRASE | I173: smoothening hair serum for thinning hair | J173: SKN-023 | K173: Top of Search | L173: 97 | M173: 0 | N173: =IF(L173=0,"",M173/L173) -> 0 | O173: =IF(M173=0,"",P173/M173) | P173: 0 | Q173: 0 | R173: 0 | S173: 0 | T173: =IF(Q173=0,"",P173/Q173) | U173: =IF(P173=0,"",Q173/P173) | V173: =IF(M173=0,"",R173/M173) | W173: 12.5 | X173: INR | Y173: India | AA173: =IF(OR(A173<DATE(2026,9,1),A173>DATE(2026,9,28)),"Check Date",INT((A173-DATE(2026,9,1))/7)+1) -> 1 | AB173: =IF(OR(AD173="",AE173="",AF173=""),"",S173*(AD173-AE173-AF173)-P173) -> 0 | AC173: =IF(P173<0,"Review",IF(OR(AD173="",AE173="",AF173=""),"Cost missing",IF(P173=0,"No Spend",IF(Q173=0,"No Sales",IF(P173/Q173<AG173,"Profitable","Losing"))))) -> No Spend | AD173: =IFERROR(VLOOKUP(J173,Product_lookup!$A:$G,5,FALSE),"") -> 549 | AE173: =IFERROR(VLOOKUP(J173,Product_lookup!$A:$G,6,FALSE),"") -> 198 | AF173: =IFERROR(VLOOKUP(J173,Product_lookup!$A:$G,7,FALSE),"") -> 139 | AG173: =IFERROR((AD173-AE173-AF173)/AD173,"") -> 0.38615665
A174: 46267 | B174: SP | Manual | Hair Care | Phrase | C174: Body & Hair | D174: Enabled | E174: AG | Hair Serum | F174: Sponsored Products | G174: hair serum for frizzy hair | H174: PHRASE | I174: hair serum | J174: SKN-023 | K174: Top of Search | L174: 637 | M174: 10 | N174: =IF(L174=0,"",M174/L174) -> 0.015698587 | O174: =IF(M174=0,"",P174/M174) -> 12.5 | P174: 125 | Q174: 0 | R174: 0 | S174: 0 | T174: =IF(Q174=0,"",P174/Q174) | U174: =IF(P174=0,"",Q174/P174) -> 0 | V174: =IF(M174=0,"",R174/M174) -> 0 | W174: 12.5 | X174: INR | Y174: India | AA174: =IF(OR(A174<DATE(2026,9,1),A174>DATE(2026,9,28)),"Check Date",INT((A174-DATE(2026,9,1))/7)+1) -> 1 | AB174: =IF(OR(AD174="",AE174="",AF174=""),"",S174*(AD174-AE174-AF174)-P174) -> -125 | AC174: =IF(P174<0,"Review",IF(OR(AD174="",AE174="",AF174=""),"Cost missing",IF(P174=0,"No Spend",IF(Q174=0,"No Sales",IF(P174/Q174<AG174,"Profitable","Losing"))))) -> No Sales | AD174: =IFERROR(VLOOKUP(J174,Product_lookup!$A:$G,5,FALSE),"") -> 549 | AE174: =IFERROR(VLOOKUP(J174,Product_lookup!$A:$G,6,FALSE),"") -> 198 | AF174: =IFERROR(VLOOKUP(J174,Product_lookup!$A:$G,7,FALSE),"") -> 139 | AG174: =IFERROR((AD174-AE174-AF174)/AD174,"") -> 0.38615665
A175: 46267 | B175: SP | Manual | Body Care | Exact | C175: Body & Hair | D175: Enabled | E175: AG | Body Lotion | F175: Sponsored Products | G175: shea body lotion paraben free | H175: EXACT | I175: shea body lotion paraben free | J175: SKN-017 | K175: Product Pages | L175: 308 | M175: 3 | N175: =IF(L175=0,"",M175/L175) -> 0.0097402597 | O175: =IF(M175=0,"",P175/M175) -> 10.57 | P175: 31.71 | Q175: 449 | R175: 1 | S175: 1 | T175: =IF(Q175=0,"",P175/Q175) -> 0.070623608 | U175: =IF(P175=0,"",Q175/P175) -> 14.159571 | V175: =IF(M175=0,"",R175/M175) -> 0.33333333 | W175: 18 | X175: INR | Y175: India | AA175: =IF(OR(A175<DATE(2026,9,1),A175>DATE(2026,9,28)),"Check Date",INT((A175-DATE(2026,9,1))/7)+1) -> 1 | AB175: =IF(OR(AD175="",AE175="",AF175=""),"",S175*(AD175-AE175-AF175)-P175) -> 111.29 | AC175: =IF(P175<0,"Review",IF(OR(AD175="",AE175="",AF175=""),"Cost missing",IF(P175=0,"No Spend",IF(Q175=0,"No Sales",IF(P175/Q175<AG175,"Profitable","Losing"))))) -> Profitable | AD175: =IFERROR(VLOOKUP(J175,Product_lookup!$A:$G,5,FALSE),"") -> 449 | AE175: =IFERROR(VLOOKUP(J175,Product_lookup!$A:$G,6,FALSE),"") -> 166 | AF175: =IFERROR(VLOOKUP(J175,Product_lookup!$A:$G,7,FALSE),"") -> 140 | AG175: =IFERROR((AD175-AE175-AF175)/AD175,"") -> 0.31848552
A176: 46267 | B176: SP | Manual | Body Care | Exact | C176: Body & Hair | D176: Enabled | E176: AG | Body Lotion | F176: Sponsored Products | G176: body lotion | H176: EXACT | I176: body lotion | J176: SKN-017 | K176: Rest of Search | L176: 2634 | M176: 33 | N176: =IF(L176=0,"",M176/L176) -> 0.012528474 | O176: =IF(M176=0,"",P176/M176) -> 11.07 | P176: 365.31 | Q176: 1347 | R176: 3 | S176: 3 | T176: =IF(Q176=0,"",P176/Q176) -> 0.27120267 | U176: =IF(P176=0,"",Q176/P176) -> 3.6872793 | V176: =IF(M176=0,"",R176/M176) -> 0.090909091 | W176: 15.5 | X176: INR | Y176: India | AA176: =IF(OR(A176<DATE(2026,9,1),A176>DATE(2026,9,28)),"Check Date",INT((A176-DATE(2026,9,1))/7)+1) -> 1 | AB176: =IF(OR(AD176="",AE176="",AF176=""),"",S176*(AD176-AE176-AF176)-P176) -> 63.69 | AC176: =IF(P176<0,"Review",IF(OR(AD176="",AE176="",AF176=""),"Cost missing",IF(P176=0,"No Spend",IF(Q176=0,"No Sales",IF(P176/Q176<AG176,"Profitable","Losing"))))) -> Profitable | AD176: =IFERROR(VLOOKUP(J176,Product_lookup!$A:$G,5,FALSE),"") -> 449 | AE176: =IFERROR(VLOOKUP(J176,Product_lookup!$A:$G,6,FALSE),"") -> 166 | AF176: =IFERROR(VLOOKUP(J176,Product_lookup!$A:$G,7,FALSE),"") -> 140 | AG176: =IFERROR((AD176-AE176-AF176)/AD176,"") -> 0.31848552
A177: 46267 | B177: SP | Manual | Body Care | Exact | C177: Body & Hair | D177: Enabled | E177: AG | Body Lotion | F177: Sponsored Products | G177: body lotion for daily use | H177: EXACT | I177: body lotion for daily use | J177: SKN-017 | K177: Top of Search | L177: 304 | M177: 1 | N177: =IF(L177=0,"",M177/L177) -> 0.0032894737 | O177: =IF(M177=0,"",P177/M177) -> 16.5 | P177: 16.5 | Q177: 0 | R177: 0 | S177: 0 | T177: =IF(Q177=0,"",P177/Q177) | U177: =IF(P177=0,"",Q177/P177) -> 0 | V177: =IF(M177=0,"",R177/M177) -> 0 | W177: 16.5 | X177: INR | Y177: India | AA177: =IF(OR(A177<DATE(2026,9,1),A177>DATE(2026,9,28)),"Check Date",INT((A177-DATE(2026,9,1))/7)+1) -> 1 | AB177: =IF(OR(AD177="",AE177="",AF177=""),"",S177*(AD177-AE177-AF177)-P177) -> -16.5 | AC177: =IF(P177<0,"Review",IF(OR(AD177="",AE177="",AF177=""),"Cost missing",IF(P177=0,"No Spend",IF(Q177=0,"No Sales",IF(P177/Q177<AG177,"Profitable","Losing"))))) -> No Sales | AD177: =IFERROR(VLOOKUP(J177,Product_lookup!$A:$G,5,FALSE),"") -> 449 | AE177: =IFERROR(VLOOKUP(J177,Product_lookup!$A:$G,6,FALSE),"") -> 166 | AF177: =IFERROR(VLOOKUP(J177,Product_lookup!$A:$G,7,FALSE),"") -> 140 | AG177: =IFERROR((AD177-AE177-AF177)/AD177,"") -> 0.31848552
A178: 46267 | B178: SP | Manual | Body Care | Exact | C178: Body & Hair | D178: Enabled | E178: AG | Body Lotion | F178: Sponsored Products | G178: shea body lotion | H178: EXACT | I178: shea body lotion | J178: SKN-017 | K178: Product Pages | L178: 918 | M178: 4 | N178: =IF(L178=0,"",M178/L178) -> 0.0043572985 | O178: =IF(M178=0,"",P178/M178) -> 9.13 | P178: 36.52 | Q178: 0 | R178: 0 | S178: 0 | T178: =IF(Q178=0,"",P178/Q178) | U178: =IF(P178=0,"",Q178/P178) -> 0 | V178: =IF(M178=0,"",R178/M178) -> 0 | W178: 14.5 | X178: INR | Y178: India | AA178: =IF(OR(A178<DATE(2026,9,1),A178>DATE(2026,9,28)),"Check Date",INT((A178-DATE(2026,9,1))/7)+1) -> 1 | AB178: =IF(OR(AD178="",AE178="",AF178=""),"",S178*(AD178-AE178-AF178)-P178) -> -36.52 | AC178: =IF(P178<0,"Review",IF(OR(AD178="",AE178="",AF178=""),"Cost missing",IF(P178=0,"No Spend",IF(Q178=0,"No Sales",IF(P178/Q178<AG178,"Profitable","Losing"))))) -> No Sales | AD178: =IFERROR(VLOOKUP(J178,Product_lookup!$A:$G,5,FALSE),"") -> 449 | AE178: =IFERROR(VLOOKUP(J178,Product_lookup!$A:$G,6,FALSE),"") -> 166 | AF178: =IFERROR(VLOOKUP(J178,Product_lookup!$A:$G,7,FALSE),"") -> 140 | AG178: =IFERROR((AD178-AE178-AF178)/AD178,"") -> 0.31848552
A179: 46267 | B179: SP | Manual | Body Care | Exact | C179: Body & Hair | D179: Enabled | E179: AG | Body Wash | F179: Sponsored Products | G179: body wash for women under 300 | H179: EXACT | I179: body wash for women under 300 | J179: SKN-018 | K179: Rest of Search | L179: 733 | M179: 6 | N179: =IF(L179=0,"",M179/L179) -> 0.0081855389 | O179: =IF(M179=0,"",P179/M179) -> 9.07 | P179: 54.42 | Q179: 0 | R179: 0 | S179: 0 | T179: =IF(Q179=0,"",P179/Q179) | U179: =IF(P179=0,"",Q179/P179) -> 0 | V179: =IF(M179=0,"",R179/M179) -> 0 | W179: 12 | X179: INR | Y179: India | AA179: =IF(OR(A179<DATE(2026,9,1),A179>DATE(2026,9,28)),"Check Date",INT((A179-DATE(2026,9,1))/7)+1) -> 1 | AB179: =IF(OR(AD179="",AE179="",AF179=""),"",S179*(AD179-AE179-AF179)-P179) -> -54.42 | AC179: =IF(P179<0,"Review",IF(OR(AD179="",AE179="",AF179=""),"Cost missing",IF(P179=0,"No Spend",IF(Q179=0,"No Sales",IF(P179/Q179<AG179,"Profitable","Losing"))))) -> No Sales | AD179: =IFERROR(VLOOKUP(J179,Product_lookup!$A:$G,5,FALSE),"") -> 349 | AE179: =IFERROR(VLOOKUP(J179,Product_lookup!$A:$G,6,FALSE),"") -> 133 | AF179: =IFERROR(VLOOKUP(J179,Product_lookup!$A:$G,7,FALSE),"") -> 121 | AG179: =IFERROR((AD179-AE179-AF179)/AD179,"") -> 0.2722063
A180: 46267 | B180: SP | Manual | Body Care | Exact | C180: Body & Hair | D180: Enabled | E180: AG | Body Wash | F180: Sponsored Products | G180: body wash for women paraben free | H180: EXACT | I180: body wash for women paraben free | J180: SKN-018 | K180: Rest of Search | L180: 543 | M180: 0 | N180: =IF(L180=0,"",M180/L180) -> 0 | O180: =IF(M180=0,"",P180/M180) | P180: 0 | Q180: 0 | R180: 0 | S180: 0 | T180: =IF(Q180=0,"",P180/Q180) | U180: =IF(P180=0,"",Q180/P180) | V180: =IF(M180=0,"",R180/M180) | W180: 12 | X180: INR | Y180: India | AA180: =IF(OR(A180<DATE(2026,9,1),A180>DATE(2026,9,28)),"Check Date",INT((A180-DATE(2026,9,1))/7)+1) -> 1 | AB180: =IF(OR(AD180="",AE180="",AF180=""),"",S180*(AD180-AE180-AF180)-P180) -> 0 | AC180: =IF(P180<0,"Review",IF(OR(AD180="",AE180="",AF180=""),"Cost missing",IF(P180=0,"No Spend",IF(Q180=0,"No Sales",IF(P180/Q180<AG180,"Profitable","Losing"))))) -> No Spend | AD180: =IFERROR(VLOOKUP(J180,Product_lookup!$A:$G,5,FALSE),"") -> 349 | AE180: =IFERROR(VLOOKUP(J180,Product_lookup!$A:$G,6,FALSE),"") -> 133 | AF180: =IFERROR(VLOOKUP(J180,Product_lookup!$A:$G,7,FALSE),"") -> 121 | AG180: =IFERROR((AD180-AE180-AF180)/AD180,"") -> 0.2722063
A181: 46267 | B181: SP | Manual | Body Care | Exact | C181: Body & Hair | D181: Enabled | E181: AG | Body Wash | F181: Sponsored Products | G181: shower gel | H181: EXACT | I181: shower gel | J181: SKN-018 | K181: Rest of Search | L181: 237 | M181: 3 | N181: =IF(L181=0,"",M181/L181) -> 0.012658228 | O181: =IF(M181=0,"",P181/M181) -> 9.91 | P181: 29.73 | Q181: 0 | R181: 0 | S181: 0 | T181: =IF(Q181=0,"",P181/Q181) | U181: =IF(P181=0,"",Q181/P181) -> 0 | V181: =IF(M181=0,"",R181/M181) -> 0 | W181: 13 | X181: INR | Y181: India | AA181: =IF(OR(A181<DATE(2026,9,1),A181>DATE(2026,9,28)),"Check Date",INT((A181-DATE(2026,9,1))/7)+1) -> 1 | AB181: =IF(OR(AD181="",AE181="",AF181=""),"",S181*(AD181-AE181-AF181)-P181) -> -29.73 | AC181: =IF(P181<0,"Review",IF(OR(AD181="",AE181="",AF181=""),"Cost missing",IF(P181=0,"No Spend",IF(Q181=0,"No Sales",IF(P181/Q181<AG181,"Profitable","Losing"))))) -> No Sales | AD181: =IFERROR(VLOOKUP(J181,Product_lookup!$A:$G,5,FALSE),"") -> 349 | AE181: =IFERROR(VLOOKUP(J181,Product_lookup!$A:$G,6,FALSE),"") -> 133 | AF181: =IFERROR(VLOOKUP(J181,Product_lookup!$A:$G,7,FALSE),"") -> 121 | AG181: =IFERROR((AD181-AE181-AF181)/AD181,"") -> 0.2722063
A182: 46267 | B182: SP | Manual | Body Care | Exact | C182: Body & Hair | D182: Enabled | E182: AG | Body Wash | F182: Sponsored Products | G182: body wash | H182: EXACT | I182: body wash | J182: SKN-018 | K182: Rest of Search | L182: 2654 | M182: 30 | N182: =IF(L182=0,"",M182/L182) -> 0.011303693 | O182: =IF(M182=0,"",P182/M182) -> 6.51 | P182: 195.3 | Q182: 349 | R182: 1 | S182: 1 | T182: =IF(Q182=0,"",P182/Q182) -> 0.55959885 | U182: =IF(P182=0,"",Q182/P182) -> 1.7869944 | V182: =IF(M182=0,"",R182/M182) -> 0.033333333 | W182: 8.5 | X182: INR | Y182: India | AA182: =IF(OR(A182<DATE(2026,9,1),A182>DATE(2026,9,28)),"Check Date",INT((A182-DATE(2026,9,1))/7)+1) -> 1 | AB182: =IF(OR(AD182="",AE182="",AF182=""),"",S182*(AD182-AE182-AF182)-P182) -> -100.3 | AC182: =IF(P182<0,"Review",IF(OR(AD182="",AE182="",AF182=""),"Cost missing",IF(P182=0,"No Spend",IF(Q182=0,"No Sales",IF(P182/Q182<AG182,"Profitable","Losing"))))) -> Losing | AD182: =IFERROR(VLOOKUP(J182,Product_lookup!$A:$G,5,FALSE),"") -> 349 | AE182: =IFERROR(VLOOKUP(J182,Product_lookup!$A:$G,6,FALSE),"") -> 133 | AF182: =IFERROR(VLOOKUP(J182,Product_lookup!$A:$G,7,FALSE),"") -> 121 | AG182: =IFERROR((AD182-AE182-AF182)/AD182,"") -> 0.2722063
A183: 46267 | B183: SP | Manual | Body Care | Exact | C183: Body & Hair | D183: Enabled | E183: AG | Body Wash | F183: Sponsored Products | G183: body wash for women | H183: EXACT | I183: body wash for women | J183: SKN-018 | K183: Product Pages | L183: 297 | M183: 4 | N183: =IF(L183=0,"",M183/L183) -> 0.013468013 | O183: =IF(M183=0,"",P183/M183) -> 6.8 | P183: 27.2 | Q183: 0 | R183: 0 | S183: 0 | T183: =IF(Q183=0,"",P183/Q183) | U183: =IF(P183=0,"",Q183/P183) -> 0 | V183: =IF(M183=0,"",R183/M183) -> 0 | W183: 8.5 | X183: INR | Y183: India | AA183: =IF(OR(A183<DATE(2026,9,1),A183>DATE(2026,9,28)),"Check Date",INT((A183-DATE(2026,9,1))/7)+1) -> 1 | AB183: =IF(OR(AD183="",AE183="",AF183=""),"",S183*(AD183-AE183-AF183)-P183) -> -27.2 | AC183: =IF(P183<0,"Review",IF(OR(AD183="",AE183="",AF183=""),"Cost missing",IF(P183=0,"No Spend",IF(Q183=0,"No Sales",IF(P183/Q183<AG183,"Profitable","Losing"))))) -> No Sales | AD183: =IFERROR(VLOOKUP(J183,Product_lookup!$A:$G,5,FALSE),"") -> 349 | AE183: =IFERROR(VLOOKUP(J183,Product_lookup!$A:$G,6,FALSE),"") -> 133 | AF183: =IFERROR(VLOOKUP(J183,Product_lookup!$A:$G,7,FALSE),"") -> 121 | AG183: =IFERROR((AD183-AE183-AF183)/AD183,"") -> 0.2722063
... A205: 46267 | B205: SP | Brand Defence | Exact | C205: Brand | D205: Enabled | E205: AG | Sunscreen Spf 50 | F205: Sponsored Products | G205: auralis sunscreen spf 50 | H205: EXACT | I205: auralis sunscreen spf 50 | J205: SKN-006 | K205: Top of Search | L205: 339 | M205: 11 | N205: =IF(L205=0,"",M205/L205) -> 0.032448378 | O205: =IF(M205=0,"",P205/M205) -> 5.5 | P205: 60.5 | Q205: 0 | R205: 0 | S205: 0 | T205: =IF(Q205=0,"",P205/Q205) | U205: =IF(P205=0,"",Q205/P205) -> 0 | V205: =IF(M205=0,"",R205/M205) -> 0 | W205: 5.5 | X205: INR | Y205: India | AA205: =IF(OR(A205<DATE(2026,9,1),A205>DATE(2026,9,28)),"Check Date",INT((A205-DATE(2026,9,1))/7)+1) -> 1 | AB205: =IF(OR(AD205="",AE205="",AF205=""),"",S205*(AD205-AE205-AF205)-P205) -> -60.5 | AC205: =IF(P205<0,"Review",IF(OR(AD205="",AE205="",AF205=""),"Cost missing",IF(P205=0,"No Spend",IF(Q205=0,"No Sales",IF(P205/Q205<AG205,"Profitable","Losing"))))) -> No Sales | AD205: =IFERROR(VLOOKUP(J205,Product_lookup!$A:$G,5,FALSE),"") -> 449 | AE205: =IFERROR(VLOOKUP(J205,Product_lookup!$A:$G,6,FALSE),"") -> 162 | AF205: =IFERROR(VLOOKUP(J205,Product_lookup!$A:$G,7,FALSE),"") -> 130 | AG205: =IFERROR((AD205-AE205-AF205)/AD205,"") -> 0.34966592
A206: 46267 | B206: SP | Brand Defence | Exact | C206: Brand | D206: Enabled | E206: AG | Sunscreen Spf 50 | F206: Sponsored Products | G206: auralis naturals sunscreen spf 50 | H206: EXACT | I206: auralis naturals sunscreen spf 50 | J206: SKN-006 | K206: Product Pages | L206: 147 | M206: 6 | N206: =IF(L206=0,"",M206/L206) -> 0.040816327 | O206: =IF(M206=0,"",P206/M206) -> 3.86 | P206: 23.16 | Q206: 0 | R206: 0 | S206: 0 | T206: =IF(Q206=0,"",P206/Q206) | U206: =IF(P206=0,"",Q206/P206) -> 0 | V206: =IF(M206=0,"",R206/M206) -> 0 | W206: 6 | X206: INR | Y206: India | Z206: bid reviewed | AA206: =IF(OR(A206<DATE(2026,9,1),A206>DATE(2026,9,28)),"Check Date",INT((A206-DATE(2026,9,1))/7)+1) -> 1 | AB206: =IF(OR(AD206="",AE206="",AF206=""),"",S206*(AD206-AE206-AF206)-P206) -> -23.16 | AC206: =IF(P206<0,"Review",IF(OR(AD206="",AE206="",AF206=""),"Cost missing",IF(P206=0,"No Spend",IF(Q206=0,"No Sales",IF(P206/Q206<AG206,"Profitable","Losing"))))) -> No Sales | AD206: =IFERROR(VLOOKUP(J206,Product_lookup!$A:$G,5,FALSE),"") -> 449 | AE206: =IFERROR(VLOOKUP(J206,Product_lookup!$A:$G,6,FALSE),"") -> 162 | AF206: =IFERROR(VLOOKUP(J206,Product_lookup!$A:$G,7,FALSE),"") -> 130 | AG206: =IFERROR((AD206-AE206-AF206)/AD206,"") -> 0.34966592
A207: 46267 | B207: SP | Brand Defence | Exact | C207: Brand | D207: Enabled | E207: AG | Kumkumadi Oil | F207: Sponsored Products | G207: auralis kumkumadi tailam | H207: EXACT | I207: auralis kumkumadi tailam | J207: SKN-024 | K207: Rest of Search | L207: 291 | M207: 4 | N207: =IF(L207=0,"",M207/L207) -> 0.013745704 | O207: =IF(M207=0,"",P207/M207) -> 8.96 | P207: 35.84 | Q207: 0 | R207: 0 | S207: 0 | T207: =IF(Q207=0,"",P207/Q207) | U207: =IF(P207=0,"",Q207/P207) -> 0 | V207: =IF(M207=0,"",R207/M207) -> 0 | W207: 15.5 | X207: INR | Y207: India | AA207: =IF(OR(A207<DATE(2026,9,1),A207>DATE(2026,9,28)),"Check Date",INT((A207-DATE(2026,9,1))/7)+1) -> 1 | AB207: =IF(OR(AD207="",AE207="",AF207=""),"",S207*(AD207-AE207-AF207)-P207) | AC207: =IF(P207<0,"Review",IF(OR(AD207="",AE207="",AF207=""),"Cost missing",IF(P207=0,"No Spend",IF(Q207=0,"No Sales",IF(P207/Q207<AG207,"Profitable","Losing"))))) -> Cost missing | AD207: =IFERROR(VLOOKUP(J207,Product_lookup!$A:$G,5,FALSE),"") | AE207: =IFERROR(VLOOKUP(J207,Product_lookup!$A:$G,6,FALSE),"") | AF207: =IFERROR(VLOOKUP(J207,Product_lookup!$A:$G,7,FALSE),"") | AG207: =IFERROR((AD207-AE207-AF207)/AD207,"")
A208: 46268 | B208: SP | Auto | Face Care | C208: Face Care | D208: Enabled | E208: AG | Vitamin C Serum | F208: Sponsored Products | G208: close-match | H208: AUTO | I208: vit c face serum dermatologist tested | J208: SKN-001 | K208: Top of Search | L208: 97 | M208: 0 | N208: =IF(L208=0,"",M208/L208) -> 0 | O208: =IF(M208=0,"",P208/M208) | P208: 0 | Q208: 0 | R208: 0 | S208: 0 | T208: =IF(Q208=0,"",P208/Q208) | U208: =IF(P208=0,"",Q208/P208) | V208: =IF(M208=0,"",R208/M208) | W208: 11 | X208: INR | Y208: India | AA208: =IF(OR(A208<DATE(2026,9,1),A208>DATE(2026,9,28)),"Check Date",INT((A208-DATE(2026,9,1))/7)+1) -> 1 | AB208: =IF(OR(AD208="",AE208="",AF208=""),"",S208*(AD208-AE208-AF208)-P208) -> 0 | AC208: =IF(P208<0,"Review",IF(OR(AD208="",AE208="",AF208=""),"Cost missing",IF(P208=0,"No Spend",IF(Q208=0,"No Sales",IF(P208/Q208<AG208,"Profitable","Losing"))))) -> No Spend | AD208: =IFERROR(VLOOKUP(J208,Product_lookup!$A:$G,5,FALSE),"") -> 599 | AE208: =IFERROR(VLOOKUP(J208,Product_lookup!$A:$G,6,FALSE),"") -> 216 | AF208: =IFERROR(VLOOKUP(J208,Product_lookup!$A:$G,7,FALSE),"") -> 144 | AG208: =IFERROR((AD208-AE208-AF208)/AD208,"") -> 0.39899833
A209: 46268 | B209: SP | Auto | Face Care | C209: Face Care | D209: Enabled | E209: AG | Vitamin C Serum | F209: Sponsored Products | G209: close-match | H209: AUTO | I209: face serum vitamin c pack of 2 | J209: SKN-001 | K209: Top of Search | L209: 216 | M209: 2 | N209: =IF(L209=0,"",M209/L209) -> 0.0092592593 | O209: =IF(M209=0,"",P209/M209) -> 11.5 | P209: 23 | Q209: 0 | R209: 0 | S209: 0 | T209: =IF(Q209=0,"",P209/Q209) | U209: =IF(P209=0,"",Q209/P209) -> 0 | V209: =IF(M209=0,"",R209/M209) -> 0 | W209: 11.5 | X209: INR | Y209: India | AA209: =IF(OR(A209<DATE(2026,9,1),A209>DATE(2026,9,28)),"Check Date",INT((A209-DATE(2026,9,1))/7)+1) -> 1 | AB209: =IF(OR(AD209="",AE209="",AF209=""),"",S209*(AD209-AE209-AF209)-P209) -> -23 | AC209: =IF(P209<0,"Review",IF(OR(AD209="",AE209="",AF209=""),"Cost missing",IF(P209=0,"No Spend",IF(Q209=0,"No Sales",IF(P209/Q209<AG209,"Profitable","Losing"))))) -> No Sales | AD209: =IFERROR(VLOOKUP(J209,Product_lookup!$A:$G,5,FALSE),"") -> 599 | AE209: =IFERROR(VLOOKUP(J209,Product_lookup!$A:$G,6,FALSE),"") -> 216 | AF209: =IFERROR(VLOOKUP(J209,Product_lookup!$A:$G,7,FALSE),"") -> 144 | AG209: =IFERROR((AD209-AE209-AF209)/AD209,"") -> 0.39899833
A210: 46268 | B210: SP | Auto | Face Care | C210: Face Care | D210: Enabled | E210: AG | Niacinamide Serum | F210: Sponsored Products | G210: substitutes | H210: AUTO | I210: botanica nine niacinamide serum | J210: SKN-002 | K210: Top of Search | L210: 395 | M210: 4 | N210: =IF(L210=0,"",M210/L210) -> 0.010126582 | O210: =IF(M210=0,"",P210/M210) -> 13 | P210: 52 | Q210: 0 | R210: 0 | S210: 0 | T210: =IF(Q210=0,"",P210/Q210) | U210: =IF(P210=0,"",Q210/P210) -> 0 | V210: =IF(M210=0,"",R210/M210) -> 0 | W210: 13 | X210: INR | Y210: India | AA210: =IF(OR(A210<DATE(2026,9,1),A210>DATE(2026,9,28)),"Check Date",INT((A210-DATE(2026,9,1))/7)+1) -> 1 | AB210: =IF(OR(AD210="",AE210="",AF210=""),"",S210*(AD210-AE210-AF210)-P210) -> -52 | AC210: =IF(P210<0,"Review",IF(OR(AD210="",AE210="",AF210=""),"Cost missing",IF(P210=0,"No Spend",IF(Q210=0,"No Sales",IF(P210/Q210<AG210,"Profitable","Losing"))))) -> No Sales | AD210: =IFERROR(VLOOKUP(J210,Product_lookup!$A:$G,5,FALSE),"") -> 549 | AE210: =IFERROR(VLOOKUP(J210,Product_lookup!$A:$G,6,FALSE),"") -> 192 | AF210: =IFERROR(VLOOKUP(J210,Product_lookup!$A:$G,7,FALSE),"") -> 139 | AG210: =IFERROR((AD210-AE210-AF210)/AD210,"") -> 0.39708561
A211: 46268 | B211: SP | Auto | Face Care | C211: Face Care | D211: Enabled | E211: AG | Niacinamide Serum | F211: Sponsored Products | G211: substitutes | H211: AUTO | I211: pureroots niacinamide 10% serum | J211: SKN-002 | K211: Rest of Search | L211: 191 | M211: 0 | N211: =IF(L211=0,"",M211/L211) -> 0 | O211: =IF(M211=0,"",P211/M211) | P211: 0 | Q211: 0 | R211: 0 | S211: 0 | T211: =IF(Q211=0,"",P211/Q211) | U211: =IF(P211=0,"",Q211/P211) | V211: =IF(M211=0,"",R211/M211) | W211: 12 | X211: INR | Y211: India | AA211: =IF(OR(A211<DATE(2026,9,1),A211>DATE(2026,9,28)),"Check Date",INT((A211-DATE(2026,9,1))/7)+1) -> 1 | AB211: =IF(OR(AD211="",AE211="",AF211=""),"",S211*(AD211-AE211-AF211)-P211) -> 0 | AC211: =IF(P211<0,"Review",IF(OR(AD211="",AE211="",AF211=""),"Cost missing",IF(P211=0,"No Spend",IF(Q211=0,"No Sales",IF(P211/Q211<AG211,"Profitable","Losing"))))) -> No Spend | AD211: =IFERROR(VLOOKUP(J211,Product_lookup!$A:$G,5,FALSE),"") -> 549 | AE211: =IFERROR(VLOOKUP(J211,Product_lookup!$A:$G,6,FALSE),"") -> 192 | AF211: =IFERROR(VLOOKUP(J211,Product_lookup!$A:$G,7,FALSE),"") -> 139 | AG211: =IFERROR((AD211-AE211-AF211)/AD211,"") -> 0.39708561
A212: 46268 | B212: SP | Auto | Face Care | C212: Face Care | D212: Enabled | E212: AG | Gel Moisturizer | F212: Sponsored Products | G212: close-match | H212: AUTO | I212: oil free moisturizer for men | J212: SKN-005 | K212: Rest of Search | L212: 186 | M212: 1 | N212: =IF(L212=0,"",M212/L212) -> 0.0053763441 | O212: =IF(M212=0,"",P212/M212) -> 7.75 | P212: 7.75 | Q212: 0 | R212: 0 | S212: 0 | T212: =IF(Q212=0,"",P212/Q212) | U212: =IF(P212=0,"",Q212/P212) -> 0 | V212: =IF(M212=0,"",R212/M212) -> 0 | W212: 12 | X212: INR | Y212: India | AA212: =IF(OR(A212<DATE(2026,9,1),A212>DATE(2026,9,28)),"Check Date",INT((A212-DATE(2026,9,1))/7)+1) -> 1 | AB212: =IF(OR(AD212="",AE212="",AF212=""),"",S212*(AD212-AE212-AF212)-P212) -> -7.75 | AC212: =IF(P212<0,"Review",IF(OR(AD212="",AE212="",AF212=""),"Cost missing",IF(P212=0,"No Spend",IF(Q212=0,"No Sales",IF(P212/Q212<AG212,"Profitable","Losing"))))) -> No Sales | AD212: =IFERROR(VLOOKUP(J212,Product_lookup!$A:$G,5,FALSE),"") -> 399 | AE212: =IFERROR(VLOOKUP(J212,Product_lookup!$A:$G,6,FALSE),"") -> 148 | AF212: =IFERROR(VLOOKUP(J212,Product_lookup!$A:$G,7,FALSE),"") -> 126 | AG212: =IFERROR((AD212-AE212-AF212)/AD212,"") -> 0.31328321
A213: 46268 | B213: SP | Auto | Face Care | C213: Face Care | D213: Enabled | E213: AG | Gel Moisturizer | F213: Sponsored Products | G213: loose-match | H213: AUTO | I213: face cream wholesale | J213: SKN-005 | K213: Top of Search | L213: 339 | M213: 2 | N213: =IF(L213=0,"",M213/L213) -> 0.005899705 | O213: =IF(M213=0,"",P213/M213) -> 11.88 | P213: 23.76 | Q213: 0 | R213: 0 | S213: 0 | T213: =IF(Q213=0,"",P213/Q213) | U213: =IF(P213=0,"",Q213/P213) -> 0 | V213: =IF(M213=0,"",R213/M213) -> 0 | W213: 12.5 | X213: INR | Y213: India | AA213: =IF(OR(A213<DATE(2026,9,1),A213>DATE(2026,9,28)),"Check Date",INT((A213-DATE(2026,9,1))/7)+1) -> 1 | AB213: =IF(OR(AD213="",AE213="",AF213=""),"",S213*(AD213-AE213-AF213)-P213) -> -23.76 | AC213: =IF(P213<0,"Review",IF(OR(AD213="",AE213="",AF213=""),"Cost missing",IF(P213=0,"No Spend",IF(Q213=0,"No Sales",IF(P213/Q213<AG213,"Profitable","Losing"))))) -> No Sales | AD213: =IFERROR(VLOOKUP(J213,Product_lookup!$A:$G,5,FALSE),"") -> 399 | AE213: =IFERROR(VLOOKUP(J213,Product_lookup!$A:$G,6,FALSE),"") -> 148 | AF213: =IFERROR(VLOOKUP(J213,Product_lookup!$A:$G,7,FALSE),"") -> 126 | AG213: =IFERROR((AD213-AE213-AF213)/AD213,"") -> 0.31328321
A214: 46268 | B214: SP | Auto | Face Care | C214: Face Care | D214: Enabled | E214: AG | Sunscreen Spf 50 | F214: Sponsored Products | G214: substitutes | H214: AUTO | I214: pureroots sunscreen | J214: SKN-006 | K214: Rest of Search | L214: 413 | M214: 2 | N214: =IF(L214=0,"",M214/L214) -> 0.004842615 | O214: =IF(M214=0,"",P214/M214) -> 5.13 | P214: 10.26 | Q214: 0 | R214: 0 | S214: 0 | T214: =IF(Q214=0,"",P214/Q214) | U214: =IF(P214=0,"",Q214/P214) -> 0 | V214: =IF(M214=0,"",R214/M214) -> 0 | W214: 9 | X214: INR | Y214: India | AA214: =IF(OR(A214<DATE(2026,9,1),A214>DATE(2026,9,28)),"Check Date",INT((A214-DATE(2026,9,1))/7)+1) -> 1 | AB214: =IF(OR(AD214="",AE214="",AF214=""),"",S214*(AD214-AE214-AF214)-P214) -> -10.26 | AC214: =IF(P214<0,"Review",IF(OR(AD214="",AE214="",AF214=""),"Cost missing",IF(P214=0,"No Spend",IF(Q214=0,"No Sales",IF(P214/Q214<AG214,"Profitable","Losing"))))) -> No Sales | AD214: =IFERROR(VLOOKUP(J214,Product_lookup!$A:$G,5,FALSE),"") -> 449 | AE214: =IFERROR(VLOOKUP(J214,Product_lookup!$A:$G,6,FALSE),"") -> 162 | AF214: =IFERROR(VLOOKUP(J214,Product_lookup!$A:$G,7,FALSE),"") -> 130 | AG214: =IFERROR((AD214-AE214-AF214)/AD214,"") -> 0.34966592
A215: 46268 | B215: SP | Auto | Face Care | C215: Face Care | D215: Enabled | E215: AG | Sunscreen Spf 50 | F215: Sponsored Products | G215: loose-match | H215: AUTO | I215: sunscreen for dry skin | J215: SKN-006 | K215: Product Pages | L215: 151 | M215: 1 | N215: =IF(L215=0,"",M215/L215) -> 0.0066225166 | O215: =IF(M215=0,"",P215/M215) -> 7.64 | P215: 7.64 | Q215: 449 | R215: 1 | S215: 1 | T215: =IF(Q215=0,"",P215/Q215) -> 0.01701559 | U215: =IF(P215=0,"",Q215/P215) -> 58.769634 | V215: =IF(M215=0,"",R215/M215) -> 1 | W215: 12.5 | X215: INR | Y215: India | AA215: =IF(OR(A215<DATE(2026,9,1),A215>DATE(2026,9,28)),"Check Date",INT((A215-DATE(2026,9,1))/7)+1) -> 1 | AB215: =IF(OR(AD215="",AE215="",AF215=""),"",S215*(AD215-AE215-AF215)-P215) -> 149.36 | AC215: =IF(P215<0,"Review",IF(OR(AD215="",AE215="",AF215=""),"Cost missing",IF(P215=0,"No Spend",IF(Q215=0,"No Sales",IF(P215/Q215<AG215,"Profitable","Losing"))))) -> Profitable | AD215: =IFERROR(VLOOKUP(J215,Product_lookup!$A:$G,5,FALSE),"") -> 449 | AE215: =IFERROR(VLOOKUP(J215,Product_lookup!$A:$G,6,FALSE),"") -> 162 | AF215: =IFERROR(VLOOKUP(J215,Product_lookup!$A:$G,7,FALSE),"") -> 130 | AG215: =IFERROR((AD215-AE215-AF215)/AD215,"") -> 0.34966592
A216: 46268 | B216: SP | Auto | Face Care | C216: Face Care | D216: Enabled | E216: AG | Face Wash | F216: Sponsored Products | G216: loose-match | H216: AUTO | I216: face wash for oily skin for women | J216: SKN-008 | K216: Product Pages | L216: 100 | M216: 0 | N216: =IF(L216=0,"",M216/L216) -> 0 | O216: =IF(M216=0,"",P216/M216) | P216: 0 | Q216: 0 | R216: 0 | S216: 0 | T216: =IF(Q216=0,"",P216/Q216) | U216: =IF(P216=0,"",Q216/P216) | V216: =IF(M216=0,"",R216/M216) | W216: 8 | X216: INR | Y216: India | AA216: =IF(OR(A216<DATE(2026,9,1),A216>DATE(2026,9,28)),"Check Date",INT((A216-DATE(2026,9,1))/7)+1) -> 1 | AB216: =IF(OR(AD216="",AE216="",AF216=""),"",S216*(AD216-AE216-AF216)-P216) -> 0 | AC216: =IF(P216<0,"Review",IF(OR(AD216="",AE216="",AF216=""),"Cost missing",IF(P216=0,"No Spend",IF(Q216=0,"No Sales",IF(P216/Q216<AG216,"Profitable","Losing"))))) -> No Spend | AD216: =IFERROR(VLOOKUP(J216,Product_lookup!$A:$G,5,FALSE),"") -> 299 | AE216: =IFERROR(VLOOKUP(J216,Product_lookup!$A:$G,6,FALSE),"") -> 114 | AF216: =IFERROR(VLOOKUP(J216,Product_lookup!$A:$G,7,FALSE),"") -> 107 | AG216: =IFERROR((AD216-AE216-AF216)/AD216,"") -> 0.26086957
A217: 46268 | B217: SP | Auto | Face Care | C217: Face Care | D217: Enabled | E217: AG | Face Wash | F217: Sponsored Products | G217: loose-match | H217: AUTO | I217: free sample face cream | J217: SKN-008 | K217: Top of Search | L217: 368 | M217: 0 | N217: =IF(L217=0,"",M217/L217) -> 0 | O217: =IF(M217=0,"",P217/M217) | P217: 0 | Q217: 0 | R217: 0 | S217: 0 | T217: =IF(Q217=0,"",P217/Q217) | U217: =IF(P217=0,"",Q217/P217) | V217: =IF(M217=0,"",R217/M217) | W217: 9 | X217: INR | Y217: India | AA217: =IF(OR(A217<DATE(2026,9,1),A217>DATE(2026,9,28)),"Check Date",INT((A217-DATE(2026,9,1))/7)+1) -> 1 | AB217: =IF(OR(AD217="",AE217="",AF217=""),"",S217*(AD217-AE217-AF217)-P217) -> 0 | AC217: =IF(P217<0,"Review",IF(OR(AD217="",AE217="",AF217=""),"Cost missing",IF(P217=0,"No Spend",IF(Q217=0,"No Sales",IF(P217/Q217<AG217,"Profitable","Losing"))))) -> No Spend | AD217: =IFERROR(VLOOKUP(J217,Product_lookup!$A:$G,5,FALSE),"") -> 299 | AE217: =IFERROR(VLOOKUP(J217,Product_lookup!$A:$G,6,FALSE),"") -> 114 | AF217: =IFERROR(VLOOKUP(J217,Product_lookup!$A:$G,7,FALSE),"") -> 107 | AG217: =IFERROR((AD217-AE217-AF217)/AD217,"") -> 0.26086957
...

Sheet Product_lookup
A1: SKU | B1: ASIN | C1: Product Name | D1: Sub-Category | E1: Selling Price (₹) | F1: Product Cost (₹) | G1: Amazon Fees (₹) | H1: Stock Status | I1: Rating | J1: Reviews
A2: SKN-001 | B2: B0F29326ML | C2: Auralis Vitamin C Face Serum 30ml | D2: Face Serum | E2: 599 | F2: 216 | G2: 144 | H2: In Stock | I2: 4.5 | J2: 2849
A3: SKN-002 | B3: B0F64LG2TJ | C3: Auralis Niacinamide 10% Face Serum 30ml | D3: Face Serum | E3: 549 | F3: 192 | G3: 139 | H3: In Stock | I3: 4 | J3: 1762
A4: SKN-003 | B4: B0FF8CZ2KA | C4: Auralis Hyaluronic Acid Face Serum 30ml | D4: Face Serum | E4: 649 | F4: 234 | G4: 148 | H4: In Stock | I4: 4.5 | J4: 1122
A5: SKN-004 | B5: B0F7EDCMPB | C5: Auralis Retinol Night Cream 50g | D5: Night Cream | E5: 799 | F5: 272 | G5: 162 | H5: In Stock | I5: 4.1 | J5: 4750
A6: SKN-005 | B6: B0F3U2M7OS | C6: Auralis Oil-Free Gel Moisturiser 100g | D6: Moisturiser | E6: 399 | F6: 148 | G6: 126 | H6: In Stock | I6: 4.6 | J6: 2128
A7: SKN-006 | B7: B0F5AF3R09 | C7: Auralis Sunscreen SPF 50 PA++++ 50g | D7: Sunscreen | E7: 449 | F7: 162 | G7: 130 | H7: In Stock | I7: 4 | J7: 4281
A8: SKN-007 | B8: B0FFQUO6SB | C8: Auralis Tinted Sunscreen SPF 40 50g | D8: Sunscreen | E8: 549 | F8: 203 | G8: 139 | H8: In Stock | I8: 3.9 | J8: 2473
A9: SKN-008 | B9: B0FEGZGSYE | C9: Auralis Foaming Face Wash 150ml | D9: Face Wash | E9: 299 | F9: 114 | G9: 107 | H9: In Stock | I9: 3.9 | J9: 4252
A10: SKN-009 | B10: B0FBANND4Y | C10: Auralis Salicylic Acid Face Wash 100ml | D10: Face Wash | E10: 279 | F10: 106 | G10: 105 | H10: In Stock | I10: 4 | J10: 1746
A11: SKN-010 | B11: B0FZ0EMRVF | C11: Auralis Rose Water Toner 200ml | D11: Toner | E11: 249 | F11: 100 | G11: 102 | H11: In Stock | I11: 4.3 | J11: 3363
A12: SKN-011 | B12: B0FTVA0HIP | C12: Auralis Under Eye Cream 15g | D12: Eye Care | E12: 499 | F12: 180 | G12: 125 | H12: In Stock | I12: 4 | J12: 2813
A13: SKN-012 | B13: B0FGAD35L9 | C13: Auralis Clay Face Mask 100g | D13: Face Mask | E13: 379 | F13: 140 | G13: 114 | H13: In Stock | I13: 4 | J13: 4693
... A26: SKN-026 | B26: B0FQ61J0AC | C26: Auralis Bath Salt Scrub 250g | D26: Body Care | E26: 379 | F26: 140 | G26: 90 | H26: Discontinued | I26: 4 | J26: 310

Sheet Analysis
A1: Amazon PPC Analysis — Auralis Naturals
A2: Reporting period: 1–28 September 2026. Profit after ads is calculated only where SKU economics are available; records with missing SKU/cost are excluded from profit totals and called out below.
A4: C1. Campaign summary
A5: Campaign | B5: Spend (₹) | C5: Sales (₹) | D5: Orders | E5: ACOS | F5: ROAS | G5: Profit after ads (₹) | H5: Rows missing cost
A6: (Campaign missing) | B6: 118.85 | C6: 1396 | D6: 3 | E6: 0.085136103 | F6: 11.745898 | G6: 318.15 | H6: 0
A7: SP | Auto | Body & Hair | B7: 15368.21 | C7: 37629 | D7: 86 | E7: 0.40841399 | F7: 2.448496 | G7: -3765.21 | H7: 1
A8: SP | Auto | Face Care | B8: 20601.43 | C8: 41257 | D8: 85 | E8: 0.49934387 | F8: 2.002628 | G8: -6311.43 | H8: 0
A9: SP | Brand Defence | Exact | B9: 9259.88 | C9: 105902 | D9: 132 | E9: 0.087438198 | F9: 11.436649 | G9: 18190.28 | H9: 51
A10: SP | Manual | Body Care | Exact | B10: 16976.15 | C10: 46206 | D10: 134 | E10: 0.36740142 | F10: 2.7218186 | G10: -3972.65 | H10: 1
A11: SP | Manual | Face Serums | Broad | B11: 12651.35 | C11: 40884 | D11: 60 | E11: 0.30944502 | F11: 3.2315919 | G11: 3941.65 | H11: 0
A12: SP | Manual | Face Serums | Exact | B12: 32417.17 | C12: 88116 | D12: 121 | E12: 0.36789198 | F12: 2.7181892 | G12: 4401.07 | H12: 1
A13: SP | Manual | Hair Care | Phrase | B13: 10362.29 | C13: 19248 | D13: 40 | E13: 0.53835671 | F13: 1.8575045 | G13: -3816.29 | H13: 0
A14: SP | Manual | Lips & Eyes | Exact | B14: 14632.23 | C14: 53031 | D14: 150 | E14: 0.27591843 | F14: 3.6242596 | G14: 1564.77 | H14: 1
A15: SP | Manual | Masks & Gels | Broad | B15: 2983.76 | C15: 4905 | D15: 14 | E15: 0.60830989 | F15: 1.643899 | G15: -1636.76 | H15: 0
A16: SP | Manual | Skincare Essentials | Broad | B16: 12259.85 | C16: 31337 | D16: 91 | E16: 0.39122603 | F16: 2.5560672 | G16: -3421.19 | H16: 1
A17: SP | Manual | Sunscreen | Phrase | B17: 8723.67 | C17: 19162 | D17: 35 | E17: 0.45525885 | F17: 2.1965526 | G17: -1707.67 | H17: 0
A18: SP | Product Targeting | Competitors | B18: 6016.81 | C18: 4790 | D18: 10 | E18: 1.256119 | F18: 0.79610292 | G18: -4273.81 | H18: 0
A20: C2. Match-type analysis
A21: Match Type | B21: Spend (₹) | C21: Sales (₹) | D21: Orders | E21: ACOS | F21: ROAS | G21: Profit after ads (₹) | H21: Rows missing cost | J21: Placement | K21: Spend (₹) | L21: Sales (₹) | M21: Orders | N21: ACOS | O21: ROAS | P21: Profit after ads (₹) | Q21: Rows missing cost
A22: AUTO | B22: 35969.64 | C22: 78886 | D22: 171 | E22: 0.45596988 | F22: 2.1931273 | G22: -10076.64 | H22: 1 | J22: Product Pages | K22: 34993.87 | L22: 97437 | M22: 207 | N22: 0.35914355 | O22: 2.784402 | P22: -3055.48 | Q22: 18
A23: BROAD | B23: 27894.96 | C23: 77126 | D23: 165 | E23: 0.36168037 | F23: 2.7648722 | G23: -1116.3 | H23: 1 | J23: Rest of Search | K23: 56866.21 | L23: 180536 | M23: 341 | N23: 0.31498543 | O23: 3.17475 | P23: 1287.92 | Q23: 20
A24: EXACT | B24: 73404.28 | C24: 294651 | D24: 540 | E24: 0.24912279 | F24: 4.0140847 | G24: 20501.62 | H24: 54 | J24: Top of Search | K24: 70511.57 | L24: 215890 | M24: 413 | N24: 0.32660878 | O24: 3.061767 | P24: 1278.47 | Q24: 18
A25: PHRASE | B25: 19085.96 | C25: 38410 | D25: 75 | E25: 0.49690081 | F25: 2.0124741 | G25: -5523.96 | H25: 0
A26: PRODUCT | B26: 6016.81 | C26: 4790 | D26: 10 | E26: 1.256119 | F26: 0.79610292 | G26: -4273.81 | H26: 0
A29: C3. Top 10 search terms by spend with ZERO orders
A30: Search terms normalized to lowercase and trimmed; aggregated across the reporting period. Includes positive spend and exactly zero total orders.
A31: Rank | B31: Search Term | C31: Spend (₹) | D31: Clicks | E31: Orders | F31: Sales (₹)
A32: 1 | B32: niacinamide serum | C32: 5911.46 | D32: 556 | E32: 0 | F32: 0
A33: 2 | B33: dandruff shampoo for dandruff | C33: 858.28 | D33: 72 | E33: 0 | F33: 0
A34: 3 | B34: shampoo for dandruff | C34: 840.6 | D34: 90 | E34: 0 | F34: 0
A35: 4 | B35: skin care course online | C35: 814.41 | D35: 106 | E35: 0 | F35: 0
A36: 5 | B36: b0xanrgqoz | C36: 767.48 | D36: 88 | E36: 0 | F36: 0
A37: 6 | B37: dermatologist near me | C37: 606.17 | D37: 60 | E37: 0 | F37: 0
A38: 7 | B38: face cream wholesale | C38: 575.17 | D38: 77 | E38: 0 | F38: 0
A39: 8 | B39: spf 50 sunscreen for face | C39: 562.61 | D39: 60 | E39: 0 | F39: 0
A40: 9 | B40: hyaluronic serum for sensitive skin | C40: 542.44 | D40: 31 | E40: 0 | F40: 0
A41: 10 | B41: retinol cream combo | C41: 535.04 | D41: 38 | E41: 0 | F41: 0
A44: C4. Top 10 search terms by profit after ads
A45: Profit is aggregated across campaigns for each normalized search term. Rows with missing SKU economics are excluded from profit calculation; known-cost row coverage is shown.
A46: Rank | B46: Search Term | C46: Profit after ads (₹) | D46: Spend (₹) | E46: Sales (₹) | F46: Rows with known cost | G46: Rows with missing cost
A47: 1 | B47: hyaluronic serum | C47: 6964.73 | D47: 4851.51 | E47: 29205 | F47: 21 | G47: 1
A48: 2 | B48: hyaluronic acid serum | C48: 4824.96 | D48: 5321.04 | E48: 24662 | F48: 27 | G48: 0
A49: 3 | B49: auralis vitamin c serum | C49: 4291.59 | D49: 966.41 | E49: 13178 | F49: 17 | G49: 0
A50: 4 | B50: under eye cream | C50: 4105.3 | D50: 1714.7 | E50: 14970 | F50: 20 | G50: 0
A51: 5 | B51: auralis face serum vitamin c | C51: 3151.11 | D51: 980.35 | E51: 11980 | F51: 15 | G51: 1
A52: 6 | B52: auralis sunscreen spf 50 | C52: 2890.39 | D52: 720.61 | E52: 10327 | F52: 19 | G52: 0
A53: 7 | B53: auralis naturals vitamin c serum | C53: 2500.19 | D53: 606.81 | E53: 7787 | F53: 14 | G53: 0
A54: 8 | B54: niacinamide 10% serum under 300 | C54: 1980.48 | D54: 853.52 | E54: 7137 | F54: 19 | G54: 0
A55: 9 | B55: auralis vit c face serum | C55: 1957.87 | D55: 432.13 | E55: 5990 | F55: 12 | G55: 0
A56: 10 | B56: auralis naturals | C56: 1876.55 | D56: 838.6 | E56: 6289 | F56: 18 | G56: 6
A59: C5. Weekly trend
A60: Weeks follow Seller_Notes: Week 1 = Sep 1–7; Week 2 = Sep 8–14; Week 3 = Sep 15–21; Week 4 = Sep 22–28.
A61: Week | B61: Dates | C61: Spend (₹) | D61: Sales (₹) | E61: Orders | F61: ACOS | G61: CVR
A62: Week 1 | B62: 1–7 Sep | C62: 37578.92 | D62: 114493 | E62: 244 | F62: 0.32822024 | G62: 0.056665118
A63: Week 2 | B63: 8–14 Sep | C63: 38546.13 | D63: 127310 | E63: 248 | F63: 0.30277378 | G63: 0.058545798
A64: Week 3 | B64: 15–21 Sep | C64: 42275.68 | D64: 142153 | E64: 265 | F64: 0.29739562 | G64: 0.056418991
A65: Week 4 | B65: 22–28 Sep | C65: 43970.92 | D65: 109907 | E65: 204 | F65: 0.40007388 | G65: 0.044155844
A72: C6. Search terms appearing in more than one campaign (stretch)
A73: Terms are case-insensitive. All campaigns in the report are included; the count is the number of distinct campaign names.
A74: Rank | B74: Search Term | C74: Campaign Count | D74: Campaigns | E74: Combined Spend (₹) | F74: Combined Sales (₹) | G74: Combined Orders
A75: 1 | B75: body lotion | C75: 2 | D75: SP | Auto | Body & Hair; SP | Manual | Body Care | Exact | E75: 6390.5 | F75: 8980 | G75: 18
A76: 2 | B76: niacinamide serum | C76: 3 | D76: SP | Auto | Face Care; SP | Manual | Face Serums | Broad; SP | Manual | Face Serums | Exact | E76: 5911.46 | F76: 0 | G76: 0
A77: 3 | B77: hyaluronic acid serum | C77: 2 | D77: SP | Manual | Face Serums | Broad; SP | Manual | Face Serums | Exact | E77: 5321.04 | F77: 24662 | G77: 35
A78: 4 | B78: vitamin c serum | C78: 3 | D78: SP | Auto | Face Care; SP | Manual | Face Serums | Broad; SP | Manual | Face Serums | Exact | E78: 5286.13 | F78: 11381 | G78: 17
A79: 5 | B79: hyaluronic serum | C79: 2 | D79: SP | Manual | Face Serums | Broad; SP | Manual | Face Serums | Exact | E79: 4851.51 | F79: 29205 | G79: 40
A80: 6 | B80: gel moisturizer | C80: 2 | D80: SP | Auto | Face Care; SP | Manual | Skincare Essentials | Broad | E80: 4127.99 | F80: 7581 | G80: 19
A81: 7 | B81: vit c face serum | C81: 3 | D81: SP | Auto | Face Care; SP | Manual | Face Serums | Broad; SP | Manual | Face Serums | Exact | E81: 2864.44 | F81: 7188 | G81: 11
A82: 8 | B82: sunscreen | C82: 2 | D82: SP | Auto | Face Care; SP | Manual | Sunscreen | Phrase | E82: 2476.44 | F82: 898 | G82: 2
A83: 9 | B83: body wash | C83: 2 | D83: SP | Auto | Body & Hair; SP | Manual | Body Care | Exact | E83: 2410.28 | F83: 5933 | G83: 16
A84: 10 | B84: shea body lotion | C84: 2 | D84: SP | Auto | Body & Hair; SP | Manual | Body Care | Exact | E84: 2040.94 | F84: 2694 | G84: 6
A85: 11 | B85: 10% niacinamide face serum | C85: 3 | D85: SP | Auto | Face Care; SP | Manual | Face Serums | Broad; SP | Manual | Face Serums | Exact | E85: 1980.26 | F85: 8235 | G85: 10
A86: 12 | B86: shower gel | C86: 2 | D86: SP | Auto | Body & Hair; SP | Manual | Body Care | Exact | E86: 1893.82 | F86: 3839 | G86: 10
... A114: 40 | B114: spf 50 sunscreen for face | C114: 2 | D114: SP | Auto | Face Care; SP | Manual | Sunscreen | Phrase | E114: 562.61 | F114: 0 | G114: 0
A115: 41 | C115: 4 | D115: SP | Auto | Face Care; SP | Manual | Face Serums | Broad; SP | Manual | Face Serums | Exact; SP | Manual | Lips & Eyes | Exact | E115: 562.15 | F115: 2494 | G115: 6
A116: 42 | B116: oil free moisturizer | C116: 2 | D116: SP | Auto | Face Care; SP | Manual | Skincare Essentials | Broad | E116: 554.97 | F116: 3591 | G116: 8
A117: 43 | B117: hyaluronic serum for sensitive skin | C117: 2 | D117: SP | Manual | Face Serums | Broad; SP | Manual | Face Serums | Exact | E117: 542.44 | F117: 0 | G117: 0
A118: 44 | B118: face cream for dogs | C118: 4 | D118: SP | Auto | Face Care; SP | Manual | Face Serums | Broad; SP | Manual | Masks & Gels | Broad; SP | Manual | Skincare Essentials | Broad | E118: 521.81 | F118: 0 | G118: 0
A119: 45 | B119: gel moisturizer dermatologist tested | C119: 2 | D119: SP | Auto | Face Care; SP | Manual | Skincare Essentials | Broad | E119: 508.69 | F119: 798 | G119: 2
A120: 46 | B120: niacinamide serum for teenagers | C120: 3 | D120: SP | Auto | Face Care; SP | Manual | Face Serums | Broad; SP | Manual | Face Serums | Exact | E120: 498.45 | F120: 0 | G120: 0
A121: 47 | B121: anti dandruff shampoo paraben free | C121: 2 | D121: SP | Auto | Body & Hair; SP | Manual | Hair Care | Phrase | E121: 454.58 | F121: 5148 | G121: 12
A122: 48 | B122: shea body lotion paraben free | C122: 2 | D122: SP | Auto | Body & Hair; SP | Manual | Body Care | Exact | E122: 450.21 | F122: 4939 | G122: 11
A123: 49 | B123: face serum hyaluronic for daily use | C123: 2 | D123: SP | Manual | Face Serums | Broad; SP | Manual | Face Serums | Exact | E123: 450.09 | F123: 1298 | G123: 2
A124: 50 | B124: empty dropper bottle | C124: 3 | D124: SP | Auto | Face Care; SP | Manual | Face Serums | Broad; SP | Manual | Skincare Essentials | Broad | E124: 432.23 | F124: 0 | G124: 0
A125: 51 | B125: sunscreen for dry skin | C125: 2 | D125: SP | Auto | Face Care; SP | Manual | Sunscreen | Phrase | E125: 409.16 | F125: 2694 | G125: 5
A126: 52 | B126: hair colour dye black | C126: 2 | D126: SP | Auto | Body & Hair; SP | Manual | Hair Care | Phrase | E126: 407.6 | F126: 0 | G126: 0
A127: 53 | B127: face serum vitamin c price | C127: 3 | D127: SP | Auto | Face Care; SP | Manual | Face Serums | Broad; SP | Manual | Face Serums | Exact | E127: 402.42 | F127: 1198 | G127: 2
... A223: 149 | B223: face toner with vitamin e | C223: 2 | D223: SP | Auto | Face Care; SP | Manual | Skincare Essentials | Broad | E223: -35.78 | F223: 0 | G223: 0
A225: Data coverage / interpretation notes
A226: Profit-after-ads figures exclude 56 rows with missing SKU economics (blank SKU or SKN-024 not found in Product_Master); no costs were guessed.
A227: Week 4 ACOS rose to 40.01% from 29.74% in Week 3 as spend increased and attributed sales/orders and CVR fell. Weekly ACOS: Week 1 32.82%, Week 2 30.28%, Week 3 29.74%, Week 4 40.01%.

Sheet Action_List
A1: Action_List
A2: One row per recommended action. Fill in the yellow cells. Delete the example row.
A4: # | B4: Campaign | C4: Search Term | D4: Product SKU | E4: Rule (R1-R4) | F4: Action | G4: Clicks | H4: Orders | I4: Spend (₹) | J4: ACOS | K4: Break-even ACOS | L4: Est. saving (₹) | M4: Reason / note
A5: 1 | B5: SP | Auto | Face Care | C5: dermavault face serum vitamin c | D5: SKN-001 | E5: R4 | F5: Negate (add as negative keyword) | G5: 23 | H5: 0 | I5: 299.16 | K5: 0.39899833 | M5: Competitor-brand term with campaign spend of at least ₹100; R4 takes priority over R1–R3.
A6: 2 | B6: SP | Manual | Hair Care | Phrase | C6: mistral herbals onion hair oil | D6: SKN-021 | E6: R4 | F6: Negate (add as negative keyword) | G6: 25 | H6: 0 | I6: 270.88 | K6: 0.31328321 | M6: Competitor-brand term with campaign spend of at least ₹100; R4 takes priority over R1–R3.
A7: 3 | B7: SP | Auto | Face Care | C7: botanica nine niacinamide serum | D7: SKN-002 | E7: R4 | F7: Negate (add as negative keyword) | G7: 27 | H7: 0 | I7: 256.62 | K7: 0.39708561 | M7: Competitor-brand term with campaign spend of at least ₹100; R4 takes priority over R1–R3.
A8: 4 | B8: SP | Auto | Body & Hair | C8: skinlore hair oil for hair growth | D8: SKN-021 | E8: R4 | F8: Negate (add as negative keyword) | G8: 25 | H8: 9 | I8: 194.05 | J8: 0.054037872 | K8: 0.31328321 | M8: Competitor-brand term with campaign spend of at least ₹100; R4 takes priority over R1–R3.
A9: 5 | B9: SP | Manual | Face Serums | Broad | C9: pureroots vit c face serum | D9: SKN-001 | E9: R4 | F9: Negate (add as negative keyword) | G9: 9 | H9: 0 | I9: 138.75 | K9: 0.39899833 | M9: Competitor-brand term with campaign spend of at least ₹100; R4 takes priority over R1–R3.
A10: 6 | B10: SP | Manual | Face Serums | Broad | C10: veluna face serum hyaluronic | D10: SKN-003 | E10: R4 | F10: Negate (add as negative keyword) | G10: 8 | H10: 0 | I10: 111 | K10: 0.41140216 | M10: Competitor-brand term with campaign spend of at least ₹100; R4 takes priority over R1–R3.
A11: 7 | B11: SP | Auto | Body & Hair | C11: veluna shea body lotion | D11: SKN-017 | E11: R4 | F11: Negate (add as negative keyword) | G11: 8 | H11: 0 | I11: 102.18 | K11: 0.31848552 | M11: Competitor-brand term with campaign spend of at least ₹100; R4 takes priority over R1–R3.
